Workbook
Name Database1: #REF!
Name Database1: #REF!
Name 금융: #REF!
Name 금융: 상해지점!$AN$149:$AN$150
Name 금융: '(1)예금승인내역'!$AM$149:$AM$150

Sheet 외화예금일일가이드라인

Sheet 승인절차
N3: 1. 신청세부내용 확인. (고시금리, 가산금리, 최종금리, 상품, 기간 등)
N4: 2. 결재자 배정에 1차 결재자 체크, 부장님 체크 -> 후결 체크
N5: 3. 심사의견에 승인조건 및 심사의견 작성 후 심사의견 저장
N6: 4. 오른쪽 상단에 결재 누르고 <승인> 누르면 끝! (승인완료가 아닌 승인)
N7: 반려하는 경우 결재 <불승인> 클릭하면 됨!

Sheet (1)규정
A1: 내규 - 국제금융/외국환 - 외국환업무지침 - 제8장 외화예금
A2: 3. 우대금리 적용
B3: 기본이율보다 우대하고자 할 경우에는 다음 각 호의 주무부서장 승인을 득하여 적용한다. 다만, 외화종합통장에 의한 우대이율 적용의 경우와 중복될 때에는 높은 이율 하나만을 적용한다.
B4: 가. 원금이 미화 1백만불 상당액 미만인 경우 : 외환사업부장
B5: 나. 원금이 미화 1백만불 상당액 이상인 경우 : 자금부장
A7: ※ 기본이율 : 넥스피아(7452:금리주요정보조회)
A10: 나. 지급준비율
A11: (1) 만기 1개월 이상 외화정기예금, 만기 30일 이상 외화양도성예금증서 및 만기 6개월 이상 외화정기적금 : 2%
A12: (2) 기타예금 : 7%
A16: 내규 - 전반관리 - 종합수익관리지침
A18: 제1장 총 칙
A19: 1. 목 적
B20: 종합수익관리 업무란 전행의 재무적 지표인 손익을 관리회계에서 정의한 손익체계에 따라 조직.상품.고객별 등의 구분으로 상세하게 산출하는것으로
B21: 여.수신 금리 결정 및 조직별 성과평가, 고객별 수익성 분석 등을 통한 전략적 의사결정을 지원하는 것을 목적으로 한다.
A23: 2. 종합수익관리 기본원칙
B25: 종합수익관리의 기본원칙은 다음 각 호와 같다.
B26: 가. 자금원가 관리
B27: (1) 내부금리 결정방식은 만기대응내부(또는 시장)금리에 의한다.
B28: (2) 계산방법은 조달자금과 운용자금을 각각 계산하는 총액법으로 한다.
B29: (3) 자금원가관리 적용대상은 은행계정(신탁계정제외) 대차대조표를 보유한 모든 회계단위로 한다. 단, 조직단위 수익성 측정에 불필요하다고 판단되는 계정과목에 대해서는 제외할 수 있다.(2009.3.5 개정)
B30: 나. 업무원가 관리
B31: (1) 모든 투입자원을 활동으로 배분하여 원가를 계산한다.
B32: (2) 집계된 원가를 각 활동과 고객·상품과의 인과관계를 기준으로 배분한다.
B33: 다. 수익성 관리
B34: (1) 수익성관리 기간은 원칙적으로 회계연도와 같이 하되, 관리목적에 따라 월별, 분기별, 반기별 또는 임의기간으로 할 수 있다.
B35: (2) 관리회계 재무제표의 작성단위는 전행, 사업본부별, 영업점별, 회계단위부서별(총계정 원장 설치부서 또는 기타 필요부서)로 한다.
B36: (3) 계정과목은 원칙적으로 재무회계 계정과목을 준용하되, 내부관리목적상 별도의 계정과목을 신설할 수 있고, 재무제표의 계정체계 및 서식 등은 재무회계와 구분하여 주무부서장이 별도로 정하는 바에 따른다.
B37: (4) 수익성분석은 모든 상품을 대상으로 계좌별로 관리함을 원칙으로 한다. 단, 계좌가 구분되지 않는 항목은 조직별 이익관리실적표에 과목기준으로 계상한다.
A39: 3. 용어의 정의
B41: 이 지침에서 사용하는 용어의 정의는 다음 각 호와 같다.
B42: 가. 자금원가관리
B43: (1) 「내부금리」라 함은 본부(원화는 자금증권부, 외화는 국제금융부)와 각 회계단위간 조달 또는 운용한 자금에 대한 자금원가를 산출하기 위하여 적용되는 내부이전가격을 말한다(2009.3.5 개정)
B44: (2) 「내부이자」라 함은 내부금리에 의거 계산되는 보상 및 부담금액을 말한다.
B45: (3) 「내부이자 결산」이라 함은 은행 내부거래 자금의 보상 및 부담에 따른 내부이자 계산을 말한다.
B46: (4) 「만기대응내부금리」라 함은 여수신 상품의 만기에 대응하는 시장대표상품의 동일한 기간 시장수익률(시장기회비용)을 내부이전가격으로 하는 내부금리 결정방식을 말한다.
B47: (5) 「개별 만기대응내부금리」라 함은 신규시점의 일별 내부금리가 만기대응 되어 만기 또는 금리개정 전일까지 적용되는 내부금리를 말한다.
B48: (6) 「가중평균 만기대응내부금리」라 함은 만기 이전에 현금흐름이 있는 우대금리(P-rate)연동 여신상품에 적용하는데 원금이 현금흐름(회수) 시점별로 각각의 개별 만기대응내부금리를 구하고, 현금흐름의 금액과 기간 비중에 따라 금리를 가중평균 하는 내부금리를 말한다.
B49: (7) 「개별 만기대응시장금리」라 함은 신규시점의 일별 시장금리가 만기대응 되어 만기 또는 금리개정 전일까지 적용되는 시장금리를 말한다.
B50: (8) 「가중평균 만기대응시장금리」라 함은 만기 이전에 현금흐름이 있는 투자유가 증권에 적용하는데 원금이 현금흐름(회수) 시점별로 각각의 개별 만기대응시장금리를 구하고, 현금흐름의 금액과 기간 비중에 따라 금리를 가중평균 하는 시장금리를 말한다.
B51: (9) 「Core율에 의한 만기대응내부금리」라 함은 계좌가 있으나 만기가 없는 상품에 적용하는 것으로 Core율(월별실적 추세를 반영하여 일정부분 변동 없이 유지예상 되는 핵심)부분은 장기 내부금리를 비Core부분은 단기 내부금리를 적용하는 것을 말한다.
B52: (10) 「Pool법에 의한 만기대응내부금리」라 함은 계좌가 없는 상품에 적용하는 것으로 과목별로 대표적인 하나의 기간을 정하고(Pool법), 그 기간에 해당하는 내부금리를 적용하는 것을 말한다.
... B77: (8) 「수정총자산」이라 함은 해당조직의 자산과 부채를 합한 것의 1/2인데 이것은 해당 조직의 ROA산출에 분모로 활용된다.
A80: 제2장 자금원가관리
A81: 1. 내부금리
B83: 은행계정 내부금리는 다음과 같이 구분 관리한다.
B84: 가. 원화 내부금리
B85: 나. 외화 내부금리
A87: 2. 운영체계
B88: 가. 기간별 조정계수는 리스크관리협의회 심의를 득하여 결정한다.
B89: 나. 대표시장금리
B90: (1) 원화는 당행 신용등급에 적합한 금리를 사용하며 1일 Call금리, 3개월 금리는 CD금리, 6개월 이상은 금융채금리를 사용하며 금융투자협회의 평균수익율을 고시금리로 한다. 1개월금리는 1일 Call금리와 3개월 CD금리를 사용하여 산출하고, 2개월금리는 1개월 금리와 3개월 CD금리를 사용하여 산출한다.
B91: (2) 외화는 주요통화 중 USD, GBP, CHF, JPY, EUR는 Libor, AUD, CAD, NZD는 Deposit rate, 기타통화는 USD통화금리로 Tellerate 고시금리로 한다.(2013.06.01 개정)
B92: (3) 대표시장상품의 기간구분(2007.12.1 개정)
B93: (가) 원화는 1일, 1개월, 2개월, 3개월, 6개월, 1년, 2년, 3년, 5년, 10년, 20년
B94: (나) 외화는 1W(1주일) 및 1M(1개월) ~ 12M(12개월)은 Libor, Deposit rate를 적용한다.(2013.06.01 개정)
B95: 다. 조정계수는 대표시장금리에 기간구분에 따라 당행 채권의 시장가격 및 시장상황을 반영하여 조정되는 Spread를 말한다. 다만, 외화는 최근 조달한 기간별 외화차입 Spread의 평균 및 시장상황을 반영하여 기간별 Spread를 산출하며, 외화 기간별 Spread의 고시구간은 1주일, 1개월, 3개월, 6개월, 1년, 2년, 3년, 4년, 5년, 6년, 7년, 8년, 9년, 10년으로 한다.(2007.12.1개정, 2009.3.5 개정)
B96: 라. 조정계수 운영주기(2007.12.1 개정)
B97: (1) 원화 : 매일
B98: (2) 외화 : 1개월
B99: 마. 유동성프리미엄은 대출약정만기(여신기간)와 금리만기(금리변동주기) 차이에서 발생하는 자금 재조달위험으로 변동금리 대출 및 유가증권에만 적용하는 Spread를 말한다. 유동성프리미엄 Spread의 고시구간은 6개월, 1년, 2년, 3년, 4년, 5년 초과로 하고, 변동주기는 3개월, 6개월, 1년, 2년, 3년으로 한다.
A101: 3. 고 시
B103: 영업점에 고시하는 만기대응 내부금리표는 다음 각호와 같다.
B104: 가. 작성주기는 매 영업일로 한다.
B105: 나. 기간 구분은 만기수익률곡선에 의거 보간법으로 산출한 일단위로 한다.
B106: 다. 고시 단위는 소수점 4자리까지(5자리에서 반올림 0.0000%)로 한다.
B107: 라. 내부금리표는 매 영업일의 기간별 만기대응내부금리로 한다.
A109: 4. 내부금리 적용원칙
B110: 가. 계좌 및 만기에 따른 내부금리
B111: (1) 계좌와 만기가 있는 모든 상품은 개별 또는 가중평균 만기대응내부(또는 시장)금리를 적용한다.
B112: (2) 계좌는 있으나 만기가 없는 상품은 Core율에 의한 만기대응내부금리를 적용한다.
B113: (3) 계좌가 없는 상품은 과목별 Pool법에 의한 만기대응내부금리를 적용한다.
B114: 나. 금리유형에 따른 내부금리
B115: (1) 확정금리는 신규시점에 기간별 일일 만기대응내부(또는 시장)금리를 만기까지 적용한다.
B116: (2) 변동금리는 변동시점에 금리개정 기간에 해당하는 기간별 일일 만기대응내부금리와 금리변동시 적용하는 기준금리에 해당하는 기간 중 장기기간에 일정 스프레드를 가감하여 금리개정일마다 재 적용한다.
B117: (3) 일정한 변동주기없이 변동되는 우대금리(P-rate)연동 여신상품은 신규시점에 기간별 일일 만기대응내부금리를 적용하고, 우대금리(P-rate)가 변동되면 내부금리도 우대금리(P-rate)변동분 만큼 변동시켜 신규시점의 자금마진이 만기까지 유지되도록 한다.
B118: 다. 자금성격에 따른 내부금리
B119: (1) 당행 일반자금은 기간별 만기대응내부(또는 시장)금리를 적용한다.
B120: (2) 당행 외부에서 차입(수탁)되는 차입성자금은 차입금리를 내부금리로 적용한다.
B121: (3) 영업점 관리여신(Workout여신, 산업합리화여신 등)은 기간별 만기대응내부금리를 적용하되, 임직원대출, 직원임차보증금은 약정이율을 내부금리로 한다.
B122: (4) 정책성자금(유동성조절목적 자금, 금융기관 MMDA 등)은 기간별 만기대응내부금리 적용을 원칙으로 하되, 내부금리를 별도로 정할 수 있다. 다만, 정책내부금리는 리스크관리협의회의 심의를 득하여 결정한다.
A124: 5. 자금원가 계산방법 등
B125: 가. 자금원가 계산은 매월별로 한다.
B126: 나. 계산원칙
B127: (1) 계좌별 내부이자 산출을 원칙으로 하되, 비계좌 등은 과목별로 산출한다. 단, 역외계정은 제외한다.
B128: (2) 여수신상품 구분없이 만기가 같으면 동일한 내부금리를 적용한다.
B129: 다. 계산방법은 다음과 같이 하되 소수점 이하는 절사한다.
B130: (1) 계좌와 만기가 있는 경우
B131: (가) 차변계정 : 계좌별 월 가용평잔 × 신규일 개별 또는 가중평균 만기대응내부금리 × 해당일수 ÷ 365
B132: (나) 대변계정 : 계좌별 월가용평잔 × 신규일 개별 또는 가중평균 만기대응내부금리 × 해당일수 ÷ 365 × (1 - 지준율)
B133: (2) 계좌는 있으나 만기가 없는 경우와 비계좌인 경우
B134: (가) 차변계정 : 계좌별 월가용평잔 × 당월 월평균 기간별(또는 CORE율에 의한) 만기대응내부금리 × 해당일수 ÷ 365
B135: (나) 대변계정 : 계좌별 월가용평잔 × 최근 6개월 평균기간별(또는 CORE율에 의한) 만기대응내부금리 × 해당일수 ÷ 365 × (1 - 지준율) 단, 외화예수금은 당월 월평균 기간별 내부금리 사용
B136: 라. 외화는 외화 계좌별/과목별 월가용평잔을 말일자 매매기준율에 의거 원화로 환산하며, 년수는 360일로 한다.
... B157: (2) Position분(원화 B/S상 외화계정 조달부문과 운용부문의 차)과 외화계정 원화 계리분은 원화 내부금리로 적용한다.
A159: 6. 내부금리 유형별 세부사항
B160: 가. 개별 만기대응내부(또는 시장)금리는 신규시점에 건별로 만기대응 되어 만기 또는 금리 개정전일까지 적용되는 내부금리로 거치식예금(정기예금, CD, 표지어음, RP 등), 적립식예금, 만기일시상환 대출금, 매입외환, 사모사채, 투자유가증권 등에 적용된다.(2008.3.17 개정)
B161: 나. 가중평균 만기대응내부(또는 시장)금리는 만기 이전에 원금의 현금흐름(회수)이 있는 우대금리(P-rate)연동 여신상품에 적용하는 데, 현금흐름 시점별 각각의 내부(또는 시장)금리와 현금흐름의 금액 및 기간비중에 따라 금리를 가중평균하는 내부(또는 시장)금리로 신규시점의 기간별 만기대응내부(또는 시장)금리를 만기까지 적용한다.
B162: (1) 가중평균만기대응내부(또는)금리 산식은 {(t시점의 현금흐름원금 ×기간(t) ×각 현금흐름 시점(t)별 만기대응내부(또는시장)금리) ÷ ∑(각 현금흐름원금 ×기간(t))} 이다.
B163: (2) 우대금리적용 원금분할상환대출, 우대금리적용 원리금분할상환대출, 투자유가증권 등에 적용된다.
B164: 다. Core율에 의한 만기대응내부금리
...

Sheet (1)예금승인내역
B1: ※ 금리협의시 기준
B2: 1. 외화MMDA | F2: 2. 외화정기예금
B3: (1) ~1주 또는 통지예금 금리 참조하여 협의 | F3: (1) 3개월 이하 : 금리부운용(콜론) vs 비금리부운용(스왑) 비교 (단, 외화제규제비율 및 NIM감안)
F4: (2) 3개월 초과 : 되도록 금리부운용(대여금)으로 매칭
X5: 0.001776
G6: 상세내역 | M6: 외부 참조금리 | V6: 내부 참조금리 | AE6: 승인정보 | AL6: 메모란
I7: 기간 | M7: 타행외화예금금리 | O7: 은행간 운용금리 | V7: 종합수익관리시스템 | Z7: 비용 | AB7: BEP금리
A8: 순번 | B8: 상담일자 | C8: 영업점 | D8: 지점장 | E8: 담당자 | F8: 고객 | G8: 시작일자 | H8: 만기일자 | I8: 일수 | J8: 월수 | K8: 예금종류 | L8: 통화/금액 | M8: 평균 | N8: 최대(은행) | O8: Tenor | P8: SOFR | Q8: LIBOR | R8: 이자(MM) | T8: 비이자(FXSWAP) | V8: 내부금리 | W8: 지준비용 | X8: 자금마진 | Y8: 고시금리 | Z8: 자금원가 | AA8: NIS | AB8: 이자운용 | AC8: 비이자운용 | AD8: 협의금리 | AE8: 고시금리 | AF8: 우대금리 | AG8: 승인금리 | AH8: 승인일자 | AI8: 신청번호 | AJ8: 여부 | AK8: 매칭 운용거래 (비이자 / 이자)
A10: 1 | B10: 42583 | C10: 여의도지점 | D10: 계장 조수현 | F10: 키움자산운용 | G10: 42583 | H10: 42674 | I10: =H10-G10 -> 91 | J10: =TRUNC(I10/30,0) -> 3 | L10: 4 | Q10: 0.007591 | S10: 0.0084 | Y10: 0.005314 | AD10: 0.0065 | AE10: =IF(Y10="","",Y10) -> 0.005314 | AG10: =IF(AF10="","",AE10+AF10) | AJ10: =IF(AG10="","N","Y") -> N
A11: =IF(B11="","",IF((YEAR(B11)-YEAR(B10))=0,A10+1,1)) -> 2 | B11: 42586 | C11: 포항공단점 | D11: 계장 배인영 | F11: 개인 | G11: 42586 | H11: 42678 | I11: =H11-G11 -> 92 | J11: =TRUNC(I11/30,0) -> 3 | K11: 정기예금 | L11: 2.5 | Q11: 0.007776 | S11: 0.0084 | Y11: 0.005495 | AD11: 0.0065 | AE11: =IF(Y11="","",Y11) -> 0.005495 | AF11: 0.001505 | AG11: =IF(AF11="","",AE11+AF11) -> 0.007 | AJ11: =IF(AG11="","N","Y") -> Y
A12: =IF(B12="","",IF((YEAR(B12)-YEAR(B11))=0,A11+1,1)) -> 3 | B12: 42587 | C12: 강남영업부 | D12: 과장 이진아 | F12: 한전 | G12: 42587 | H12: 42618 | I12: =H12-G12 -> 31 | J12: =TRUNC(I12/30,0) -> 1 | K12: MMDA | L12: 50 | Q12: 0.005039 | S12: 0.0055 | Y12: 0.002359 | AD12: 0.0043 | AE12: =IF(Y12="","",Y12) -> 0.002359 | AG12: =IF(AF12="","",AE12+AF12) | AJ12: =IF(AG12="","N","Y") -> N
A13: =IF(B13="","",IF((YEAR(B13)-YEAR(B12))=0,A12+1,1)) -> 4 | B13: 42590 | C13: 울산영업부 | D13: 차장 김정인 | F13: 석유공사 | G13: 42590 | H13: 42654 | I13: =H13-G13 -> 64 | J13: =TRUNC(I13/30,0) -> 2 | K13: 정기예금 | L13: 55 | Q13: 0.006148 | S13: =AVERAGE(0.0064,0.009,0.007) -> 0.0074666667 | Y13: 0.003475 | AD13: 0.0038 | AE13: =IF(Y13="","",Y13) -> 0.003475 | AG13: =IF(AF13="","",AE13+AF13) | AJ13: =IF(AG13="","N","Y") -> N
A14: =IF(B14="","",IF((YEAR(B14)-YEAR(B13))=0,A13+1,1)) -> 5 | B14: 42593 | C14: 울산영업부 | D14: 차장 김정인 | F14: 석유공사 | G14: 42593 | H14: 42641 | I14: =H14-G14 -> 48 | J14: =TRUNC(I14/30,0) -> 1 | K14: 정기예금 | L14: 28 | Q14: 0.0051765 | S14: =AVERAGE(0.0064,0.0085,0.0058) -> 0.0069 | Y14: 0.002547 | AD14: 0.0035 | AE14: =IF(Y14="","",Y14) -> 0.002547 | AG14: =IF(AF14="","",AE14+AF14) | AJ14: =IF(AG14="","N","Y") -> N
A15: =IF(B15="","",IF((YEAR(B15)-YEAR(B14))=0,A14+1,1)) -> 6 | B15: 42606 | C15: 울산영업부 | D15: 차장 김정인 | F15: 석유공사 | G15: 42606 | H15: 42639 | I15: =H15-G15 -> 33 | J15: =TRUNC(I15/30,0) -> 1 | K15: 정기예금 | L15: 60 | Q15: 0.0052439 | S15: =AVERAGE(0.0076,0.008,0.0058) -> 0.0071333333 | Y15: 0.002614 | AD15: 0.004 | AE15: =IF(Y15="","",Y15) -> 0.002614 | AF15: 0.001386 | AG15: =IF(AF15="","",AE15+AF15) -> 0.004 | AJ15: =IF(AG15="","N","Y") -> Y
A16: =IF(B16="","",IF((YEAR(B16)-YEAR(B15))=0,A15+1,1)) -> 7 | B16: 42612 | C16: 강남영업부 | D16: 과장 이진아 | F16: 한전 | G16: 42612 | H16: 42643 | I16: =H16-G16 -> 31 | J16: =TRUNC(I16/30,0) -> 1 | K16: MMDA | L16: 50 | Q16: 0.0052439 | S16: =AVERAGE(0.007,0.0051,0.0058) -> 0.0059666667 | Y16: 0.000852 | AD16: 0.0045 | AE16: =IF(Y16="","",Y16) -> 0.000852 | AG16: =IF(AF16="","",AE16+AF16) | AJ16: =IF(AG16="","N","Y") -> N
A17: =IF(B17="","",IF((YEAR(B17)-YEAR(B16))=0,A16+1,1)) -> 8 | B17: 42612 | C17: 울산영업부 | D17: 차장 김정인 | F17: 석유공사 | G17: 42612 | H17: 42661 | I17: =H17-G17 -> 49 | J17: =TRUNC(I17/30,0) -> 1 | K17: 정기예금 | L17: 40 | Q17: 0.0052439 | S17: =AVERAGE(0.007,0.0051,0.0058) -> 0.0059666667 | Y17: 0.002614 | AD17: 0.0036 | AE17: =IF(Y17="","",Y17) -> 0.002614 | AG17: =IF(AF17="","",AE17+AF17) | AJ17: =IF(AG17="","N","Y") -> N
A18: =IF(B18="","",IF((YEAR(B18)-YEAR(B17))=0,A17+1,1)) -> 9 | B18: 42618 | C18: 서울영업부 | D18: 차장 이순정 | F18: 현대중공업 | G18: 42618 | H18: 42648 | I18: =H18-G18 -> 30 | J18: =TRUNC(I18/30,0) -> 1 | K18: MMDA | L18: 50 | Q18: 0.0052572 | S18: 0.0046 | Y18: 0.000857 | AD18: 0.004 | AE18: =IF(Y18="","",Y18) -> 0.000857 | AG18: =IF(AF18="","",AE18+AF18) | AJ18: =IF(AG18="","N","Y") -> N
A19: =IF(B19="","",IF((YEAR(B19)-YEAR(B18))=0,A18+1,1)) -> 10 | B19: 42620 | C19: 울산영업부 | D19: 계장 고재희 | F19: 석유공사 | G19: 42620 | H19: 42670 | I19: =H19-G19 -> 50 | J19: =TRUNC(I19/30,0) -> 1 | K19: 정기예금 | L19: 90 | Q19: 0.0051656 | S19: 0.005 | Y19: 0.002573 | AD19: 0.0035 | AE19: =IF(Y19="","",Y19) -> 0.002573 | AG19: =IF(AF19="","",AE19+AF19) | AJ19: =IF(AG19="","N","Y") -> N
A20: =IF(B20="","",IF((YEAR(B20)-YEAR(B19))=0,A19+1,1)) -> 11 | B20: 42620 | C20: 성서지점 | D20: 차장 이민 | F20: 법인고객 | G20: 42620 | H20: 42985 | I20: =H20-G20 -> 365 | J20: =TRUNC(I20/30,0) -> 12 | K20: 정기예금 | L20: 2 | Q20: 0.009825 | S20: =AVERAGE(0.0145,0.015,0.013) -> 0.014166667 | Y20: 0.009825 | AD20: 0.0115 | AE20: =IF(Y20="","",Y20) -> 0.009825 | AG20: =IF(AF20="","",AE20+AF20) | AJ20: =IF(AG20="","N","Y") -> N
A21: =IF(B21="","",IF((YEAR(B21)-YEAR(B20))=0,A20+1,1)) -> 12 | B21: 42622 | C21: 울산영업부 | D21: 차장 김정인 | F21: 석유공사 | G21: 42622 | H21: 42652 | I21: =H21-G21 -> 30 | J21: =TRUNC(I21/30,0) -> 1 | K21: MMDA | L21: 0 | Q21: 0.0042211 | S21: =AVERAGE(0.0045,0.0046,0.0047) -> 0.0046 | Y21: 0.000878 | AD21: 0.0025 | AE21: =IF(Y21="","",Y21) -> 0.000878 | AG21: =IF(AF21="","",AE21+AF21) | AJ21: =IF(AG21="","N","Y") -> N
A22: =IF(B22="","",IF((YEAR(B22)-YEAR(B21))=0,A21+1,1)) -> 13 | B22: 42622 | C22: 〃 | D22: 〃 | F22: 〃 | G22: 42622 | H22: 42652 | I22: =H22-G22 -> 30 | J22: =TRUNC(I22/30,0) -> 1 | K22: 정기예금 | L22: 0 | Q22: 0.0051822 | S22: =AVERAGE(0.007,0.0075) -> 0.00725 | Y22: 0.002553 | AD22: 0.0035 | AE22: =IF(Y22="","",Y22) -> 0.002553 | AG22: =IF(AF22="","",AE22+AF22) | AJ22: =IF(AG22="","N","Y") -> N
A23: =IF(B23="","",IF((YEAR(B23)-YEAR(B22))=0,A22+1,1)) -> 14 | B23: 42622 | C23: 〃 | D23: 〃 | F23: 〃 | G23: 42622 | H23: 42683 | I23: =H23-G23 -> 61 | J23: =TRUNC(I23/30,0) -> 2 | K23: 정기예금 | L23: 0 | Q23: 0.0066467 | S23: =AVERAGE(0.0077,0.0082) -> 0.00795 | Y23: 0.003988 | AD23: 0.0045 | AE23: =IF(Y23="","",Y23) -> 0.003988 | AG23: =IF(AF23="","",AE23+AF23) | AJ23: =IF(AG23="","N","Y") -> N
A24: =IF(B24="","",IF((YEAR(B24)-YEAR(B23))=0,A23+1,1)) -> 15 | B24: 42622 | C24: 〃 | D24: 〃 | F24: 〃 | G24: 42622 | H24: 42713 | I24: =H24-G24 -> 91 | J24: =TRUNC(I24/30,0) -> 3 | K24: 정기예금 | L24: 0 | Q24: 0.0084544 | S24: =AVERAGE(0.0115,0.0088,0.012) -> 0.010766667 | Y24: 0.00616 | AD24: 0.0067 | AE24: =IF(Y24="","",Y24) -> 0.00616 | AG24: =IF(AF24="","",AE24+AF24) | AJ24: =IF(AG24="","N","Y") -> N
A25: =IF(B25="","",IF((YEAR(B25)-YEAR(B24))=0,A24+1,1)) -> 16 | B25: 42622 | C25: 〃 | D25: 〃 | F25: 〃 | G25: 42622 | H25: 42803 | I25: =H25-G25 -> 181 | J25: =TRUNC(I25/30,0) -> 6 | K25: 정기예금 | L25: 0 | Q25: 0.0123472 | S25: =AVERAGE(0.0129,0.0116,0.0112) -> 0.0119 | Y25: 0.009675 | AD25: 0.01 | AE25: =IF(Y25="","",Y25) -> 0.009675 | AG25: =IF(AF25="","",AE25+AF25) | AJ25: =IF(AG25="","N","Y") -> N
A26: =IF(B26="","",IF((YEAR(B26)-YEAR(B25))=0,A25+1,1)) -> 17 | B26: 42634 | C26: 울산영업부 | D26: 차장 김정인 | F26: 석유공사 | G26: 42634 | H26: 42670 | I26: =H26-G26 -> 36 | J26: =TRUNC(I26/30,0) -> 1 | K26: 정기예금 | L26: 80 | Q26: 0.0054306 | S26: =AVERAGE(0.0065,0.0057,0.004) -> 0.0054 | Y26: 0.002796 | AD26: 0.0035 | AE26: =IF(Y26="","",Y26) -> 0.002796 | AG26: =IF(AF26="","",AE26+AF26) | AJ26: =IF(AG26="","N","Y") -> N
A27: =IF(B27="","",IF((YEAR(B27)-YEAR(B26))=0,A26+1,1)) -> 18 | B27: 42636 | C27: 강남영업부 | D27: 과장 이진아 | F27: 한전 | G27: 42636 | H27: 42666 | I27: =H27-G27 -> 30 | J27: =TRUNC(I27/30,0) -> 1 | K27: MMDA | L27: 50 | Q27: 0.0042322 | S27: =AVERAGE(0.0065,0.0057,0.004) -> 0.0054 | Y27: 0.000977 | AD27: 0.0047 | AE27: =IF(Y27="","",Y27) -> 0.000977 | AG27: =IF(AF27="","",AE27+AF27) | AJ27: =IF(AG27="","N","Y") -> N
A28: =IF(B28="","",IF((YEAR(B28)-YEAR(B27))=0,A27+1,1)) -> 19 | B28: 42649 | C28: 강남영업부 | D28: 차장 황수덕 | F28: SK하이닉스 | G28: 42649 | H28: 42680 | I28: =H28-G28 -> 31 | J28: =TRUNC(I28/30,0) -> 1 | K28: MMDA | L28: 50 | Q28: 0.0042822 | Y28: 0.000977 | AE28: =IF(Y28="","",Y28) -> 0.000977 | AG28: =IF(AF28="","",AE28+AF28) | AJ28: =IF(AG28="","N","Y") -> N
A29: =IF(B29="","",IF((YEAR(B29)-YEAR(B28))=0,A28+1,1)) -> 20 | B29: 42649 | C29: 성서지점 | D29: 대리 홍지현 | F29: 법인고객 | G29: 42649 | H29: 43014 | I29: =H29-G29 -> 365 | J29: =TRUNC(I29/30,0) -> 12 | K29: 정기예금 | L29: 2 | Q29: 0.0157267 | S29: =AVERAGE(0.015,0.014,0.0135) -> 0.014166667 | Y29: 0.011434 | AD29: 0.0125 | AE29: =IF(Y29="","",Y29) -> 0.011434 | AG29: =IF(AF29="","",AE29+AF29) | AJ29: =IF(AG29="","N","Y") -> N
A30: =IF(B30="","",IF((YEAR(B30)-YEAR(B29))=0,A29+1,1)) -> 21 | B30: 42650 | C30: 성서지점 | D30: 행원 이현경 | F30: ㈜나인플러스 | G30: 42650 | H30: 42742 | I30: =H30-G30 -> 92 | J30: =TRUNC(I30/30,0) -> 3 | K30: 정기예금 | L30: 1 | Q30: 0.0087156 | S30: =AVERAGE(0.0115,0.011,0.0089) -> 0.010466667 | Y30: 0.0064 | AD30: 0.007 | AE30: =IF(Y30="","",Y30) -> 0.0064 | AG30: 0.0071 | AJ30: =IF(AG30="","N","Y") -> Y
A31: =IF(B31="","",IF((YEAR(B31)-YEAR(B30))=0,A30+1,1)) -> 22 | B31: 42661 | C31: 울산영업부 | D31: 차장 김정인 | F31: 석유공사 | G31: 42661 | H31: 42695 | I31: =H31-G31 -> 34 | J31: =TRUNC(I31/30,0) -> 1 | K31: 정기예금 | L31: 70 | Q31: 0.0052789 | S31: =AVERAGE(0.0077,0.008) -> 0.00785 | Y31: 0.002647 | AD31: 0.0036 | AE31: =IF(Y31="","",Y31) -> 0.002647 | AJ31: =IF(AG31="","N","Y") -> N
A32: =IF(B32="","",IF((YEAR(B32)-YEAR(B31))=0,A31+1,1)) -> 23 | B32: 42668 | C32: 울산영업부 | D32: 차장 김정인 | F32: 석유공사 | G32: 42668 | H32: 42684 | I32: =H32-G32 -> 16 | J32: =TRUNC(I32/30,0) -> 0 | K32: 정기예금 | L32: 45 | Q32: 0.0045589 | S32: =AVERAGE(0.006,0.005) -> 0.0055 | Y32: 0.001577 | AD32: 0.002 | AE32: =IF(Y32="","",Y32) -> 0.001577 | AJ32: =IF(AG32="","N","Y") -> N
A33: =IF(B33="","",IF((YEAR(B33)-YEAR(B32))=0,A32+1,1)) -> 24 | B33: 42668 | C33: 〃 | D33: 〃 | F33: 〃 | G33: 42668 | H33: 42690 | I33: =H33-G33 -> 22 | J33: =TRUNC(I33/30,0) -> 0 | K33: 〃 | L33: 35 | Q33: 0.0045589 | S33: =AVERAGE(0.006,0.005) -> 0.0055 | Y33: 0.001577 | AD33: 0.002 | AE33: =IF(Y33="","",Y33) -> 0.001577 | AJ33: =IF(AG33="","N","Y") -> N
A34: =IF(B34="","",IF((YEAR(B34)-YEAR(B33))=0,A33+1,1)) -> 25 | B34: 42668 | C34: 〃 | D34: 〃 | F34: 〃 | G34: 42668 | H34: 42704 | I34: =H34-G34 -> 36 | J34: =TRUNC(I34/30,0) -> 1 | K34: 〃 | L34: 70 | Q34: 0.00534 | S34: =AVERAGE(0.0058,0.0065) -> 0.00615 | Y34: 0.002708 | AD34: 0.004 | AE34: =IF(Y34="","",Y34) -> 0.002708 | AG34: 0.004 | AJ34: =IF(AG34="","N","Y") -> Y
A35: =IF(B35="","",IF((YEAR(B35)-YEAR(B34))=0,A34+1,1)) -> 26 | B35: 42678 | C35: 〃 | D35: 〃 | F35: 〃 | G35: 42678 | H35: 42711 | I35: =H35-G35 -> 33 | J35: =TRUNC(I35/30,0) -> 1 | K35: 〃 | L35: 20 | Q35: 0.0053256 | AD35: 0.0036 | AE35: =IF(Y35="","",Y35) | AG35: 0 | AJ35: =IF(AG35="","N","Y") -> Y
A36: =IF(B36="","",IF((YEAR(B36)-YEAR(B35))=0,A35+1,1)) -> 27 | B36: 42678 | C36: 〃 | D36: 〃 | F36: 〃 | G36: 42678 | H36: 42711 | I36: =H36-G36 -> 33 | J36: =TRUNC(I36/30,0) -> 1 | K36: 〃 | L36: 30 | Q36: 0.0053256 | AD36: 0.0036 | AE36: =IF(Y36="","",Y36) | AJ36: =IF(AG36="","N","Y") -> N
A37: =IF(B37="","",IF((YEAR(B37)-YEAR(B36))=0,A36+1,1)) -> 28 | B37: 42682 | C37: 반월공단지점 | D37: 대리 김수현 | F37: ㈜이수엑사켐 | G37: 42682 | H37: 42725 | I37: =H37-G37 -> 43 | J37: =TRUNC(I37/30,0) -> 1 | K37: 〃 | L37: 7 | Q37: 0.0053533 | S37: =AVERAGE(0.0058,0.0065) -> 0.00615 | Y37: 0.002721 | AD37: 0.0036 | AE37: =IF(Y37="","",Y37) -> 0.002721 | AG37: 0.0036 | AJ37: =IF(AG37="","N","Y") -> Y
A38: =IF(B38="","",IF((YEAR(B38)-YEAR(B37))=0,A37+1,1)) -> 29 | B38: 42690 | C38: 울산영업부 | D38: 차장 김정인 | F38: 석유공사 | G38: 42690 | H38: 42718 | I38: =H38-G38 -> 28 | J38: =TRUNC(I38/30,0) -> 0 | K38: 〃 | L38: 30 | Q38: 0.0055011 | S38: =AVERAGE(0.0055,0.006) -> 0.00575 | Y38: 0.001605 | AD38: 0.0029 | AE38: =IF(Y38="","",Y38) -> 0.001605 | AJ38: =IF(AG38="","N","Y") -> N
A39: =IF(B39="","",IF((YEAR(B39)-YEAR(B38))=0,A38+1,1)) -> 30 | B39: 42695 | C39: 울산영업부 | D39: 차장 김정인 | F39: 석유공사 | G39: 42695 | H39: 42726 | I39: =H39-G39 -> 31 | J39: =TRUNC(I39/30,0) -> 1 | K39: 〃 | L39: 60 | Q39: 0.00566 | S39: =AVERAGE(0.0055,0.006) -> 0.00575 | Y39: 0.003021 | AD39: 0.0039 | AE39: =IF(Y39="","",Y39) -> 0.003021 | AJ39: =IF(AG39="","N","Y") -> N
A40: =IF(B40="","",IF((YEAR(B40)-YEAR(B39))=0,A39+1,1)) -> 31 | B40: 42702 | C40: 울산영업부 | D40: 차장 김정인 | F40: 석유공사 | G40: 42702 | H40: 42718 | I40: =H40-G40 -> 16 | J40: =TRUNC(I40/30,0) -> 0 | K40: 〃 | L40: 30 | Q40: 0.0045822 | S40: =AVERAGE(0.0052,0.0058,0.0051) -> 0.0053666667 | Y40: 0.001598 | AD40: 0.0026 | AE40: =IF(Y40="","",Y40) -> 0.001598 | AJ40: =IF(AG40="","N","Y") -> N
A41: =IF(B41="","",IF((YEAR(B41)-YEAR(B40))=0,A40+1,1)) -> 32 | B41: 42702 | C41: 울산영업부 | D41: 차장 김정인 | F41: 석유공사 | G41: 42702 | H41: 42724 | I41: =H41-G41 -> 22 | J41: =TRUNC(I41/30,0) -> 0 | K41: 〃 | L41: 50 | Q41: 0.0045822 | S41: =AVERAGE(0.0052,0.0058,0.0054) -> 0.0054666667 | Y41: 0.001598 | AD41: 0.003 | AE41: =IF(Y41="","",Y41) -> 0.001598 | AJ41: =IF(AG41="","N","Y") -> N
A42: =IF(B42="","",IF((YEAR(B42)-YEAR(B41))=0,A41+1,1)) -> 33 | B42: 42702 | C42: 울산영업부 | D42: 차장 김정인 | F42: 석유공사 | G42: 42702 | H42: 42727 | I42: =H42-G42 -> 25 | J42: =TRUNC(I42/30,0) -> 0 | K42: 〃 | L42: 80 | Q42: 0.0045822 | S42: =AVERAGE(0.0052,0.0058,0.0054) -> 0.0054666667 | Y42: 0.001598 | AD42: 0.003 | AE42: =IF(Y42="","",Y42) -> 0.001598 | AJ42: =IF(AG42="","N","Y") -> N
A43: =IF(B43="","",IF((YEAR(B43)-YEAR(B42))=0,A42+1,1)) -> 34 | B43: 42702 | C43: 울산영업부 | D43: 차장 김정인 | F43: 석유공사 | G43: 42702 | H43: 42734 | I43: =H43-G43 -> 32 | J43: =TRUNC(I43/30,0) -> 1 | K43: 〃 | L43: 120 | Q43: 0.0060589 | S43: =AVERAGE(0.007,0.006) -> 0.0065 | Y43: 0.003411 | AD43: 0.0042 | AE43: =IF(Y43="","",Y43) -> 0.003411 | AJ43: =IF(AG43="","N","Y") -> N
A44: =IF(B44="","",IF((YEAR(B44)-YEAR(B43))=0,A43+1,1)) -> 35 | B44: 42702 | C44: 울산영업부 | D44: 차장 김정인 | F44: 석유공사 | G44: 42702 | H44: 42734 | I44: =H44-G44 -> 32 | J44: =TRUNC(I44/30,0) -> 1 | K44: 〃 | L44: 110 | Q44: 0.0060589 | S44: =AVERAGE(0.007,0.006) -> 0.0065 | Y44: 0.003411 | AD44: 0.0042 | AE44: =IF(Y44="","",Y44) -> 0.003411 | AJ44: =IF(AG44="","N","Y") -> N
A45: =IF(B45="","",IF((YEAR(B45)-YEAR(B44))=0,A44+1,1)) -> 36 | B45: 42704 | C45: 강남영업부 | D45: 과장 이진아 | F45: 한전 | G45: 42704 | H45: 42734 | I45: =H45-G45 -> 30 | J45: =TRUNC(I45/30,0) -> 1 | K45: MMDA | L45: 50 | Q45: 0.0046044 | S45: =AVERAGE(0.007,0.006) -> 0.0065 | AD45: 0.0047 | AE45: =IF(Y45="","",Y45) | AJ45: =IF(AG45="","N","Y") -> N
A46: =IF(B46="","",IF((YEAR(B46)-YEAR(B45))=0,A45+1,1)) -> 37 | B46: 42704 | C46: 울산영업부 | D46: 차장 김정인 | F46: 석유공사 | G46: 42704 | H46: 42726 | I46: =H46-G46 -> 22 | J46: =TRUNC(I46/30,0) -> 0 | K46: 정기예금 | L46: 20 | Q46: 0.0046044 | S46: =AVERAGE(0.0055,0.0065) -> 0.006 | Y46: 0.001619 | AD46: 0.004 | AE46: =IF(Y46="","",Y46) -> 0.001619 | AJ46: =IF(AG46="","N","Y") -> N
A47: =IF(B47="","",IF((YEAR(B47)-YEAR(B46))=0,A46+1,1)) -> 38 | B47: 42704 | C47: 울산영업부 | D47: 차장 김정인 | F47: 석유공사 | G47: 42704 | H47: 42734 | I47: =H47-G47 -> 30 | J47: =TRUNC(I47/30,0) -> 1 | K47: 정기예금 | L47: 30 | Q47: 0.0061672 | S47: =AVERAGE(0.011,0.0063) -> 0.00865 | Y47: 0.003518 | AD47: 0.0046 | AE47: =IF(Y47="","",Y47) -> 0.003518 | AJ47: =IF(AG47="","N","Y") -> N
A48: =IF(B48="","",IF((YEAR(B48)-YEAR(B47))=0,A47+1,1)) -> 39 | B48: 42711 | C48: 울산영업부 | D48: 차장 김정인 | F48: 석유공사 | G48: 42711 | H48: 42739 | I48: =H48-G48 -> 28 | J48: =TRUNC(I48/30,0) -> 0 | K48: 정기예금 | L48: 50 | Q48: 0.0064889 | S48: =AVERAGE(0.016,0.0064) -> 0.0112 | Y48: 0.003834 | AD48: 0.0044 | AE48: =IF(Y48="","",Y48) -> 0.003834 | AJ48: =IF(AG48="","N","Y") -> N
A49: =IF(B49="","",IF((YEAR(B49)-YEAR(B48))=0,A48+1,1)) -> 40 | B49: 42718 | C49: 울산영업부 | D49: 차장 김정인 | F49: 석유공사 | G49: 42718 | H49: 42746 | I49: =H49-G49 -> 28 | J49: =TRUNC(I49/30,0) -> 0 | K49: 정기예금 | L49: 60 | Q49: 0.0070389 | S49: =AVERAGE(0.017,0.0081,0.0061) -> 0.0104 | Y49: 0.004373 | AD49: 0.0052 | AE49: =IF(Y49="","",Y49) -> 0.004373 | AG49: 0.0052 | AJ49: =IF(AG49="","N","Y") -> Y
A50: =IF(B50="","",IF((YEAR(B50)-YEAR(B49))=0,A49+1,1)) -> 41 | B50: 42724 | C50: 울산영업부 | D50: 차장 김정인 | F50: 석유공사 | G50: 42724 | H50: 42730 | I50: =H50-G50 -> 6 | J50: =TRUNC(I50/30,0) -> 0 | K50: 정기예금 | L50: 25 | Q50: 0.006811 | S50: 0.005 | Y50: 0.003275 | AD50: 0.0033 | AE50: =IF(Y50="","",Y50) -> 0.003275 | AJ50: =IF(AG50="","N","Y") -> N
A51: =IF(B51="","",IF((YEAR(B51)-YEAR(B50))=0,A50+1,1)) -> 42 | B51: 42724 | C51: 울산영업부 | D51: 차장 김정인 | F51: 석유공사 | G51: 42724 | H51: 42732 | I51: =H51-G51 -> 8 | J51: =TRUNC(I51/30,0) -> 0 | K51: 정기예금 | L51: 25 | Q51: 0.0070306 | S51: 0.005 | Y51: 0.003875 | AD51: 0.0039 | AE51: =IF(Y51="","",Y51) -> 0.003875 | AJ51: =IF(AG51="","N","Y") -> N
A52: =IF(B52="","",IF((YEAR(B52)-YEAR(B51))=0,A51+1,1)) -> 43 | B52: 42724 | C52: 강남영업부 | D52: 과장 이진아 | F52: 한전 | G52: 42724 | H52: 42755 | I52: =H52-G52 -> 31 | J52: =TRUNC(I52/30,0) -> 1 | K52: MMDA | L52: 50 | AD52: 0.005 | AE52: =IF(Y52="","",Y52) | AJ52: =IF(AG52="","N","Y") -> N
A53: =IF(B53="","",IF((YEAR(B53)-YEAR(B52))=0,A52+1,1)) -> 44 | B53: 42733 | C53: 울산영업부 | D53: 차장 김정인 | F53: 석유공사 | G53: 42733 | H53: 42760 | I53: =H53-G53 -> 27 | J53: =TRUNC(I53/30,0) -> 0 | K53: 정기예금 | L53: 50 | Q53: 0.0071533 | S53: =AVERAGE(0.0092,0.0075) -> 0.00835 | Y53: 0.00399 | AD53: 0.0059 | AE53: =IF(Y53="","",Y53) -> 0.00399 | AJ53: =IF(AG53="","N","Y") -> N
A54: =IF(B54="","",IF((YEAR(B54)-YEAR(B53))=0,A53+1,1)) -> 45 | B54: 42733 | C54: 울산영업부 | D54: 차장 김정인 | F54: 석유공사 | G54: 42733 | H54: 42767 | I54: =H54-G54 -> 34 | J54: =TRUNC(I54/30,0) -> 1 | K54: 정기예금 | L54: 50 | Q54: 0.0077 | S54: =AVERAGE(0.0092,0.0075) -> 0.00835 | Y54: 0.005021 | AD54: 0.0059 | AE54: =IF(Y54="","",Y54) -> 0.005021 | AJ54: =IF(AG54="","N","Y") -> N
A55: =IF(B55="","",IF((YEAR(B55)-YEAR(B54))=0,A54+1,1)) -> 46 | B55: 42734 | C55: 울산영업부 | D55: 차장 김정인 | F55: 석유공사 | G55: 42734 | H55: 42774 | I55: =H55-G55 -> 40 | J55: =TRUNC(I55/30,0) -> 1 | K55: 정기예금 | L55: 60 | Q55: 0.0077111 | S55: =AVERAGE(0.0095,0.0075) -> 0.0085 | Y55: 0.005031 | AD55: 0.0064 | AE55: =IF(Y55="","",Y55) -> 0.005031 | AJ55: =IF(AG55="","N","Y") -> N
A56: =IF(B56="","",IF((YEAR(B56)-YEAR(B55))=0,A55+1,1)) -> 47 | B56: 42734 | C56: 울산영업부 | D56: 차장 김정인 | F56: 석유공사 | G56: 42734 | H56: 42781 | I56: =H56-G56 -> 47 | J56: =TRUNC(I56/30,0) -> 1 | K56: 정기예금 | L56: 60 | Q56: 0.0077111 | S56: =AVERAGE(0.0095,0.0075) -> 0.0085 | Y56: 0.005031 | AD56: 0.0064 | AE56: =IF(Y56="","",Y56) -> 0.005031 | AJ56: =IF(AG56="","N","Y") -> N
A57: =IF(B57="","",IF((YEAR(B57)-YEAR(B56))=0,A56+1,1)) -> 1 | B57: 42737 | C57: 강남영업부 | D57: 과장 이진아 | F57: 한전 | G57: 42737 | H57: 42766 | I57: =H57-G57 -> 29 | J57: =TRUNC(I57/30,0) -> 0 | K57: MMDA | L57: 50 | AD57: 0.0064 | AE57: =IF(Y57="","",Y57) | AJ57: =IF(AG57="","N","Y") -> N
A58: =IF(B58="","",IF((YEAR(B58)-YEAR(B57))=0,A57+1,1)) -> 2 | B58: 42739 | C58: 울산영업부 | D58: 차장 김정인 | F58: 석유공사 | G58: 42739 | H58: 42789 | I58: =H58-G58 -> 50 | J58: =TRUNC(I58/30,0) -> 1 | K58: 정기예금 | L58: 50 | Q58: 0.0077333 | S58: =AVERAGE(0.011,0.0093) -> 0.01015 | Y58: 0.005053 | AD58: 0.0075 | AE58: =IF(Y58="","",Y58) -> 0.005053 | AJ58: =IF(AG58="","N","Y") -> N
A59: =IF(B59="","",IF((YEAR(B59)-YEAR(B58))=0,A58+1,1)) -> 3 | B59: 42746 | C59: 울산영업부 | D59: 차장 김정인 | F59: 석유공사 | G59: 42746 | H59: 42801 | I59: =H59-G59 -> 55 | J59: =TRUNC(I59/30,0) -> 1 | K59: 정기예금 | L59: 60 | Q59: 0.00765 | S59: =AVERAGE(0.012,0.009) -> 0.0105 | Y59: 0.004972 | AD59: 0.0075 | AE59: =IF(Y59="","",Y59) -> 0.004972 | AG59: 0.0073 | AJ59: =IF(AG59="","N","Y") -> Y
A60: =IF(B60="","",IF((YEAR(B60)-YEAR(B59))=0,A59+1,1)) -> 4 | B60: 42753 | C60: 울산영업부 | D60: 차장 김정인 | F60: 석유공사 | G60: 42753 | H60: 42801 | I60: =H60-G60 -> 48 | J60: =TRUNC(I60/30,0) -> 1 | K60: 정기예금 | L60: 40 | Q60: 0.0076944 | S60: =AVERAGE(0.011,0.009) -> 0.01 | Y60: 0.005015 | AD60: 0.0064 | AE60: =IF(Y60="","",Y60) -> 0.005015 | AJ60: =IF(AG60="","N","Y") -> N
A61: =IF(B61="","",IF((YEAR(B61)-YEAR(B60))=0,A60+1,1)) -> 5 | B61: 42753 | C61: 강남영업부 | D61: 과장 이진아 | F61: SK하이닉스 | G61: 42753 | H61: 42784 | I61: =H61-G61 -> 31 | J61: =TRUNC(I61/30,0) -> 1 | K61: MMDA | L61: 50 | Q61: 0.0076944 | S61: =AVERAGE(0.011,0.009) -> 0.01 | Y61: 0.005015 | AD61: 0.006 | AE61: =IF(Y61="","",Y61) -> 0.005015 | AJ61: =IF(AG61="","N","Y") -> N
A62: =IF(B62="","",IF((YEAR(B62)-YEAR(B61))=0,A61+1,1)) -> 6 | B62: 42759 | C62: 강남영업부 | D62: 과장 이진아 | F62: 한전 | G62: 42759 | H62: 42790 | I62: =H62-G62 -> 31 | J62: =TRUNC(I62/30,0) -> 1 | K62: MMDA | L62: 50 | Q62: 0.0077111 | S62: =AVERAGE(0.0103,0.01) -> 0.01015 | Y62: 0.005031 | AD62: 0.0064 | AE62: =IF(Y62="","",Y62) -> 0.005031 | AJ62: =IF(AG62="","N","Y") -> N
A63: =IF(B63="","",IF((YEAR(B63)-YEAR(B62))=0,A62+1,1)) -> 7 | B63: 42759 | C63: 강남영업부 | D63: 과장 이진아 | F63: 한전 | G63: 42759 | H63: 42818 | I63: =H63-G63 -> 59 | J63: =TRUNC(I63/30,0) -> 1 | K63: 정기예금 | L63: 50 | Q63: 0.0084694 | S63: =AVERAGE(0.012,0.011) -> 0.0115 | Y63: 0.005031 | AD63: 0.0075 | AE63: =IF(Y63="","",Y63) -> 0.005031 | AJ63: =IF(AG63="","N","Y") -> N
A64: =IF(B64="","",IF((YEAR(B64)-YEAR(B63))=0,A63+1,1)) -> 8 | B64: 42761 | C64: 강남영업부 | D64: 과장 이진아 | F64: 한전 | G64: 42761 | H64: 42851 | I64: =H64-G64 -> 90 | J64: =TRUNC(I64/30,0) -> 3 | K64: 정기예금 | L64: 50 | Q64: 0.0103789 | S64: =AVERAGE(0.013,0.014) -> 0.0135 | Y64: 0.008046 | AD64: 0.009 | AE64: =IF(Y64="","",Y64) -> 0.008046 | AJ64: =IF(AG64="","N","Y") -> N
A65: =IF(B65="","",IF((YEAR(B65)-YEAR(B64))=0,A64+1,1)) -> 9 | B65: 42760 | C65: 울산영업부 | D65: 차장 김정인 | F65: 석유공사 | G65: 42760 | H65: 42801 | I65: =H65-G65 -> 41 | J65: =TRUNC(I65/30,0) -> 1 | K65: 정기예금 | L65: 50 | Q65: 0.0077333 | S65: =AVERAGE(0.0103,0.01) -> 0.01015 | Y65: 0.005053 | AD65: 0.0071 | AE65: =IF(Y65="","",Y65) -> 0.005053 | AJ65: =IF(AG65="","N","Y") -> N
A66: =IF(B66="","",IF((YEAR(B66)-YEAR(B65))=0,A65+1,1)) -> 10 | B66: 42761 | C66: 강남영업부 | D66: 과장 이진아 | F66: SK하이닉스 | G66: 42761 | H66: 42794 | I66: =H66-G66 -> 33 | J66: =TRUNC(I66/30,0) -> 1 | K66: MMDA | L66: 50 | Q66: 0.0077333 | S66: =AVERAGE(0.0103,0.01) -> 0.01015 | Y66: 0.005053 | AD66: 0.006 | AE66: =IF(Y66="","",Y66) -> 0.005053 | AG66: 0.0057 | AJ66: =IF(AG66="","N","Y") -> Y
A67: =IF(B67="","",IF((YEAR(B67)-YEAR(B66))=0,A66+1,1)) -> 11 | B67: 42767 | C67: 울산영업부 | D67: 차장 김정인 | F67: 석유공사 | G67: 42767 | H67: 42801 | I67: =H67-G67 -> 34 | J67: =TRUNC(I67/30,0) -> 1 | K67: 정기예금 | L67: 70 | Q67: 0.0077944 | S67: =AVERAGE(0.008,0.0087) -> 0.00835 | Y67: 0.005113 | AD67: 0.0063 | AE67: =IF(Y67="","",Y67) -> 0.005113 | AJ67: =IF(AG67="","N","Y") -> N
A68: =IF(B68="","",IF((YEAR(B68)-YEAR(B67))=0,A67+1,1)) -> 12 | B68: 42767 | C68: 강남영업부 | D68: 과장 이진아 | F68: 한전 | G68: 42767 | H68: 42794 | I68: =H68-G68 -> 27 | J68: =TRUNC(I68/30,0) -> 0 | K68: MMDA | L68: 50 | Q68: 0.0077944 | S68: =AVERAGE(0.008,0.0085) -> 0.00825 | Y68: 0.005113 | AD68: 0.0063 | AE68: =IF(Y68="","",Y68) -> 0.005113 | AJ68: =IF(AG68="","N","Y") -> N
A69: =IF(B69="","",IF((YEAR(B69)-YEAR(B68))=0,A68+1,1)) -> 13 | B69: 42774 | C69: 울산영업부 | D69: 차장 김정인 | F69: 석유공사 | G69: 42774 | H69: 42801 | I69: =H69-G69 -> 27 | J69: =TRUNC(I69/30,0) -> 0 | K69: 정기예금 | L69: 40 | Q69: 0.0077278 | S69: =AVERAGE(0.008,0.0087) -> 0.00835 | Y69: 0.004043 | AD69: 0.007 | AE69: =IF(Y69="","",Y69) -> 0.004043 | AJ69: =IF(AG69="","N","Y") -> N
A70: =IF(B70="","",IF((YEAR(B70)-YEAR(B69))=0,A69+1,1)) -> 14 | B70: 42781 | C70: 울산영업부 | D70: 차장 김정인 | F70: 석유공사 | G70: 42781 | H70: 42811 | I70: =H70-G70 -> 30 | J70: =TRUNC(I70/30,0) -> 1 | K70: 정기예금 | L70: 60 | Q70: 0.0077 | S70: =AVERAGE(0.008,0.0095) -> 0.00875 | Y70: 0.005021 | AD70: 0.007 | AE70: =IF(Y70="","",Y70) -> 0.005021 | AJ70: =IF(AG70="","N","Y") -> N
A71: =IF(B71="","",IF((YEAR(B71)-YEAR(B70))=0,A70+1,1)) -> 15 | B71: 42789 | C71: 울산영업부 | D71: 차장 김정인 | F71: 석유공사 | G71: 42789 | H71: 42801 | I71: =H71-G71 -> 12 | J71: =TRUNC(I71/30,0) -> 0 | K71: 정기예금 | L71: 60 | Q71: 0.0077944 | S71: =AVERAGE(0.0084,0.0085) -> 0.00845 | Y71: 0.003976 | AD71: 0.007 | AE71: =IF(Y71="","",Y71) -> 0.003976 | AJ71: =IF(AG71="","N","Y") -> N
A72: =IF(B72="","",IF((YEAR(B72)-YEAR(B71))=0,A71+1,1)) -> 16 | B72: 42796 | C72: 강남영업부 | D72: 과장 이진아 | F72: 한전 | G72: 42796 | H72: 42825 | I72: =H72-G72 -> 29 | J72: =TRUNC(I72/30,0) -> 0 | K72: MMDA | L72: 100 | Q72: 0.0081056 | S72: =AVERAGE(0.0095,0.0083,0.0082) -> 0.0086666667 | Y72: 0.00395 | AD72: 0.0064 | AE72: =IF(Y72="","",Y72) -> 0.00395 | AJ72: =IF(AG72="","N","Y") -> N
A73: =IF(B73="","",IF((YEAR(B73)-YEAR(B72))=0,A72+1,1)) -> 17 | B73: 42807 | C73: 강남영업부 | D73: 팀장 조은주 | F73: 한전 | G73: 42807 | H73: 42814 | I73: =H73-G73 -> 7 | J73: =TRUNC(I73/30,0) -> 0 | K73: 정기예금 | L73: 50 | Q73: 0.0084611 | S73: 0.007 | Y73: 0.005206 | AD73: 0.005206 | AE73: =IF(Y73="","",Y73) -> 0.005206 | AJ73: =IF(AG73="","N","Y") -> N
A74: =IF(B74="","",IF((YEAR(B74)-YEAR(B73))=0,A73+1,1)) -> 18 | B74: 42807 | C74: 강남영업부 | D74: 팀장 조은주 | F74: 한전 | G74: 42807 | H74: 42824 | I74: =H74-G74 -> 17 | J74: =TRUNC(I74/30,0) -> 0 | K74: MMDA | L74: 60 | Q74: 0.0084611 | S74: 0.007 | Y74: 0.005206 | AD74: 0.0062 | AE74: =IF(Y74="","",Y74) -> 0.005206 | AJ74: =IF(AG74="","N","Y") -> N
A75: =IF(B75="","",IF((YEAR(B75)-YEAR(B74))=0,A74+1,1)) -> 19 | B75: 42807 | C75: 포항공단점 | D75: 과장 이제훈 | F75: ㈜제이엔테크 | G75: 42807 | H75: 42870 | I75: =H75-G75 -> 63 | J75: =TRUNC(I75/30,0) -> 2 | K75: 정기예금 | L75: 1 | Q75: 0.006202 | S75: =AVERAGE(0.0109,0.0125) -> 0.0117 | Y75: 0.006202 | AD75: 0.0068 | AE75: =IF(Y75="","",Y75) -> 0.006202 | AG75: 0.0068 | AJ75: =IF(AG75="","N","Y") -> Y
A76: =IF(B76="","",IF((YEAR(B76)-YEAR(B75))=0,A75+1,1)) -> 20 | B76: 42811 | C76: 울산영업부 | D76: 차장 김정인 | F76: 석유공사 | G76: 42811 | H76: 42829 | I76: =H76-G76 -> 18 | J76: =TRUNC(I76/30,0) -> 0 | K76: 정기예금 | L76: 60 | Q76: 0.0094567 | S76: =AVERAGE(0.0094,0.01) -> 0.0097 | Y76: 0.006132 | AD76: 0.0074 | AE76: =IF(Y76="","",Y76) -> 0.006132 | AJ76: =IF(AG76="","N","Y") -> N
A77: =IF(B77="","",IF((YEAR(B77)-YEAR(B76))=0,A76+1,1)) -> 21 | B77: 42814 | C77: 강남영업부 | D77: 과장 이진아 | F77: 한전 | G77: 42814 | H77: 42821 | I77: =H77-G77 -> 7 | J77: =TRUNC(I77/30,0) -> 0 | K77: 정기예금 | Q77: 0.0094611 | S77: 0.0094 | Y77: 0.006136 | AD77: 0.0052 | AE77: =IF(Y77="","",Y77) -> 0.006136 | AJ77: =IF(AG77="","N","Y") -> N
A78: =IF(B78="","",IF((YEAR(B78)-YEAR(B77))=0,A77+1,1)) -> 22 | B78: 42816 | C78: 강남영업부 | D78: 과장 이진아 | F78: SK하이닉스 | G78: 42816 | H78: 42846 | I78: =H78-G78 -> 30 | J78: =TRUNC(I78/30,0) -> 1 | K78: MMDA | L78: 100 | Q78: 0.0092533 | S78: 0.0094 | Y78: 0.005536 | AD78: 0.0065 | AE78: =IF(Y78="","",Y78) -> 0.005536 | AG78: 0.0065 | AJ78: =IF(AG78="","N","Y") -> Y
A79: =IF(B79="","",IF((YEAR(B79)-YEAR(B78))=0,A78+1,1)) -> 23 | B79: 42818 | C79: 강남영업부 | D79: 과장 이진아 | F79: 한전 | G79: 42818 | H79: 42912 | I79: =H79-G79 -> 94 | J79: =TRUNC(I79/30,0) -> 3 | K79: 정기예금 | L79: 50 | Q79: 0.0115289 | S79: =AVERAGE(0.011,0.0145,0.012) -> 0.0125 | Y79: 0.009173 | AD79: 0.01 | AE79: =IF(Y79="","",Y79) -> 0.009173 | AJ79: =IF(AG79="","N","Y") -> N
A80: =IF(B80="","",IF((YEAR(B80)-YEAR(B79))=0,A79+1,1)) -> 24 | B80: 42818 | C80: 강남영업부 | D80: 과장 이진아 | F80: 한전 | G80: 42818 | H80: 42849 | I80: =H80-G80 -> 31 | J80: =TRUNC(I80/30,0) -> 1 | K80: MMDA | L80: 50 | Q80: 0.0092611 | S80: 0.0094 | Y80: 0.005515 | AD80: 0.0065 | AE80: =IF(Y80="","",Y80) -> 0.005515 | AJ80: =IF(AG80="","N","Y") -> N
A81: =IF(B81="","",IF((YEAR(B81)-YEAR(B80))=0,A80+1,1)) -> 25 | B81: 42822 | C81: 울산영업부 | D81: 차장 김정인 | F81: 석유공사 | G81: 42822 | H81: 42828 | I81: =H81-G81 -> 6 | J81: =TRUNC(I81/30,0) -> 0 | K81: 정기예금 | L81: 200 | Q81: 0.0094389 | S81: 0.0095 | Y81: 0.005515 | AD81: 0.0074 | AE81: =IF(Y81="","",Y81) -> 0.005515 | AJ81: =IF(AG81="","N","Y") -> N
A82: =IF(B82="","",IF((YEAR(B82)-YEAR(B81))=0,A81+1,1)) -> 26 | B82: 42822 | C82: 울산영업부 | D82: 차장 김정인 | F82: 석유공사 | G82: 42822 | H82: 42843 | I82: =H82-G82 -> 21 | J82: =TRUNC(I82/30,0) -> 0 | K82: 정기예금 | L82: 50 | Q82: 0.0094389 | S82: =AVERAGE(0.0102,0.0105) -> 0.01035 | Y82: 0.006115 | AD82: 0.008 | AE82: =IF(Y82="","",Y82) -> 0.006115 | AJ82: =IF(AG82="","N","Y") -> N
A83: =IF(B83="","",IF((YEAR(B83)-YEAR(B82))=0,A82+1,1)) -> 27 | B83: 42822 | C83: 울산영업부 | D83: 차장 김정인 | F83: 석유공사 | G83: 42822 | H83: 42865 | I83: =H83-G83 -> 43 | J83: =TRUNC(I83/30,0) -> 1 | K83: 정기예금 | L83: 100 | Q83: 0.0098278 | S83: =AVERAGE(0.0111,0.012) -> 0.01155 | Y83: 0.007106 | AD83: 0.009 | AE83: =IF(Y83="","",Y83) -> 0.007106 | AJ83: =IF(AG83="","N","Y") -> N
A84: =IF(B84="","",IF((YEAR(B84)-YEAR(B83))=0,A83+1,1)) -> 28 | B84: 42822 | C84: 울산영업부 | D84: 차장 김정인 | F84: 석유공사 | G84: 42822 | H84: 42893 | I84: =H84-G84 -> 71 | J84: =TRUNC(I84/30,0) -> 2 | K84: 정기예금 | L84: 100 | Q84: 0.0102278 | S84: =AVERAGE(0.0114,0.012,0.0119) -> 0.011766667 | Y84: 0.007106 | AD84: 0.0095 | AE84: =IF(Y84="","",Y84) -> 0.007106 | AJ84: =IF(AG84="","N","Y") -> N
A85: =IF(B85="","",IF((YEAR(B85)-YEAR(B84))=0,A84+1,1)) -> 29 | B85: 42822 | C85: 울산영업부 | D85: 차장 김정인 | F85: 석유공사 | G85: 42822 | H85: 42920 | I85: =H85-G85 -> 98 | J85: =TRUNC(I85/30,0) -> 3 | K85: 정기예금 | L85: 200 | Q85: 0.0115128 | S85: =AVERAGE(0.012,0.0119,0.012) -> 0.011966667 | Y85: 0.009157 | AD85: 0.01 | AE85: =IF(Y85="","",Y85) -> 0.009157 | AJ85: =IF(AG85="","N","Y") -> N
A86: =IF(B86="","",IF((YEAR(B86)-YEAR(B85))=0,A85+1,1)) -> 30 | B86: 42821 | C86: 강남영업부 | D86: 과장 이진아 | F86: 한전 | G86: 42821 | H86: 42852 | I86: =H86-G86 -> 31 | J86: =TRUNC(I86/30,0) -> 1 | K86: MMDA | L86: 70 | Q86: 0.0092667 | S86: =AVERAGE(0.0098,0.0097,0.0096) -> 0.0097 | Y86: 0.005515 | AD86: 0.0066 | AE86: =IF(Y86="","",Y86) -> 0.005515 | AJ86: =IF(AG86="","N","Y") -> N
A87: =IF(B87="","",IF((YEAR(B87)-YEAR(B86))=0,A86+1,1)) -> 31 | B87: 42823 | C87: 강남영업부 | D87: 팀장 조은주 | F87: SK하이닉스 | G87: 42823 | H87: 42854 | I87: =H87-G87 -> 31 | J87: =TRUNC(I87/30,0) -> 1 | K87: MMDA | L87: 50 | Q87: 0.0092667 | S87: =AVERAGE(0.0098,0.0097,0.0096) -> 0.0097 | Y87: 0.005515 | AD87: 0.0063 | AE87: =IF(Y87="","",Y87) -> 0.005515 | AG87: 0.0065 | AJ87: =IF(AG87="","N","Y") -> Y
A88: =IF(B88="","",IF((YEAR(B88)-YEAR(B87))=0,A87+1,1)) -> 32 | B88: 42824 | C88: 강남영업부 | D88: 과장 이진아 | F88: 한전 | G88: 42824 | H88: 42855 | I88: =H88-G88 -> 31 | J88: =TRUNC(I88/30,0) -> 1 | K88: MMDA | L88: 30 | Q88: 0.0092556 | S88: =AVERAGE(0.0098,0.0097) -> 0.00975 | Y88: 0.005551 | AD88: 0.0066 | AE88: =IF(Y88="","",Y88) -> 0.005551 | AJ88: =IF(AG88="","N","Y") -> N
A89: =IF(B89="","",IF((YEAR(B89)-YEAR(B88))=0,A88+1,1)) -> 33 | B89: 42829 | C89: 울산영업부 | D89: 차장 김정인 | F89: 석유공사 | G89: 42829 | H89: 42850 | I89: =H89-G89 -> 21 | J89: =TRUNC(I89/30,0) -> 0 | K89: 정기예금 | L89: 60 | Q89: 0.009511 | S89: =AVERAGE(0.011,0.0103) -> 0.01065 | Y89: 0.006181 | AD89: 0.0074 | AE89: =IF(Y89="","",Y89) -> 0.006181 | AJ89: =IF(AG89="","N","Y") -> N
A90: =IF(B90="","",IF((YEAR(B90)-YEAR(B89))=0,A89+1,1)) -> 34 | B90: 42839 | C90: 강남영업부 | D90: 과장 이진아 | F90: 한전 | G90: 42839 | H90: 42849 | I90: =H90-G90 -> 10 | J90: =TRUNC(I90/30,0) -> 0 | K90: 정기예금 | L90: 50 | Q90: 0.008205 | S90: 0.0097 | Y90: 0.005131 | AD90: 0.007 | AE90: =IF(Y90="","",Y90) -> 0.005131 | AJ90: =IF(AG90="","N","Y") -> N
A91: =IF(B91="","",IF((YEAR(B91)-YEAR(B90))=0,A90+1,1)) -> 35 | B91: 42839 | C91: 강남영업부 | D91: 과장 이진아 | F91: 한전 | G91: 42839 | H91: 42853 | I91: =H91-G91 -> 14 | J91: =TRUNC(I91/30,0) -> 0 | K91: MMDA | L91: 45 | Q91: 0.008011 | S91: 0.0097 | Y91: 0.004331 | AD91: 0.0064 | AE91: =IF(Y91="","",Y91) -> 0.004331 | AJ91: =IF(AG91="","N","Y") -> N
A92: =IF(B92="","",IF((YEAR(B92)-YEAR(B91))=0,A91+1,1)) -> 36 | B92: 42843 | C92: 울산영업부 | D92: 차장 김정인 | F92: 석유공사 | G92: 42843 | H92: 42879 | I92: =H92-G92 -> 36 | J92: =TRUNC(I92/30,0) -> 1 | K92: 정기예금 | L92: 40 | Q92: 0.0099444 | S92: =AVERAGE(0.0113,0.0112) -> 0.01125 | Y92: 0.00632 | AD92: 0.009 | AE92: =IF(Y92="","",Y92) -> 0.00632 | AJ92: =IF(AG92="","N","Y") -> N
A93: =IF(B93="","",IF((YEAR(B93)-YEAR(B92))=0,A92+1,1)) -> 37 | B93: 42845 | C93: 강남영업부 | D93: 과장 이진아 | F93: SK하이닉스 | G93: 42845 | H93: 42877 | I93: =H93-G93 -> 32 | J93: =TRUNC(I93/30,0) -> 1 | K93: MMDA | L93: 150 | Q93: 0.0093 | S93: =AVERAGE(0.0098,0.0096) -> 0.0097 | Y93: 0.004336 | AD93: 0.0065 | AE93: =IF(Y93="","",Y93) -> 0.004336 | AJ93: =IF(AG93="","N","Y") -> N
A94: =IF(B94="","",IF((YEAR(B94)-YEAR(B93))=0,A93+1,1)) -> 38 | B94: 42849 | C94: 강남영업부 | D94: 과장 이진아 | F94: 한전 | G94: 42849 | H94: 42879 | I94: =H94-G94 -> 30 | J94: =TRUNC(I94/30,0) -> 1 | K94: MMDA | L94: 50 | Q94: 0.0092944 | S94: =AVERAGE(0.0098,0.0096) -> 0.0097 | Y94: 0.004326 | AD94: 0.0068 | AE94: =IF(Y94="","",Y94) -> 0.004326 | AJ94: =IF(AG94="","N","Y") -> N
A95: =IF(B95="","",IF((YEAR(B95)-YEAR(B94))=0,A94+1,1)) -> 39 | B95: 42850 | C95: 울산영업부 | D95: 차장 김정인 | F95: 석유공사 | G95: 42850 | H95: 42885 | I95: =H95-G95 -> 35 | J95: =TRUNC(I95/30,0) -> 1 | K95: 정기예금 | L95: 60 | Q95: 0.0099111 | S95: =AVERAGE(0.0111,0.0115) -> 0.0113 | Y95: 0.006287 | AD95: 0.0085 | AE95: =IF(Y95="","",Y95) -> 0.006287 | AJ95: =IF(AG95="","N","Y") -> N
A96: =IF(B96="","",IF((YEAR(B96)-YEAR(B95))=0,A95+1,1)) -> 40 | B96: 42851 | C96: 강남영업부 | D96: 과장 이진아 | F96: 한전 | G96: 42851 | H96: 42881 | I96: =H96-G96 -> 30 | J96: =TRUNC(I96/30,0) -> 1 | K96: 정기예금 | L96: 50 | Q96: 0.0099222 | S96: =AVERAGE(0.0111,0.0115) -> 0.0113 | Y96: 0.006298 | Z96: 0.0021 | AA96: 0.001 | AC96: =S96-Z96-AA96 -> 0.0082 | AD96: 0.009 | AE96: =IF(Y96="","",Y96) -> 0.006298 | AJ96: =IF(AG96="","N","Y") -> N | AL96: 1.1%이상
A97: =IF(B97="","",IF((YEAR(B97)-YEAR(B96))=0,A96+1,1)) -> 41 | B97: 42851 | C97: 강남영업부 | D97: 과장 이진아 | F97: 한전 | G97: 42851 | H97: 42912 | I97: =H97-G97 -> 61 | J97: =TRUNC(I97/30,0) -> 2 | K97: 정기예금 | L97: 50 | Q97: 0.0104056 | S97: 0.0124 | Y97: 0.006771 | Z97: 0.0021 | AA97: 0.001 | AC97: =S97-Z97-AA97 -> 0.0093 | AD97: 0.0092 | AE97: =IF(Y97="","",Y97) -> 0.006771 | AJ97: =IF(AG97="","N","Y") -> N
A98: =IF(B98="","",IF((YEAR(B98)-YEAR(B97))=0,A97+1,1)) -> 42 | B98: 42851 | C98: 강남영업부 | D98: 과장 이진아 | F98: 한전 | G98: 42851 | H98: 42943 | I98: =H98-G98 -> 92 | J98: =TRUNC(I98/30,0) -> 3 | K98: 정기예금 | L98: 50 | Q98: 0.0117039 | S98: =AVERAGE(0.0133,0.014) -> 0.01365 | Y98: 0.007544 | Z98: 0.0021 | AA98: 0.001 | AC98: =S98-Z98-AA98 -> 0.01055 | AD98: 0.011 | AE98: =IF(Y98="","",Y98) -> 0.007544 | AJ98: =IF(AG98="","N","Y") -> N | AL98: 1.5% 이상
A99: =IF(B99="","",IF((YEAR(B99)-YEAR(B98))=0,A98+1,1)) -> 43 | B99: 42865 | C99: 울산영업부 | D99: 차장 김정인 | F99: 석유공사 | G99: 42865 | H99: 42907 | I99: =H99-G99 -> 42 | J99: =TRUNC(I99/30,0) -> 1 | K99: 정기예금 | L99: 30 | Q99: 0.0098856 | S99: =AVERAGE(0.0113,0.0112) -> 0.01125 | Y99: 0.006262 | Z99: 0.0021 | AA99: 0.001 | AC99: =S99-Z99-AA99 -> 0.00815 | AD99: 0.009 | AE99: =IF(Y99="","",Y99) -> 0.006262 | AJ99: =IF(AG99="","N","Y") -> N
A100: =IF(B100="","",IF((YEAR(B100)-YEAR(B99))=0,A99+1,1)) -> 44 | B100: 42874 | C100: 서울영업부 | D100: 차장 이순정 | F100: 현대중공업 | G100: 42874 | H100: 42905 | I100: =H100-G100 -> 31 | J100: =TRUNC(I100/30,0) -> 1 | K100: MMDA | L100: 10 | Q100: 0.0092778 | S100: =AVERAGE(0.0099,0.0098) -> 0.00985 | Y100: 0.004346 | Z100: 0.0032 | AA100: 0.001 | AC100: =S100-Z100-AA100 -> 0.00565 | AD100: 0.006 | AE100: =IF(Y100="","",Y100) -> 0.004346 | AG100: 0.006 | AJ100: =IF(AG100="","N","Y") -> Y
A101: =IF(B101="","",IF((YEAR(B101)-YEAR(B100))=0,A100+1,1)) -> 45 | B101: 42874 | C101: 강남영업부 | D101: 과장 이진아 | F101: SK하이닉스 | G101: 42874 | H101: 42908 | I101: =H101-G101 -> 34 | J101: =TRUNC(I101/30,0) -> 1 | K101: MMDA | L101: 150 | Q101: 0.0092778 | S101: =AVERAGE(0.0099,0.0098) -> 0.00985 | Y101: 0.004346 | Z101: 0.0032 | AA101: 0.001 | AC101: =S101-Z101-AA101 -> 0.00565 | AD101: 0.0065 | AE101: =IF(Y101="","",Y101) -> 0.004346 | AG101: 0.0065 | AJ101: =IF(AG101="","N","Y") -> Y
...

Sheet 예금만기도래
A1: TODAY | B1: =TEXT(A2,"aaaa") -> 월요일 | D1: +1일 | E1: =TEXT(D2,"aaaa") -> 화요일 | G1: +2일 | H1: =TEXT(G2,"aaaa") -> 수요일 | J1: +3일 | K1: =TEXT(J2,"aaaa") -> 목요일 | M1: +4일 | N1: =TEXT(M2,"aaaa") -> 금요일 | P1: +5일 | Q1: =TEXT(P2,"aaaa") -> 토요일 | S1: +6일 | T1: =TEXT(S2,"aaaa") -> 일요일 | V1: +7일 | W1: =TEXT(V2,"aaaa") -> 월요일 | Y1: +8일 | Z1: =TEXT(Y2,"aaaa") -> 화요일 | AB1: +9일 | AC1: =TEXT(AB2,"aaaa") -> 수요일 | AF1: 만기일 | AG1: 시작일 | AH1: 업체명 | AI1: 금액 | AJ1: 금리 | AK1: 예금종류
A2: =TODAY() -> 46188 | B2: 예금종류 | C2: $ | D2: =$A$2+_xlfn.NUMBERVALUE(MID(D1,3,1)) -> 46189 | E2: 예금종류 | F2: $ | G2: =$A$2+_xlfn.NUMBERVALUE(MID(G1,3,1)) -> 46190 | H2: 예금종류 | I2: $ | J2: =$A$2+_xlfn.NUMBERVALUE(MID(J1,3,1)) -> 46191 | K2: 예금종류 | L2: $ | M2: =$A$2+_xlfn.NUMBERVALUE(MID(M1,3,1)) -> 46192 | N2: 예금종류 | O2: $ | P2: =$A$2+_xlfn.NUMBERVALUE(MID(P1,3,1)) -> 46193 | Q2: 예금종류 | R2: $ | S2: =$A$2+_xlfn.NUMBERVALUE(MID(S1,3,1)) -> 46194 | T2: 예금종류 | U2: $ | V2: =$A$2+_xlfn.NUMBERVALUE(MID(V1,3,1)) -> 46195 | W2: 예금종류 | X2: $ | Y2: =$A$2+_xlfn.NUMBERVALUE(MID(Y1,3,1)) -> 46196 | Z2: 예금종류 | AA2: $ | AB2: =$A$2+_xlfn.NUMBERVALUE(MID(AB1,3,1)) -> 46197 | AC2: 예금종류 | AD2: $ | AE2: ='(1)예금승인내역'!H632 -> 45313 | AF2: =VALUE(AE2) -> 45313 | AG2: ='(1)예금승인내역'!G632 -> 45280 | AH2: ='(1)예금승인내역'!F632 -> 주식회사 한국비앤씨 | AI2: ='(1)예금승인내역'!L632 -> 5 | AJ2: ='(1)예금승인내역'!AG632 -> 0.0525 | AK2: ='(1)예금승인내역'!K632 -> 정기예금
A3: {=IFERROR( INDEX($AH$2:$AH$9999,SMALL(IF($AF$2:$AF$9999=$A$2, ROW($AH$2:$AH$9999)-ROW($AH$2)+1),ROWS(A$3:$A3))),"")} -> ㈜이수스페셜티케미컬 | B3: {=IFERROR( INDEX($AK$2:$AK$9999,SMALL(IF($AF$2:$AF$9999=$A$2, ROW($AK$2:$AK$9999)-ROW($AK$2)+1),ROWS($A$3:B3))),"")} -> MMDA | C3: {=IFERROR( INDEX($AI$2:$AI$9999,SMALL(IF($AF$2:$AF$9999=$A$2, ROW($AI$2:$AI$9999)-ROW($AI$2)+1),ROWS($A$3:C3))),"")} -> 7.97 | D3: {=IFERROR( INDEX($AH$2:$AH$9999,SMALL(IF($AF$2:$AF$9999=$D$2, ROW($AH$2:$AH$9999)-ROW($AH$2)+1),ROWS($D$3:D3))),"")} -> ㈜ 동아홀딩스 | E3: {=IFERROR( INDEX($AK$2:$AK$9999,SMALL(IF($AF$2:$AF$9999=$D$2, ROW($AK$2:$AK$9999)-ROW($AK$2)+1),ROWS($D$3:E3))),"")} -> 정기예금 | F3: {=IFERROR( INDEX($AI$2:$AI$9999,SMALL(IF($AF$2:$AF$9999=$D$2, ROW($AI$2:$AI$9999)-ROW($AI$2)+1),ROWS($F$3:F3))),"")} -> 2.19 | G3: {=IFERROR( INDEX($AH$2:$AH$9999,SMALL(IF($AF$2:$AF$9999=$G$2, ROW($AH$2:$AH$9999)-ROW($AH$2)+1),ROWS($G$3:G3))),"")} -> 거림테크주식회사 | H3: {=IFERROR( INDEX($AK$2:$AK$9999,SMALL(IF($AF$2:$AF$9999=$G$2, ROW($AK$2:$AK$9999)-ROW($AK$2)+1),ROWS($G$3:H3))),"")} -> 정기예금 | I3: {=IFERROR( INDEX($AI$2:$AI$9999,SMALL(IF($AF$2:$AF$9999=$G$2, ROW($AI$2:$AI$9999)-ROW($AI$2)+1),ROWS($I$3:I3))),"")} -> 2 | J3: {=IFERROR( INDEX($AH$2:$AH$9999,SMALL(IF($AF$2:$AF$9999=$J$2, ROW($AH$2:$AH$9999)-ROW($AH$2)+1),ROWS($J$3:J3))),"")} | K3: {=IFERROR( INDEX($AK$2:$AK$9999,SMALL(IF($AF$2:$AF$9999=$J$2, ROW($AK$2:$AK$9999)-ROW($AK$2)+1),ROWS($J$3:K3))),"")} | L3: {=IFERROR( INDEX($AI$2:$AI$9999,SMALL(IF($AF$2:$AF$9999=$J$2, ROW($AI$2:$AI$9999)-ROW($AI$2)+1),ROWS($L$3:L3))),"")} | M3: {=IFERROR( INDEX($AH$2:$AH$9999,SMALL(IF($AF$2:$AF$9999=$M$2, ROW($AH$2:$AH$9999)-ROW($AH$2)+1),ROWS($M$3:M3))),"")} -> ㈜일지테크 | N3: {=IFERROR( INDEX($AK$2:$AK$9999,SMALL(IF($AF$2:$AF$9999=$M$2, ROW($AK$2:$AK$9999)-ROW($AK$2)+1),ROWS($M$3:N3))),"")} -> MMDA | O3: {=IFERROR( INDEX($AI$2:$AI$9999,SMALL(IF($AF$2:$AF$9999=$M$2, ROW($AI$2:$AI$9999)-ROW($AI$2)+1),ROWS($O$3:O3))),"")} -> 11.11 | P3: {=IFERROR( INDEX($AH$2:$AH$9999,SMALL(IF($AF$2:$AF$9999=$P$2, ROW($AH$2:$AH$9999)-ROW($AH$2)+1),ROWS($P$3:P3))),"")} | Q3: {=IFERROR( INDEX($AK$2:$AK$9999,SMALL(IF($AF$2:$AF$9999=$P$2, ROW($AK$2:$AK$9999)-ROW($AK$2)+1),ROWS($P$3:Q3))),"")} | R3: {=IFERROR( INDEX($AI$2:$AI$9999,SMALL(IF($AF$2:$AF$9999=$P$2, ROW($AI$2:$AI$9999)-ROW($AI$2)+1),ROWS($R$3:R3))),"")} | S3: {=IFERROR( INDEX($AH$2:$AH$9999,SMALL(IF($AF$2:$AF$9999=$S$2, ROW($AH$2:$AH$9999)-ROW($AH$2)+1),ROWS($S$3:S3))),"")} | T3: {=IFERROR( INDEX($AK$2:$AK$9999,SMALL(IF($AF$2:$AF$9999=$S$2, ROW($AK$2:$AK$9999)-ROW($AK$2)+1),ROWS($S$3:T3))),"")} | U3: {=IFERROR( INDEX($AI$2:$AI$9999,SMALL(IF($AF$2:$AF$9999=$S$2, ROW($AI$2:$AI$9999)-ROW($AI$2)+1),ROWS($U$3:U3))),"")} | V3: {=IFERROR( INDEX($AH$2:$AH$9999,SMALL(IF($AF$2:$AF$9999=$V$2, ROW($AH$2:$AH$9999)-ROW($AH$2)+1),ROWS($V$3:V3))),"")} -> 한국비앤씨㈜ | W3: {=IFERROR( INDEX($AK$2:$AK$9999,SMALL(IF($AF$2:$AF$9999=$V$2, ROW($AK$2:$AK$9999)-ROW($AK$2)+1),ROWS($V$3:W3))),"")} -> MMDA | X3: {=IFERROR( INDEX($AI$2:$AI$9999,SMALL(IF($AF$2:$AF$9999=$V$2, ROW($AI$2:$AI$9999)-ROW($AI$2)+1),ROWS($X$3:X3))),"")} -> 8.67 | Y3: {=IFERROR( INDEX($AH$2:$AH$9999,SMALL(IF($AF$2:$AF$9999=$Y$2, ROW($AH$2:$AH$9999)-ROW($AH$2)+1),ROWS($Y$3:Y3))),"")} -> ㈜비앤에프 | Z3: {=IFERROR( INDEX($AK$2:$AK$9999,SMALL(IF($AF$2:$AF$9999=$Y$2, ROW($AK$2:$AK$9999)-ROW($AK$2)+1),ROWS($Y$3:Z3))),"")} -> 정기예금 | AA3: {=IFERROR( INDEX($AI$2:$AI$9999,SMALL(IF($AF$2:$AF$9999=$Y$2, ROW($AI$2:$AI$9999)-ROW($AI$2)+1),ROWS($AA$3:AA3))),"")} -> 1 | AB3: {=IFERROR( INDEX($AH$2:$AH$9999,SMALL(IF($AF$2:$AF$9999=$AB$2, ROW($AH$2:$AH$9999)-ROW($AH$2)+1),ROWS($AB$3:AB3))),"")} | AC3: {=IFERROR( INDEX($AK$2:$AK$9999,SMALL(IF($AF$2:$AF$9999=$AB$2, ROW($AK$2:$AK$9999)-ROW($AK$2)+1),ROWS($AB$3:AC3))),"")} | AD3: {=IFERROR( INDEX($AI$2:$AI$9999,SMALL(IF($AF$2:$AF$9999=$AB$2, ROW($AI$2:$AI$9999)-ROW($AI$2)+1),ROWS($AD$3:AD3))),"")} | AE3: ='(1)예금승인내역'!H633 -> 45313 | AF3: =VALUE(AE3) -> 45313 | AG3: ='(1)예금승인내역'!G633 -> 45280 | AH3: ='(1)예금승인내역'!F633 -> 주식회사 한국비앤씨 | AI3: ='(1)예금승인내역'!L633 -> 5 | AJ3: ='(1)예금승인내역'!AG633 -> 0.0525 | AK3: ='(1)예금승인내역'!K633 -> 정기예금
A4: {=IFERROR( INDEX($AH$2:$AH$9999,SMALL(IF($AF$2:$AF$9999=$A$2, ROW($AH$2:$AH$9999)-ROW($AH$2)+1),ROWS(A$3:$A4))),"")} -> ㈜현대그린푸드 | B4: {=IFERROR( INDEX($AK$2:$AK$9999,SMALL(IF($AF$2:$AF$9999=$A$2, ROW($AK$2:$AK$9999)-ROW($AK$2)+1),ROWS($A$3:B4))),"")} -> MMDA | C4: {=IFERROR( INDEX($AI$2:$AI$9999,SMALL(IF($AF$2:$AF$9999=$A$2, ROW($AI$2:$AI$9999)-ROW($AI$2)+1),ROWS($A$3:C4))),"")} -> 1.43 | D4: {=IFERROR( INDEX($AH$2:$AH$9999,SMALL(IF($AF$2:$AF$9999=$D$2, ROW($AH$2:$AH$9999)-ROW($AH$2)+1),ROWS($D$3:D4))),"")} -> 해내다컨트리클럽 | E4: {=IFERROR( INDEX($AK$2:$AK$9999,SMALL(IF($AF$2:$AF$9999=$D$2, ROW($AK$2:$AK$9999)-ROW($AK$2)+1),ROWS($D$3:E4))),"")} -> 정기예금 | F4: {=IFERROR( INDEX($AI$2:$AI$9999,SMALL(IF($AF$2:$AF$9999=$D$2, ROW($AI$2:$AI$9999)-ROW($AI$2)+1),ROWS($F$3:F4))),"")} -> 3.65 | G4: {=IFERROR( INDEX($AH$2:$AH$9999,SMALL(IF($AF$2:$AF$9999=$G$2, ROW($AH$2:$AH$9999)-ROW($AH$2)+1),ROWS($G$3:G4))),"")} | H4: {=IFERROR( INDEX($AK$2:$AK$9999,SMALL(IF($AF$2:$AF$9999=$G$2, ROW($AK$2:$AK$9999)-ROW($AK$2)+1),ROWS($G$3:H4))),"")} | I4: {=IFERROR( INDEX($AI$2:$AI$9999,SMALL(IF($AF$2:$AF$9999=$G$2, ROW($AI$2:$AI$9999)-ROW($AI$2)+1),ROWS($I$3:I4))),"")} | J4: {=IFERROR( INDEX($AH$2:$AH$9999,SMALL(IF($AF$2:$AF$9999=$J$2, ROW($AH$2:$AH$9999)-ROW($AH$2)+1),ROWS($J$3:J4))),"")} | K4: {=IFERROR( INDEX($AK$2:$AK$9999,SMALL(IF($AF$2:$AF$9999=$J$2, ROW($AK$2:$AK$9999)-ROW($AK$2)+1),ROWS($J$3:K4))),"")} | L4: {=IFERROR( INDEX($AI$2:$AI$9999,SMALL(IF($AF$2:$AF$9999=$J$2, ROW($AI$2:$AI$9999)-ROW($AI$2)+1),ROWS($L$3:L4))),"")} | M4: {=IFERROR( INDEX($AH$2:$AH$9999,SMALL(IF($AF$2:$AF$9999=$M$2, ROW($AH$2:$AH$9999)-ROW($AH$2)+1),ROWS($M$3:M4))),"")} -> ㈜약진통상 | N4: {=IFERROR( INDEX($AK$2:$AK$9999,SMALL(IF($AF$2:$AF$9999=$M$2, ROW($AK$2:$AK$9999)-ROW($AK$2)+1),ROWS($M$3:N4))),"")} -> MMDA | O4: {=IFERROR( INDEX($AI$2:$AI$9999,SMALL(IF($AF$2:$AF$9999=$M$2, ROW($AI$2:$AI$9999)-ROW($AI$2)+1),ROWS($O$3:O4))),"")} -> 12.39 | P4: {=IFERROR( INDEX($AH$2:$AH$9999,SMALL(IF($AF$2:$AF$9999=$P$2, ROW($AH$2:$AH$9999)-ROW($AH$2)+1),ROWS($P$3:P4))),"")} | Q4: {=IFERROR( INDEX($AK$2:$AK$9999,SMALL(IF($AF$2:$AF$9999=$P$2, ROW($AK$2:$AK$9999)-ROW($AK$2)+1),ROWS($P$3:Q4))),"")} | R4: {=IFERROR( INDEX($AI$2:$AI$9999,SMALL(IF($AF$2:$AF$9999=$P$2, ROW($AI$2:$AI$9999)-ROW($AI$2)+1),ROWS($R$3:R4))),"")} | S4: {=IFERROR( INDEX($AH$2:$AH$9999,SMALL(IF($AF$2:$AF$9999=$S$2, ROW($AH$2:$AH$9999)-ROW($AH$2)+1),ROWS($S$3:S4))),"")} | T4: {=IFERROR( INDEX($AK$2:$AK$9999,SMALL(IF($AF$2:$AF$9999=$S$2, ROW($AK$2:$AK$9999)-ROW($AK$2)+1),ROWS($S$3:T4))),"")} | U4: {=IFERROR( INDEX($AI$2:$AI$9999,SMALL(IF($AF$2:$AF$9999=$S$2, ROW($AI$2:$AI$9999)-ROW($AI$2)+1),ROWS($U$3:U4))),"")} | V4: {=IFERROR( INDEX($AH$2:$AH$9999,SMALL(IF($AF$2:$AF$9999=$V$2, ROW($AH$2:$AH$9999)-ROW($AH$2)+1),ROWS($V$3:V4))),"")} -> 더스킨팩토리 | W4: {=IFERROR( INDEX($AK$2:$AK$9999,SMALL(IF($AF$2:$AF$9999=$V$2, ROW($AK$2:$AK$9999)-ROW($AK$2)+1),ROWS($V$3:W4))),"")} -> 정기예금 | X4: {=IFERROR( INDEX($AI$2:$AI$9999,SMALL(IF($AF$2:$AF$9999=$V$2, ROW($AI$2:$AI$9999)-ROW($AI$2)+1),ROWS($X$3:X4))),"")} -> 1 | Y4: {=IFERROR( INDEX($AH$2:$AH$9999,SMALL(IF($AF$2:$AF$9999=$Y$2, ROW($AH$2:$AH$9999)-ROW($AH$2)+1),ROWS($Y$3:Y4))),"")} -> ㈜비앤에프 | Z4: {=IFERROR( INDEX($AK$2:$AK$9999,SMALL(IF($AF$2:$AF$9999=$Y$2, ROW($AK$2:$AK$9999)-ROW($AK$2)+1),ROWS($Y$3:Z4))),"")} -> 정기예금 | AA4: {=IFERROR( INDEX($AI$2:$AI$9999,SMALL(IF($AF$2:$AF$9999=$Y$2, ROW($AI$2:$AI$9999)-ROW($AI$2)+1),ROWS($AA$3:AA4))),"")} -> 1 | AB4: {=IFERROR( INDEX($AH$2:$AH$9999,SMALL(IF($AF$2:$AF$9999=$AB$2, ROW($AH$2:$AH$9999)-ROW($AH$2)+1),ROWS($AB$3:AB4))),"")} | AC4: {=IFERROR( INDEX($AK$2:$AK$9999,SMALL(IF($AF$2:$AF$9999=$AB$2, ROW($AK$2:$AK$9999)-ROW($AK$2)+1),ROWS($AB$3:AC4))),"")} | AD4: {=IFERROR( INDEX($AI$2:$AI$9999,SMALL(IF($AF$2:$AF$9999=$AB$2, ROW($AI$2:$AI$9999)-ROW($AI$2)+1),ROWS($AD$3:AD4))),"")} | AE4: ='(1)예금승인내역'!H634 -> 45313 | AF4: =VALUE(AE4) -> 45313 | AG4: ='(1)예금승인내역'!G634 -> 45280 | AH4: ='(1)예금승인내역'!F634 -> ㈜대우로지스틱스 | AI4: ='(1)예금승인내역'!L634 -> 1 | AJ4: ='(1)예금승인내역'!AG634 -> 0.0435 | AK4: ='(1)예금승인내역'!K634 -> MMDA
A5: {=IFERROR( INDEX($AH$2:$AH$9999,SMALL(IF($AF$2:$AF$9999=$A$2, ROW($AH$2:$AH$9999)-ROW($AH$2)+1),ROWS(A$3:$A5))),"")} -> 와이엠에스에이 | B5: {=IFERROR( INDEX($AK$2:$AK$9999,SMALL(IF($AF$2:$AF$9999=$A$2, ROW($AK$2:$AK$9999)-ROW($AK$2)+1),ROWS($A$3:B5))),"")} -> MMDA | C5: {=IFERROR( INDEX($AI$2:$AI$9999,SMALL(IF($AF$2:$AF$9999=$A$2, ROW($AI$2:$AI$9999)-ROW($AI$2)+1),ROWS($A$3:C5))),"")} -> 4.3 | D5: {=IFERROR( INDEX($AH$2:$AH$9999,SMALL(IF($AF$2:$AF$9999=$D$2, ROW($AH$2:$AH$9999)-ROW($AH$2)+1),ROWS($D$3:D5))),"")} -> 거림테크주식회사 | E5: {=IFERROR( INDEX($AK$2:$AK$9999,SMALL(IF($AF$2:$AF$9999=$D$2, ROW($AK$2:$AK$9999)-ROW($AK$2)+1),ROWS($D$3:E5))),"")} -> 정기예금 | F5: {=IFERROR( INDEX($AI$2:$AI$9999,SMALL(IF($AF$2:$AF$9999=$D$2, ROW($AI$2:$AI$9999)-ROW($AI$2)+1),ROWS($F$3:F5))),"")} -> 2 | G5: {=IFERROR( INDEX($AH$2:$AH$9999,SMALL(IF($AF$2:$AF$9999=$G$2, ROW($AH$2:$AH$9999)-ROW($AH$2)+1),ROWS($G$3:G5))),"")} | H5: {=IFERROR( INDEX($AK$2:$AK$9999,SMALL(IF($AF$2:$AF$9999=$G$2, ROW($AK$2:$AK$9999)-ROW($AK$2)+1),ROWS($G$3:H5))),"")} | I5: {=IFERROR( INDEX($AI$2:$AI$9999,SMALL(IF($AF$2:$AF$9999=$G$2, ROW($AI$2:$AI$9999)-ROW($AI$2)+1),ROWS($I$3:I5))),"")} | J5: {=IFERROR( INDEX($AH$2:$AH$9999,SMALL(IF($AF$2:$AF$9999=$J$2, ROW($AH$2:$AH$9999)-ROW($AH$2)+1),ROWS($J$3:J5))),"")} | K5: {=IFERROR( INDEX($AK$2:$AK$9999,SMALL(IF($AF$2:$AF$9999=$J$2, ROW($AK$2:$AK$9999)-ROW($AK$2)+1),ROWS($J$3:K5))),"")} | L5: {=IFERROR( INDEX($AI$2:$AI$9999,SMALL(IF($AF$2:$AF$9999=$J$2, ROW($AI$2:$AI$9999)-ROW($AI$2)+1),ROWS($L$3:L5))),"")} | M5: {=IFERROR( INDEX($AH$2:$AH$9999,SMALL(IF($AF$2:$AF$9999=$M$2, ROW($AH$2:$AH$9999)-ROW($AH$2)+1),ROWS($M$3:M5))),"")} -> ㈜약진통상 | N5: {=IFERROR( INDEX($AK$2:$AK$9999,SMALL(IF($AF$2:$AF$9999=$M$2, ROW($AK$2:$AK$9999)-ROW($AK$2)+1),ROWS($M$3:N5))),"")} -> MMDA | O5: {=IFERROR( INDEX($AI$2:$AI$9999,SMALL(IF($AF$2:$AF$9999=$M$2, ROW($AI$2:$AI$9999)-ROW($AI$2)+1),ROWS($O$3:O5))),"")} -> 12.39 | P5: {=IFERROR( INDEX($AH$2:$AH$9999,SMALL(IF($AF$2:$AF$9999=$P$2, ROW($AH$2:$AH$9999)-ROW($AH$2)+1),ROWS($P$3:P5))),"")} | Q5: {=IFERROR( INDEX($AK$2:$AK$9999,SMALL(IF($AF$2:$AF$9999=$P$2, ROW($AK$2:$AK$9999)-ROW($AK$2)+1),ROWS($P$3:Q5))),"")} | R5: {=IFERROR( INDEX($AI$2:$AI$9999,SMALL(IF($AF$2:$AF$9999=$P$2, ROW($AI$2:$AI$9999)-ROW($AI$2)+1),ROWS($R$3:R5))),"")} | S5: {=IFERROR( INDEX($AH$2:$AH$9999,SMALL(IF($AF$2:$AF$9999=$S$2, ROW($AH$2:$AH$9999)-ROW($AH$2)+1),ROWS($S$3:S5))),"")} | T5: {=IFERROR( INDEX($AK$2:$AK$9999,SMALL(IF($AF$2:$AF$9999=$S$2, ROW($AK$2:$AK$9999)-ROW($AK$2)+1),ROWS($S$3:T5))),"")} | U5: {=IFERROR( INDEX($AI$2:$AI$9999,SMALL(IF($AF$2:$AF$9999=$S$2, ROW($AI$2:$AI$9999)-ROW($AI$2)+1),ROWS($U$3:U5))),"")} | V5: {=IFERROR( INDEX($AH$2:$AH$9999,SMALL(IF($AF$2:$AF$9999=$V$2, ROW($AH$2:$AH$9999)-ROW($AH$2)+1),ROWS($V$3:V5))),"")} | W5: {=IFERROR( INDEX($AK$2:$AK$9999,SMALL(IF($AF$2:$AF$9999=$V$2, ROW($AK$2:$AK$9999)-ROW($AK$2)+1),ROWS($V$3:W5))),"")} | X5: {=IFERROR( INDEX($AI$2:$AI$9999,SMALL(IF($AF$2:$AF$9999=$V$2, ROW($AI$2:$AI$9999)-ROW($AI$2)+1),ROWS($X$3:X5))),"")} | Y5: {=IFERROR( INDEX($AH$2:$AH$9999,SMALL(IF($AF$2:$AF$9999=$Y$2, ROW($AH$2:$AH$9999)-ROW($AH$2)+1),ROWS($Y$3:Y5))),"")} | Z5: {=IFERROR( INDEX($AK$2:$AK$9999,SMALL(IF($AF$2:$AF$9999=$Y$2, ROW($AK$2:$AK$9999)-ROW($AK$2)+1),ROWS($Y$3:Z5))),"")} | AA5: {=IFERROR( INDEX($AI$2:$AI$9999,SMALL(IF($AF$2:$AF$9999=$Y$2, ROW($AI$2:$AI$9999)-ROW($AI$2)+1),ROWS($AA$3:AA5))),"")} | AB5: {=IFERROR( INDEX($AH$2:$AH$9999,SMALL(IF($AF$2:$AF$9999=$AB$2, ROW($AH$2:$AH$9999)-ROW($AH$2)+1),ROWS($AB$3:AB5))),"")} | AC5: {=IFERROR( INDEX($AK$2:$AK$9999,SMALL(IF($AF$2:$AF$9999=$AB$2, ROW($AK$2:$AK$9999)-ROW($AK$2)+1),ROWS($AB$3:AC5))),"")} | AD5: {=IFERROR( INDEX($AI$2:$AI$9999,SMALL(IF($AF$2:$AF$9999=$AB$2, ROW($AI$2:$AI$9999)-ROW($AI$2)+1),ROWS($AD$3:AD5))),"")} | AE5: ='(1)예금승인내역'!H635 -> 45659 | AF5: =VALUE(AE5) -> 45659 | AG5: ='(1)예금승인내역'!G635 -> 45293 | AH5: ='(1)예금승인내역'!F635 -> 윤만수 | AI5: ='(1)예금승인내역'!L635 -> 1 | AJ5: ='(1)예금승인내역'!AG635 -> 0.05 | AK5: ='(1)예금승인내역'!K635 -> 정기예금
A6: {=IFERROR( INDEX($AH$2:$AH$9999,SMALL(IF($AF$2:$AF$9999=$A$2, ROW($AH$2:$AH$9999)-ROW($AH$2)+1),ROWS(A$3:$A6))),"")} -> 엘티메탈 | B6: {=IFERROR( INDEX($AK$2:$AK$9999,SMALL(IF($AF$2:$AF$9999=$A$2, ROW($AK$2:$AK$9999)-ROW($AK$2)+1),ROWS($A$3:B6))),"")} -> MMDA | C6: {=IFERROR( INDEX($AI$2:$AI$9999,SMALL(IF($AF$2:$AF$9999=$A$2, ROW($AI$2:$AI$9999)-ROW($AI$2)+1),ROWS($A$3:C6))),"")} -> 7 | D6: {=IFERROR( INDEX($AH$2:$AH$9999,SMALL(IF($AF$2:$AF$9999=$D$2, ROW($AH$2:$AH$9999)-ROW($AH$2)+1),ROWS($D$3:D6))),"")} | E6: {=IFERROR( INDEX($AK$2:$AK$9999,SMALL(IF($AF$2:$AF$9999=$D$2, ROW($AK$2:$AK$9999)-ROW($AK$2)+1),ROWS($D$3:E6))),"")} | F6: {=IFERROR( INDEX($AI$2:$AI$9999,SMALL(IF($AF$2:$AF$9999=$D$2, ROW($AI$2:$AI$9999)-ROW($AI$2)+1),ROWS($F$3:F6))),"")} | G6: {=IFERROR( INDEX($AH$2:$AH$9999,SMALL(IF($AF$2:$AF$9999=$G$2, ROW($AH$2:$AH$9999)-ROW($AH$2)+1),ROWS($G$3:G6))),"")} | H6: {=IFERROR( INDEX($AK$2:$AK$9999,SMALL(IF($AF$2:$AF$9999=$G$2, ROW($AK$2:$AK$9999)-ROW($AK$2)+1),ROWS($G$3:H6))),"")} | I6: {=IFERROR( INDEX($AI$2:$AI$9999,SMALL(IF($AF$2:$AF$9999=$G$2, ROW($AI$2:$AI$9999)-ROW($AI$2)+1),ROWS($I$3:I6))),"")} | J6: {=IFERROR( INDEX($AH$2:$AH$9999,SMALL(IF($AF$2:$AF$9999=$J$2, ROW($AH$2:$AH$9999)-ROW($AH$2)+1),ROWS($J$3:J6))),"")} | K6: {=IFERROR( INDEX($AK$2:$AK$9999,SMALL(IF($AF$2:$AF$9999=$J$2, ROW($AK$2:$AK$9999)-ROW($AK$2)+1),ROWS($J$3:K6))),"")} | L6: {=IFERROR( INDEX($AI$2:$AI$9999,SMALL(IF($AF$2:$AF$9999=$J$2, ROW($AI$2:$AI$9999)-ROW($AI$2)+1),ROWS($L$3:L6))),"")} | M6: {=IFERROR( INDEX($AH$2:$AH$9999,SMALL(IF($AF$2:$AF$9999=$M$2, ROW($AH$2:$AH$9999)-ROW($AH$2)+1),ROWS($M$3:M6))),"")} -> 대원지에스아이 | N6: {=IFERROR( INDEX($AK$2:$AK$9999,SMALL(IF($AF$2:$AF$9999=$M$2, ROW($AK$2:$AK$9999)-ROW($AK$2)+1),ROWS($M$3:N6))),"")} -> 정기예금 | O6: {=IFERROR( INDEX($AI$2:$AI$9999,SMALL(IF($AF$2:$AF$9999=$M$2, ROW($AI$2:$AI$9999)-ROW($AI$2)+1),ROWS($O$3:O6))),"")} -> 1.5 | P6: {=IFERROR( INDEX($AH$2:$AH$9999,SMALL(IF($AF$2:$AF$9999=$P$2, ROW($AH$2:$AH$9999)-ROW($AH$2)+1),ROWS($P$3:P6))),"")} | Q6: {=IFERROR( INDEX($AK$2:$AK$9999,SMALL(IF($AF$2:$AF$9999=$P$2, ROW($AK$2:$AK$9999)-ROW($AK$2)+1),ROWS($P$3:Q6))),"")} | R6: {=IFERROR( INDEX($AI$2:$AI$9999,SMALL(IF($AF$2:$AF$9999=$P$2, ROW($AI$2:$AI$9999)-ROW($AI$2)+1),ROWS($R$3:R6))),"")} | S6: {=IFERROR( INDEX($AH$2:$AH$9999,SMALL(IF($AF$2:$AF$9999=$S$2, ROW($AH$2:$AH$9999)-ROW($AH$2)+1),ROWS($S$3:S6))),"")} | T6: {=IFERROR( INDEX($AK$2:$AK$9999,SMALL(IF($AF$2:$AF$9999=$S$2, ROW($AK$2:$AK$9999)-ROW($AK$2)+1),ROWS($S$3:T6))),"")} | U6: {=IFERROR( INDEX($AI$2:$AI$9999,SMALL(IF($AF$2:$AF$9999=$S$2, ROW($AI$2:$AI$9999)-ROW($AI$2)+1),ROWS($U$3:U6))),"")} | V6: {=IFERROR( INDEX($AH$2:$AH$9999,SMALL(IF($AF$2:$AF$9999=$V$2, ROW($AH$2:$AH$9999)-ROW($AH$2)+1),ROWS($V$3:V6))),"")} | W6: {=IFERROR( INDEX($AK$2:$AK$9999,SMALL(IF($AF$2:$AF$9999=$V$2, ROW($AK$2:$AK$9999)-ROW($AK$2)+1),ROWS($V$3:W6))),"")} | X6: {=IFERROR( INDEX($AI$2:$AI$9999,SMALL(IF($AF$2:$AF$9999=$V$2, ROW($AI$2:$AI$9999)-ROW($AI$2)+1),ROWS($X$3:X6))),"")} | Y6: {=IFERROR( INDEX($AH$2:$AH$9999,SMALL(IF($AF$2:$AF$9999=$Y$2, ROW($AH$2:$AH$9999)-ROW($AH$2)+1),ROWS($Y$3:Y6))),"")} | Z6: {=IFERROR( INDEX($AK$2:$AK$9999,SMALL(IF($AF$2:$AF$9999=$Y$2, ROW($AK$2:$AK$9999)-ROW($AK$2)+1),ROWS($Y$3:Z6))),"")} | AA6: {=IFERROR( INDEX($AI$2:$AI$9999,SMALL(IF($AF$2:$AF$9999=$Y$2, ROW($AI$2:$AI$9999)-ROW($AI$2)+1),ROWS($AA$3:AA6))),"")} | AB6: {=IFERROR( INDEX($AH$2:$AH$9999,SMALL(IF($AF$2:$AF$9999=$AB$2, ROW($AH$2:$AH$9999)-ROW($AH$2)+1),ROWS($AB$3:AB6))),"")} | AC6: {=IFERROR( INDEX($AK$2:$AK$9999,SMALL(IF($AF$2:$AF$9999=$AB$2, ROW($AK$2:$AK$9999)-ROW($AK$2)+1),ROWS($AB$3:AC6))),"")} | AD6: {=IFERROR( INDEX($AI$2:$AI$9999,SMALL(IF($AF$2:$AF$9999=$AB$2, ROW($AI$2:$AI$9999)-ROW($AI$2)+1),ROWS($AD$3:AD6))),"")} | AE6: ='(1)예금승인내역'!H636 -> 45659 | AF6: =VALUE(AE6) -> 45659 | AG6: ='(1)예금승인내역'!G636 -> 45293 | AH6: ='(1)예금승인내역'!F636 -> 윤만수 | AI6: ='(1)예금승인내역'!L636 -> 0.5 | AJ6: ='(1)예금승인내역'!AG636 -> 0.05 | AK6: ='(1)예금승인내역'!K636 -> 정기예금
A7: {=IFERROR( INDEX($AH$2:$AH$9999,SMALL(IF($AF$2:$AF$9999=$A$2, ROW($AH$2:$AH$9999)-ROW($AH$2)+1),ROWS(A$3:$A7))),"")} | B7: {=IFERROR( INDEX($AK$2:$AK$9999,SMALL(IF($AF$2:$AF$9999=$A$2, ROW($AK$2:$AK$9999)-ROW($AK$2)+1),ROWS($A$3:B7))),"")} | C7: {=IFERROR( INDEX($AI$2:$AI$9999,SMALL(IF($AF$2:$AF$9999=$A$2, ROW($AI$2:$AI$9999)-ROW($AI$2)+1),ROWS($A$3:C7))),"")} | D7: {=IFERROR( INDEX($AH$2:$AH$9999,SMALL(IF($AF$2:$AF$9999=$D$2, ROW($AH$2:$AH$9999)-ROW($AH$2)+1),ROWS($D$3:D7))),"")} | E7: {=IFERROR( INDEX($AK$2:$AK$9999,SMALL(IF($AF$2:$AF$9999=$D$2, ROW($AK$2:$AK$9999)-ROW($AK$2)+1),ROWS($D$3:E7))),"")} | F7: {=IFERROR( INDEX($AI$2:$AI$9999,SMALL(IF($AF$2:$AF$9999=$D$2, ROW($AI$2:$AI$9999)-ROW($AI$2)+1),ROWS($F$3:F7))),"")} | G7: {=IFERROR( INDEX($AH$2:$AH$9999,SMALL(IF($AF$2:$AF$9999=$G$2, ROW($AH$2:$AH$9999)-ROW($AH$2)+1),ROWS($G$3:G7))),"")} | H7: {=IFERROR( INDEX($AK$2:$AK$9999,SMALL(IF($AF$2:$AF$9999=$G$2, ROW($AK$2:$AK$9999)-ROW($AK$2)+1),ROWS($G$3:H7))),"")} | I7: {=IFERROR( INDEX($AI$2:$AI$9999,SMALL(IF($AF$2:$AF$9999=$G$2, ROW($AI$2:$AI$9999)-ROW($AI$2)+1),ROWS($I$3:I7))),"")} | J7: {=IFERROR( INDEX($AH$2:$AH$9999,SMALL(IF($AF$2:$AF$9999=$J$2, ROW($AH$2:$AH$9999)-ROW($AH$2)+1),ROWS($J$3:J7))),"")} | K7: {=IFERROR( INDEX($AK$2:$AK$9999,SMALL(IF($AF$2:$AF$9999=$J$2, ROW($AK$2:$AK$9999)-ROW($AK$2)+1),ROWS($J$3:K7))),"")} | L7: {=IFERROR( INDEX($AI$2:$AI$9999,SMALL(IF($AF$2:$AF$9999=$J$2, ROW($AI$2:$AI$9999)-ROW($AI$2)+1),ROWS($L$3:L7))),"")} | M7: {=IFERROR( INDEX($AH$2:$AH$9999,SMALL(IF($AF$2:$AF$9999=$M$2, ROW($AH$2:$AH$9999)-ROW($AH$2)+1),ROWS($M$3:M7))),"")} -> ㈜비알팜 | N7: {=IFERROR( INDEX($AK$2:$AK$9999,SMALL(IF($AF$2:$AF$9999=$M$2, ROW($AK$2:$AK$9999)-ROW($AK$2)+1),ROWS($M$3:N7))),"")} -> MMDA | O7: {=IFERROR( INDEX($AI$2:$AI$9999,SMALL(IF($AF$2:$AF$9999=$M$2, ROW($AI$2:$AI$9999)-ROW($AI$2)+1),ROWS($O$3:O7))),"")} -> 5.73 | P7: {=IFERROR( INDEX($AH$2:$AH$9999,SMALL(IF($AF$2:$AF$9999=$P$2, ROW($AH$2:$AH$9999)-ROW($AH$2)+1),ROWS($P$3:P7))),"")} | Q7: {=IFERROR( INDEX($AK$2:$AK$9999,SMALL(IF($AF$2:$AF$9999=$P$2, ROW($AK$2:$AK$9999)-ROW($AK$2)+1),ROWS($P$3:Q7))),"")} | R7: {=IFERROR( INDEX($AI$2:$AI$9999,SMALL(IF($AF$2:$AF$9999=$P$2, ROW($AI$2:$AI$9999)-ROW($AI$2)+1),ROWS($R$3:R7))),"")} | S7: {=IFERROR( INDEX($AH$2:$AH$9999,SMALL(IF($AF$2:$AF$9999=$S$2, ROW($AH$2:$AH$9999)-ROW($AH$2)+1),ROWS($S$3:S7))),"")} | T7: {=IFERROR( INDEX($AK$2:$AK$9999,SMALL(IF($AF$2:$AF$9999=$S$2, ROW($AK$2:$AK$9999)-ROW($AK$2)+1),ROWS($S$3:T7))),"")} | U7: {=IFERROR( INDEX($AI$2:$AI$9999,SMALL(IF($AF$2:$AF$9999=$S$2, ROW($AI$2:$AI$9999)-ROW($AI$2)+1),ROWS($U$3:U7))),"")} | V7: {=IFERROR( INDEX($AH$2:$AH$9999,SMALL(IF($AF$2:$AF$9999=$V$2, ROW($AH$2:$AH$9999)-ROW($AH$2)+1),ROWS($V$3:V7))),"")} | W7: {=IFERROR( INDEX($AK$2:$AK$9999,SMALL(IF($AF$2:$AF$9999=$V$2, ROW($AK$2:$AK$9999)-ROW($AK$2)+1),ROWS($V$3:W7))),"")} | X7: {=IFERROR( INDEX($AI$2:$AI$9999,SMALL(IF($AF$2:$AF$9999=$V$2, ROW($AI$2:$AI$9999)-ROW($AI$2)+1),ROWS($X$3:X7))),"")} | Y7: {=IFERROR( INDEX($AH$2:$AH$9999,SMALL(IF($AF$2:$AF$9999=$Y$2, ROW($AH$2:$AH$9999)-ROW($AH$2)+1),ROWS($Y$3:Y7))),"")} | Z7: {=IFERROR( INDEX($AK$2:$AK$9999,SMALL(IF($AF$2:$AF$9999=$Y$2, ROW($AK$2:$AK$9999)-ROW($AK$2)+1),ROWS($Y$3:Z7))),"")} | AA7: {=IFERROR( INDEX($AI$2:$AI$9999,SMALL(IF($AF$2:$AF$9999=$Y$2, ROW($AI$2:$AI$9999)-ROW($AI$2)+1),ROWS($AA$3:AA7))),"")} | AB7: {=IFERROR( INDEX($AH$2:$AH$9999,SMALL(IF($AF$2:$AF$9999=$AB$2, ROW($AH$2:$AH$9999)-ROW($AH$2)+1),ROWS($AB$3:AB7))),"")} | AC7: {=IFERROR( INDEX($AK$2:$AK$9999,SMALL(IF($AF$2:$AF$9999=$AB$2, ROW($AK$2:$AK$9999)-ROW($AK$2)+1),ROWS($AB$3:AC7))),"")} | AD7: {=IFERROR( INDEX($AI$2:$AI$9999,SMALL(IF($AF$2:$AF$9999=$AB$2, ROW($AI$2:$AI$9999)-ROW($AI$2)+1),ROWS($AD$3:AD7))),"")} | AE7: ='(1)예금승인내역'!H637 -> 45335 | AF7: =VALUE(AE7) -> 45335 | AG7: ='(1)예금승인내역'!G637 -> 45302 | AH7: ='(1)예금승인내역'!F637 -> 한국비철㈜ | AI7: ='(1)예금승인내역'!L637 -> 8.59 | AJ7: ='(1)예금승인내역'!AG637 -> 0.043 | AK7: ='(1)예금승인내역'!K637 -> MMDA
A8: {=IFERROR( INDEX($AH$2:$AH$9999,SMALL(IF($AF$2:$AF$9999=$A$2, ROW($AH$2:$AH$9999)-ROW($AH$2)+1),ROWS(A$3:$A8))),"")} | B8: {=IFERROR( INDEX($AK$2:$AK$9999,SMALL(IF($AF$2:$AF$9999=$A$2, ROW($AK$2:$AK$9999)-ROW($AK$2)+1),ROWS($A$3:B8))),"")} | C8: {=IFERROR( INDEX($AI$2:$AI$9999,SMALL(IF($AF$2:$AF$9999=$A$2, ROW($AI$2:$AI$9999)-ROW($AI$2)+1),ROWS($A$3:C8))),"")} | D8: {=IFERROR( INDEX($AH$2:$AH$9999,SMALL(IF($AF$2:$AF$9999=$D$2, ROW($AH$2:$AH$9999)-ROW($AH$2)+1),ROWS($D$3:D8))),"")} | E8: {=IFERROR( INDEX($AK$2:$AK$9999,SMALL(IF($AF$2:$AF$9999=$D$2, ROW($AK$2:$AK$9999)-ROW($AK$2)+1),ROWS($D$3:E8))),"")} | F8: {=IFERROR( INDEX($AI$2:$AI$9999,SMALL(IF($AF$2:$AF$9999=$D$2, ROW($AI$2:$AI$9999)-ROW($AI$2)+1),ROWS($F$3:F8))),"")} | G8: {=IFERROR( INDEX($AH$2:$AH$9999,SMALL(IF($AF$2:$AF$9999=$G$2, ROW($AH$2:$AH$9999)-ROW($AH$2)+1),ROWS($G$3:G8))),"")} | H8: {=IFERROR( INDEX($AK$2:$AK$9999,SMALL(IF($AF$2:$AF$9999=$G$2, ROW($AK$2:$AK$9999)-ROW($AK$2)+1),ROWS($G$3:H8))),"")} | I8: {=IFERROR( INDEX($AI$2:$AI$9999,SMALL(IF($AF$2:$AF$9999=$G$2, ROW($AI$2:$AI$9999)-ROW($AI$2)+1),ROWS($I$3:I8))),"")} | J8: {=IFERROR( INDEX($AH$2:$AH$9999,SMALL(IF($AF$2:$AF$9999=$J$2, ROW($AH$2:$AH$9999)-ROW($AH$2)+1),ROWS($J$3:J8))),"")} | K8: {=IFERROR( INDEX($AK$2:$AK$9999,SMALL(IF($AF$2:$AF$9999=$J$2, ROW($AK$2:$AK$9999)-ROW($AK$2)+1),ROWS($J$3:K8))),"")} | L8: {=IFERROR( INDEX($AI$2:$AI$9999,SMALL(IF($AF$2:$AF$9999=$J$2, ROW($AI$2:$AI$9999)-ROW($AI$2)+1),ROWS($L$3:L8))),"")} | M8: {=IFERROR( INDEX($AH$2:$AH$9999,SMALL(IF($AF$2:$AF$9999=$M$2, ROW($AH$2:$AH$9999)-ROW($AH$2)+1),ROWS($M$3:M8))),"")} | N8: {=IFERROR( INDEX($AK$2:$AK$9999,SMALL(IF($AF$2:$AF$9999=$M$2, ROW($AK$2:$AK$9999)-ROW($AK$2)+1),ROWS($M$3:N8))),"")} | O8: {=IFERROR( INDEX($AI$2:$AI$9999,SMALL(IF($AF$2:$AF$9999=$M$2, ROW($AI$2:$AI$9999)-ROW($AI$2)+1),ROWS($O$3:O8))),"")} | P8: {=IFERROR( INDEX($AH$2:$AH$9999,SMALL(IF($AF$2:$AF$9999=$P$2, ROW($AH$2:$AH$9999)-ROW($AH$2)+1),ROWS($P$3:P8))),"")} | Q8: {=IFERROR( INDEX($AK$2:$AK$9999,SMALL(IF($AF$2:$AF$9999=$P$2, ROW($AK$2:$AK$9999)-ROW($AK$2)+1),ROWS($P$3:Q8))),"")} | R8: {=IFERROR( INDEX($AI$2:$AI$9999,SMALL(IF($AF$2:$AF$9999=$P$2, ROW($AI$2:$AI$9999)-ROW($AI$2)+1),ROWS($R$3:R8))),"")} | S8: {=IFERROR( INDEX($AH$2:$AH$9999,SMALL(IF($AF$2:$AF$9999=$S$2, ROW($AH$2:$AH$9999)-ROW($AH$2)+1),ROWS($S$3:S8))),"")} | T8: {=IFERROR( INDEX($AK$2:$AK$9999,SMALL(IF($AF$2:$AF$9999=$S$2, ROW($AK$2:$AK$9999)-ROW($AK$2)+1),ROWS($S$3:T8))),"")} | U8: {=IFERROR( INDEX($AI$2:$AI$9999,SMALL(IF($AF$2:$AF$9999=$S$2, ROW($AI$2:$AI$9999)-ROW($AI$2)+1),ROWS($U$3:U8))),"")} | V8: {=IFERROR( INDEX($AH$2:$AH$9999,SMALL(IF($AF$2:$AF$9999=$V$2, ROW($AH$2:$AH$9999)-ROW($AH$2)+1),ROWS($V$3:V8))),"")} | W8: {=IFERROR( INDEX($AK$2:$AK$9999,SMALL(IF($AF$2:$AF$9999=$V$2, ROW($AK$2:$AK$9999)-ROW($AK$2)+1),ROWS($V$3:W8))),"")} | X8: {=IFERROR( INDEX($AI$2:$AI$9999,SMALL(IF($AF$2:$AF$9999=$V$2, ROW($AI$2:$AI$9999)-ROW($AI$2)+1),ROWS($X$3:X8))),"")} | Y8: {=IFERROR( INDEX($AH$2:$AH$9999,SMALL(IF($AF$2:$AF$9999=$Y$2, ROW($AH$2:$AH$9999)-ROW($AH$2)+1),ROWS($Y$3:Y8))),"")} | Z8: {=IFERROR( INDEX($AK$2:$AK$9999,SMALL(IF($AF$2:$AF$9999=$Y$2, ROW($AK$2:$AK$9999)-ROW($AK$2)+1),ROWS($Y$3:Z8))),"")} | AA8: {=IFERROR( INDEX($AI$2:$AI$9999,SMALL(IF($AF$2:$AF$9999=$Y$2, ROW($AI$2:$AI$9999)-ROW($AI$2)+1),ROWS($AA$3:AA8))),"")} | AB8: {=IFERROR( INDEX($AH$2:$AH$9999,SMALL(IF($AF$2:$AF$9999=$AB$2, ROW($AH$2:$AH$9999)-ROW($AH$2)+1),ROWS($AB$3:AB8))),"")} | AC8: {=IFERROR( INDEX($AK$2:$AK$9999,SMALL(IF($AF$2:$AF$9999=$AB$2, ROW($AK$2:$AK$9999)-ROW($AK$2)+1),ROWS($AB$3:AC8))),"")} | AD8: {=IFERROR( INDEX($AI$2:$AI$9999,SMALL(IF($AF$2:$AF$9999=$AB$2, ROW($AI$2:$AI$9999)-ROW($AI$2)+1),ROWS($AD$3:AD8))),"")} | AE8: ='(1)예금승인내역'!H638 -> 45579 | AF8: =VALUE(AE8) -> 45579 | AG8: ='(1)예금승인내역'!G638 -> 45303 | AH8: ='(1)예금승인내역'!F638 -> 케이와이글로벌셀앤진사모투자합자회사 | AI8: ='(1)예금승인내역'!L638 -> 2.48 | AJ8: ='(1)예금승인내역'!AG638 -> 0.0515 | AK8: ='(1)예금승인내역'!K638 -> 정기예금
A9: {=IFERROR( INDEX($AH$2:$AH$9999,SMALL(IF($AF$2:$AF$9999=$A$2, ROW($AH$2:$AH$9999)-ROW($AH$2)+1),ROWS(A$3:$A9))),"")} | B9: {=IFERROR( INDEX($AK$2:$AK$9999,SMALL(IF($AF$2:$AF$9999=$A$2, ROW($AK$2:$AK$9999)-ROW($AK$2)+1),ROWS($A$3:B9))),"")} | C9: {=IFERROR( INDEX($AI$2:$AI$9999,SMALL(IF($AF$2:$AF$9999=$A$2, ROW($AI$2:$AI$9999)-ROW($AI$2)+1),ROWS($A$3:C9))),"")} | D9: {=IFERROR( INDEX($AH$2:$AH$9999,SMALL(IF($AF$2:$AF$9999=$D$2, ROW($AH$2:$AH$9999)-ROW($AH$2)+1),ROWS($D$3:D9))),"")} | E9: {=IFERROR( INDEX($AK$2:$AK$9999,SMALL(IF($AF$2:$AF$9999=$D$2, ROW($AK$2:$AK$9999)-ROW($AK$2)+1),ROWS($D$3:E9))),"")} | F9: {=IFERROR( INDEX($AI$2:$AI$9999,SMALL(IF($AF$2:$AF$9999=$D$2, ROW($AI$2:$AI$9999)-ROW($AI$2)+1),ROWS($F$3:F9))),"")} | G9: {=IFERROR( INDEX($AH$2:$AH$9999,SMALL(IF($AF$2:$AF$9999=$G$2, ROW($AH$2:$AH$9999)-ROW($AH$2)+1),ROWS($G$3:G9))),"")} | H9: {=IFERROR( INDEX($AK$2:$AK$9999,SMALL(IF($AF$2:$AF$9999=$G$2, ROW($AK$2:$AK$9999)-ROW($AK$2)+1),ROWS($G$3:H9))),"")} | I9: {=IFERROR( INDEX($AI$2:$AI$9999,SMALL(IF($AF$2:$AF$9999=$G$2, ROW($AI$2:$AI$9999)-ROW($AI$2)+1),ROWS($I$3:I9))),"")} | J9: {=IFERROR( INDEX($AH$2:$AH$9999,SMALL(IF($AF$2:$AF$9999=$J$2, ROW($AH$2:$AH$9999)-ROW($AH$2)+1),ROWS($J$3:J9))),"")} | K9: {=IFERROR( INDEX($AK$2:$AK$9999,SMALL(IF($AF$2:$AF$9999=$J$2, ROW($AK$2:$AK$9999)-ROW($AK$2)+1),ROWS($J$3:K9))),"")} | L9: {=IFERROR( INDEX($AI$2:$AI$9999,SMALL(IF($AF$2:$AF$9999=$J$2, ROW($AI$2:$AI$9999)-ROW($AI$2)+1),ROWS($L$3:L9))),"")} | M9: {=IFERROR( INDEX($AH$2:$AH$9999,SMALL(IF($AF$2:$AF$9999=$M$2, ROW($AH$2:$AH$9999)-ROW($AH$2)+1),ROWS($M$3:M9))),"")} | N9: {=IFERROR( INDEX($AK$2:$AK$9999,SMALL(IF($AF$2:$AF$9999=$M$2, ROW($AK$2:$AK$9999)-ROW($AK$2)+1),ROWS($M$3:N9))),"")} | O9: {=IFERROR( INDEX($AI$2:$AI$9999,SMALL(IF($AF$2:$AF$9999=$M$2, ROW($AI$2:$AI$9999)-ROW($AI$2)+1),ROWS($O$3:O9))),"")} | P9: {=IFERROR( INDEX($AH$2:$AH$9999,SMALL(IF($AF$2:$AF$9999=$P$2, ROW($AH$2:$AH$9999)-ROW($AH$2)+1),ROWS($P$3:P9))),"")} | Q9: {=IFERROR( INDEX($AK$2:$AK$9999,SMALL(IF($AF$2:$AF$9999=$P$2, ROW($AK$2:$AK$9999)-ROW($AK$2)+1),ROWS($P$3:Q9))),"")} | R9: {=IFERROR( INDEX($AI$2:$AI$9999,SMALL(IF($AF$2:$AF$9999=$P$2, ROW($AI$2:$AI$9999)-ROW($AI$2)+1),ROWS($R$3:R9))),"")} | S9: {=IFERROR( INDEX($AH$2:$AH$9999,SMALL(IF($AF$2:$AF$9999=$S$2, ROW($AH$2:$AH$9999)-ROW($AH$2)+1),ROWS($S$3:S9))),"")} | T9: {=IFERROR( INDEX($AK$2:$AK$9999,SMALL(IF($AF$2:$AF$9999=$S$2, ROW($AK$2:$AK$9999)-ROW($AK$2)+1),ROWS($S$3:T9))),"")} | U9: {=IFERROR( INDEX($AI$2:$AI$9999,SMALL(IF($AF$2:$AF$9999=$S$2, ROW($AI$2:$AI$9999)-ROW($AI$2)+1),ROWS($U$3:U9))),"")} | V9: {=IFERROR( INDEX($AH$2:$AH$9999,SMALL(IF($AF$2:$AF$9999=$V$2, ROW($AH$2:$AH$9999)-ROW($AH$2)+1),ROWS($V$3:V9))),"")} | W9: {=IFERROR( INDEX($AK$2:$AK$9999,SMALL(IF($AF$2:$AF$9999=$V$2, ROW($AK$2:$AK$9999)-ROW($AK$2)+1),ROWS($V$3:W9))),"")} | X9: {=IFERROR( INDEX($AI$2:$AI$9999,SMALL(IF($AF$2:$AF$9999=$V$2, ROW($AI$2:$AI$9999)-ROW($AI$2)+1),ROWS($X$3:X9))),"")} | Y9: {=IFERROR( INDEX($AH$2:$AH$9999,SMALL(IF($AF$2:$AF$9999=$Y$2, ROW($AH$2:$AH$9999)-ROW($AH$2)+1),ROWS($Y$3:Y9))),"")} | Z9: {=IFERROR( INDEX($AK$2:$AK$9999,SMALL(IF($AF$2:$AF$9999=$Y$2, ROW($AK$2:$AK$9999)-ROW($AK$2)+1),ROWS($Y$3:Z9))),"")} | AA9: {=IFERROR( INDEX($AI$2:$AI$9999,SMALL(IF($AF$2:$AF$9999=$Y$2, ROW($AI$2:$AI$9999)-ROW($AI$2)+1),ROWS($AA$3:AA9))),"")} | AB9: {=IFERROR( INDEX($AH$2:$AH$9999,SMALL(IF($AF$2:$AF$9999=$AB$2, ROW($AH$2:$AH$9999)-ROW($AH$2)+1),ROWS($AB$3:AB9))),"")} | AC9: {=IFERROR( INDEX($AK$2:$AK$9999,SMALL(IF($AF$2:$AF$9999=$AB$2, ROW($AK$2:$AK$9999)-ROW($AK$2)+1),ROWS($AB$3:AC9))),"")} | AD9: {=IFERROR( INDEX($AI$2:$AI$9999,SMALL(IF($AF$2:$AF$9999=$AB$2, ROW($AI$2:$AI$9999)-ROW($AI$2)+1),ROWS($AD$3:AD9))),"")} | AE9: ='(1)예금승인내역'!H639 -> 45314 | AF9: =VALUE(AE9) -> 45314 | AG9: ='(1)예금승인내역'!G639 -> 45307 | AH9: ='(1)예금승인내역'!F639 -> 한국석유공사 | AI9: ='(1)예금승인내역'!L639 -> 20 | AJ9: ='(1)예금승인내역'!AG639 -> 0.0505 | AK9: ='(1)예금승인내역'!K639 -> 정기예금
A10: {=IFERROR( INDEX($AH$2:$AH$9999,SMALL(IF($AF$2:$AF$9999=$A$2, ROW($AH$2:$AH$9999)-ROW($AH$2)+1),ROWS(A$3:$A10))),"")} | B10: {=IFERROR( INDEX($AK$2:$AK$9999,SMALL(IF($AF$2:$AF$9999=$A$2, ROW($AK$2:$AK$9999)-ROW($AK$2)+1),ROWS($A$3:B10))),"")} | C10: {=IFERROR( INDEX($AI$2:$AI$9999,SMALL(IF($AF$2:$AF$9999=$A$2, ROW($AI$2:$AI$9999)-ROW($AI$2)+1),ROWS($A$3:C10))),"")} | D10: {=IFERROR( INDEX($AH$2:$AH$9999,SMALL(IF($AF$2:$AF$9999=$D$2, ROW($AH$2:$AH$9999)-ROW($AH$2)+1),ROWS($D$3:D10))),"")} | E10: {=IFERROR( INDEX($AK$2:$AK$9999,SMALL(IF($AF$2:$AF$9999=$D$2, ROW($AK$2:$AK$9999)-ROW($AK$2)+1),ROWS($D$3:E10))),"")} | F10: {=IFERROR( INDEX($AI$2:$AI$9999,SMALL(IF($AF$2:$AF$9999=$D$2, ROW($AI$2:$AI$9999)-ROW($AI$2)+1),ROWS($F$3:F10))),"")} | G10: {=IFERROR( INDEX($AH$2:$AH$9999,SMALL(IF($AF$2:$AF$9999=$G$2, ROW($AH$2:$AH$9999)-ROW($AH$2)+1),ROWS($G$3:G10))),"")} | H10: {=IFERROR( INDEX($AK$2:$AK$9999,SMALL(IF($AF$2:$AF$9999=$G$2, ROW($AK$2:$AK$9999)-ROW($AK$2)+1),ROWS($G$3:H10))),"")} | I10: {=IFERROR( INDEX($AI$2:$AI$9999,SMALL(IF($AF$2:$AF$9999=$G$2, ROW($AI$2:$AI$9999)-ROW($AI$2)+1),ROWS($I$3:I10))),"")} | J10: {=IFERROR( INDEX($AH$2:$AH$9999,SMALL(IF($AF$2:$AF$9999=$J$2, ROW($AH$2:$AH$9999)-ROW($AH$2)+1),ROWS($J$3:J10))),"")} | K10: {=IFERROR( INDEX($AK$2:$AK$9999,SMALL(IF($AF$2:$AF$9999=$J$2, ROW($AK$2:$AK$9999)-ROW($AK$2)+1),ROWS($J$3:K10))),"")} | L10: {=IFERROR( INDEX($AI$2:$AI$9999,SMALL(IF($AF$2:$AF$9999=$J$2, ROW($AI$2:$AI$9999)-ROW($AI$2)+1),ROWS($L$3:L10))),"")} | M10: {=IFERROR( INDEX($AH$2:$AH$9999,SMALL(IF($AF$2:$AF$9999=$M$2, ROW($AH$2:$AH$9999)-ROW($AH$2)+1),ROWS($M$3:M10))),"")} | N10: {=IFERROR( INDEX($AK$2:$AK$9999,SMALL(IF($AF$2:$AF$9999=$M$2, ROW($AK$2:$AK$9999)-ROW($AK$2)+1),ROWS($M$3:N10))),"")} | O10: {=IFERROR( INDEX($AI$2:$AI$9999,SMALL(IF($AF$2:$AF$9999=$M$2, ROW($AI$2:$AI$9999)-ROW($AI$2)+1),ROWS($O$3:O10))),"")} | P10: {=IFERROR( INDEX($AH$2:$AH$9999,SMALL(IF($AF$2:$AF$9999=$P$2, ROW($AH$2:$AH$9999)-ROW($AH$2)+1),ROWS($P$3:P10))),"")} | Q10: {=IFERROR( INDEX($AK$2:$AK$9999,SMALL(IF($AF$2:$AF$9999=$P$2, ROW($AK$2:$AK$9999)-ROW($AK$2)+1),ROWS($P$3:Q10))),"")} | R10: {=IFERROR( INDEX($AI$2:$AI$9999,SMALL(IF($AF$2:$AF$9999=$P$2, ROW($AI$2:$AI$9999)-ROW($AI$2)+1),ROWS($R$3:R10))),"")} | S10: {=IFERROR( INDEX($AH$2:$AH$9999,SMALL(IF($AF$2:$AF$9999=$S$2, ROW($AH$2:$AH$9999)-ROW($AH$2)+1),ROWS($S$3:S10))),"")} | T10: {=IFERROR( INDEX($AK$2:$AK$9999,SMALL(IF($AF$2:$AF$9999=$S$2, ROW($AK$2:$AK$9999)-ROW($AK$2)+1),ROWS($S$3:T10))),"")} | U10: {=IFERROR( INDEX($AI$2:$AI$9999,SMALL(IF($AF$2:$AF$9999=$S$2, ROW($AI$2:$AI$9999)-ROW($AI$2)+1),ROWS($U$3:U10))),"")} | V10: {=IFERROR( INDEX($AH$2:$AH$9999,SMALL(IF($AF$2:$AF$9999=$V$2, ROW($AH$2:$AH$9999)-ROW($AH$2)+1),ROWS($V$3:V10))),"")} | W10: {=IFERROR( INDEX($AK$2:$AK$9999,SMALL(IF($AF$2:$AF$9999=$V$2, ROW($AK$2:$AK$9999)-ROW($AK$2)+1),ROWS($V$3:W10))),"")} | X10: {=IFERROR( INDEX($AI$2:$AI$9999,SMALL(IF($AF$2:$AF$9999=$V$2, ROW($AI$2:$AI$9999)-ROW($AI$2)+1),ROWS($X$3:X10))),"")} | Y10: {=IFERROR( INDEX($AH$2:$AH$9999,SMALL(IF($AF$2:$AF$9999=$Y$2, ROW($AH$2:$AH$9999)-ROW($AH$2)+1),ROWS($Y$3:Y10))),"")} | Z10: {=IFERROR( INDEX($AK$2:$AK$9999,SMALL(IF($AF$2:$AF$9999=$Y$2, ROW($AK$2:$AK$9999)-ROW($AK$2)+1),ROWS($Y$3:Z10))),"")} | AA10: {=IFERROR( INDEX($AI$2:$AI$9999,SMALL(IF($AF$2:$AF$9999=$Y$2, ROW($AI$2:$AI$9999)-ROW($AI$2)+1),ROWS($AA$3:AA10))),"")} | AB10: {=IFERROR( INDEX($AH$2:$AH$9999,SMALL(IF($AF$2:$AF$9999=$AB$2, ROW($AH$2:$AH$9999)-ROW($AH$2)+1),ROWS($AB$3:AB10))),"")} | AC10: {=IFERROR( INDEX($AK$2:$AK$9999,SMALL(IF($AF$2:$AF$9999=$AB$2, ROW($AK$2:$AK$9999)-ROW($AK$2)+1),ROWS($AB$3:AC10))),"")} | AD10: {=IFERROR( INDEX($AI$2:$AI$9999,SMALL(IF($AF$2:$AF$9999=$AB$2, ROW($AI$2:$AI$9999)-ROW($AI$2)+1),ROWS($AD$3:AD10))),"")} | AE10: ='(1)예금승인내역'!H640 -> 45348 | AF10: =VALUE(AE10) -> 45348 | AG10: ='(1)예금승인내역'!G640 -> 45316 | AH10: ='(1)예금승인내역'!F640 -> ㈜와이투솔루션 | AI10: ='(1)예금승인내역'!L640 -> 1 | AJ10: ='(1)예금승인내역'!AG640 -> 0.0515 | AK10: ='(1)예금승인내역'!K640 -> 정기예금
A11: {=IFERROR( INDEX($AH$2:$AH$9999,SMALL(IF($AF$2:$AF$9999=$A$2, ROW($AH$2:$AH$9999)-ROW($AH$2)+1),ROWS(A$3:$A11))),"")} | B11: {=IFERROR( INDEX($AK$2:$AK$9999,SMALL(IF($AF$2:$AF$9999=$A$2, ROW($AK$2:$AK$9999)-ROW($AK$2)+1),ROWS($A$3:B11))),"")} | C11: {=IFERROR( INDEX($AI$2:$AI$9999,SMALL(IF($AF$2:$AF$9999=$A$2, ROW($AI$2:$AI$9999)-ROW($AI$2)+1),ROWS($A$3:C11))),"")} | D11: {=IFERROR( INDEX($AH$2:$AH$9999,SMALL(IF($AF$2:$AF$9999=$D$2, ROW($AH$2:$AH$9999)-ROW($AH$2)+1),ROWS($D$3:D11))),"")} | E11: {=IFERROR( INDEX($AK$2:$AK$9999,SMALL(IF($AF$2:$AF$9999=$D$2, ROW($AK$2:$AK$9999)-ROW($AK$2)+1),ROWS($D$3:E11))),"")} | F11: {=IFERROR( INDEX($AI$2:$AI$9999,SMALL(IF($AF$2:$AF$9999=$D$2, ROW($AI$2:$AI$9999)-ROW($AI$2)+1),ROWS($F$3:F11))),"")} | G11: {=IFERROR( INDEX($AH$2:$AH$9999,SMALL(IF($AF$2:$AF$9999=$G$2, ROW($AH$2:$AH$9999)-ROW($AH$2)+1),ROWS($G$3:G11))),"")} | H11: {=IFERROR( INDEX($AK$2:$AK$9999,SMALL(IF($AF$2:$AF$9999=$G$2, ROW($AK$2:$AK$9999)-ROW($AK$2)+1),ROWS($G$3:H11))),"")} | I11: {=IFERROR( INDEX($AI$2:$AI$9999,SMALL(IF($AF$2:$AF$9999=$G$2, ROW($AI$2:$AI$9999)-ROW($AI$2)+1),ROWS($I$3:I11))),"")} | J11: {=IFERROR( INDEX($AH$2:$AH$9999,SMALL(IF($AF$2:$AF$9999=$J$2, ROW($AH$2:$AH$9999)-ROW($AH$2)+1),ROWS($J$3:J11))),"")} | K11: {=IFERROR( INDEX($AK$2:$AK$9999,SMALL(IF($AF$2:$AF$9999=$J$2, ROW($AK$2:$AK$9999)-ROW($AK$2)+1),ROWS($J$3:K11))),"")} | L11: {=IFERROR( INDEX($AI$2:$AI$9999,SMALL(IF($AF$2:$AF$9999=$J$2, ROW($AI$2:$AI$9999)-ROW($AI$2)+1),ROWS($L$3:L11))),"")} | M11: {=IFERROR( INDEX($AH$2:$AH$9999,SMALL(IF($AF$2:$AF$9999=$M$2, ROW($AH$2:$AH$9999)-ROW($AH$2)+1),ROWS($M$3:M11))),"")} | N11: {=IFERROR( INDEX($AK$2:$AK$9999,SMALL(IF($AF$2:$AF$9999=$M$2, ROW($AK$2:$AK$9999)-ROW($AK$2)+1),ROWS($M$3:N11))),"")} | O11: {=IFERROR( INDEX($AI$2:$AI$9999,SMALL(IF($AF$2:$AF$9999=$M$2, ROW($AI$2:$AI$9999)-ROW($AI$2)+1),ROWS($O$3:O11))),"")} | P11: {=IFERROR( INDEX($AH$2:$AH$9999,SMALL(IF($AF$2:$AF$9999=$P$2, ROW($AH$2:$AH$9999)-ROW($AH$2)+1),ROWS($P$3:P11))),"")} | Q11: {=IFERROR( INDEX($AK$2:$AK$9999,SMALL(IF($AF$2:$AF$9999=$P$2, ROW($AK$2:$AK$9999)-ROW($AK$2)+1),ROWS($P$3:Q11))),"")} | R11: {=IFERROR( INDEX($AI$2:$AI$9999,SMALL(IF($AF$2:$AF$9999=$P$2, ROW($AI$2:$AI$9999)-ROW($AI$2)+1),ROWS($R$3:R11))),"")} | S11: {=IFERROR( INDEX($AH$2:$AH$9999,SMALL(IF($AF$2:$AF$9999=$S$2, ROW($AH$2:$AH$9999)-ROW($AH$2)+1),ROWS($S$3:S11))),"")} | T11: {=IFERROR( INDEX($AK$2:$AK$9999,SMALL(IF($AF$2:$AF$9999=$S$2, ROW($AK$2:$AK$9999)-ROW($AK$2)+1),ROWS($S$3:T11))),"")} | U11: {=IFERROR( INDEX($AI$2:$AI$9999,SMALL(IF($AF$2:$AF$9999=$S$2, ROW($AI$2:$AI$9999)-ROW($AI$2)+1),ROWS($U$3:U11))),"")} | V11: {=IFERROR( INDEX($AH$2:$AH$9999,SMALL(IF($AF$2:$AF$9999=$V$2, ROW($AH$2:$AH$9999)-ROW($AH$2)+1),ROWS($V$3:V11))),"")} | W11: {=IFERROR( INDEX($AK$2:$AK$9999,SMALL(IF($AF$2:$AF$9999=$V$2, ROW($AK$2:$AK$9999)-ROW($AK$2)+1),ROWS($V$3:W11))),"")} | X11: {=IFERROR( INDEX($AI$2:$AI$9999,SMALL(IF($AF$2:$AF$9999=$V$2, ROW($AI$2:$AI$9999)-ROW($AI$2)+1),ROWS($X$3:X11))),"")} | Y11: {=IFERROR( INDEX($AH$2:$AH$9999,SMALL(IF($AF$2:$AF$9999=$Y$2, ROW($AH$2:$AH$9999)-ROW($AH$2)+1),ROWS($Y$3:Y11))),"")} | Z11: {=IFERROR( INDEX($AK$2:$AK$9999,SMALL(IF($AF$2:$AF$9999=$Y$2, ROW($AK$2:$AK$9999)-ROW($AK$2)+1),ROWS($Y$3:Z11))),"")} | AA11: {=IFERROR( INDEX($AI$2:$AI$9999,SMALL(IF($AF$2:$AF$9999=$Y$2, ROW($AI$2:$AI$9999)-ROW($AI$2)+1),ROWS($AA$3:AA11))),"")} | AB11: {=IFERROR( INDEX($AH$2:$AH$9999,SMALL(IF($AF$2:$AF$9999=$AB$2, ROW($AH$2:$AH$9999)-ROW($AH$2)+1),ROWS($AB$3:AB11))),"")} | AC11: {=IFERROR( INDEX($AK$2:$AK$9999,SMALL(IF($AF$2:$AF$9999=$AB$2, ROW($AK$2:$AK$9999)-ROW($AK$2)+1),ROWS($AB$3:AC11))),"")} | AD11: {=IFERROR( INDEX($AI$2:$AI$9999,SMALL(IF($AF$2:$AF$9999=$AB$2, ROW($AI$2:$AI$9999)-ROW($AI$2)+1),ROWS($AD$3:AD11))),"")} | AE11: ='(1)예금승인내역'!H641 -> 45348 | AF11: =VALUE(AE11) -> 45348 | AG11: ='(1)예금승인내역'!G641 -> 45316 | AH11: ='(1)예금승인내역'!F641 -> ㈜와이투솔루션 | AI11: ='(1)예금승인내역'!L641 -> 1 | AJ11: ='(1)예금승인내역'!AG641 -> 0.0515 | AK11: ='(1)예금승인내역'!K641 -> 정기예금
A12: {=IFERROR( INDEX($AH$2:$AH$9999,SMALL(IF($AF$2:$AF$9999=$A$2, ROW($AH$2:$AH$9999)-ROW($AH$2)+1),ROWS(A$3:$A12))),"")} | B12: {=IFERROR( INDEX($AK$2:$AK$9999,SMALL(IF($AF$2:$AF$9999=$A$2, ROW($AK$2:$AK$9999)-ROW($AK$2)+1),ROWS($A$3:B12))),"")} | C12: {=IFERROR( INDEX($AI$2:$AI$9999,SMALL(IF($AF$2:$AF$9999=$A$2, ROW($AI$2:$AI$9999)-ROW($AI$2)+1),ROWS($A$3:C12))),"")} | D12: {=IFERROR( INDEX($AH$2:$AH$9999,SMALL(IF($AF$2:$AF$9999=$D$2, ROW($AH$2:$AH$9999)-ROW($AH$2)+1),ROWS($D$3:D12))),"")} | E12: {=IFERROR( INDEX($AK$2:$AK$9999,SMALL(IF($AF$2:$AF$9999=$D$2, ROW($AK$2:$AK$9999)-ROW($AK$2)+1),ROWS($D$3:E12))),"")} | F12: {=IFERROR( INDEX($AI$2:$AI$9999,SMALL(IF($AF$2:$AF$9999=$D$2, ROW($AI$2:$AI$9999)-ROW($AI$2)+1),ROWS($F$3:F12))),"")} | G12: {=IFERROR( INDEX($AH$2:$AH$9999,SMALL(IF($AF$2:$AF$9999=$G$2, ROW($AH$2:$AH$9999)-ROW($AH$2)+1),ROWS($G$3:G12))),"")} | H12: {=IFERROR( INDEX($AK$2:$AK$9999,SMALL(IF($AF$2:$AF$9999=$G$2, ROW($AK$2:$AK$9999)-ROW($AK$2)+1),ROWS($G$3:H12))),"")} | I12: {=IFERROR( INDEX($AI$2:$AI$9999,SMALL(IF($AF$2:$AF$9999=$G$2, ROW($AI$2:$AI$9999)-ROW($AI$2)+1),ROWS($I$3:I12))),"")} | J12: {=IFERROR( INDEX($AH$2:$AH$9999,SMALL(IF($AF$2:$AF$9999=$J$2, ROW($AH$2:$AH$9999)-ROW($AH$2)+1),ROWS($J$3:J12))),"")} | K12: {=IFERROR( INDEX($AK$2:$AK$9999,SMALL(IF($AF$2:$AF$9999=$J$2, ROW($AK$2:$AK$9999)-ROW($AK$2)+1),ROWS($J$3:K12))),"")} | L12: {=IFERROR( INDEX($AI$2:$AI$9999,SMALL(IF($AF$2:$AF$9999=$J$2, ROW($AI$2:$AI$9999)-ROW($AI$2)+1),ROWS($L$3:L12))),"")} | M12: {=IFERROR( INDEX($AH$2:$AH$9999,SMALL(IF($AF$2:$AF$9999=$M$2, ROW($AH$2:$AH$9999)-ROW($AH$2)+1),ROWS($M$3:M12))),"")} | N12: {=IFERROR( INDEX($AK$2:$AK$9999,SMALL(IF($AF$2:$AF$9999=$M$2, ROW($AK$2:$AK$9999)-ROW($AK$2)+1),ROWS($M$3:N12))),"")} | O12: {=IFERROR( INDEX($AI$2:$AI$9999,SMALL(IF($AF$2:$AF$9999=$M$2, ROW($AI$2:$AI$9999)-ROW($AI$2)+1),ROWS($O$3:O12))),"")} | P12: {=IFERROR( INDEX($AH$2:$AH$9999,SMALL(IF($AF$2:$AF$9999=$P$2, ROW($AH$2:$AH$9999)-ROW($AH$2)+1),ROWS($P$3:P12))),"")} | Q12: {=IFERROR( INDEX($AK$2:$AK$9999,SMALL(IF($AF$2:$AF$9999=$P$2, ROW($AK$2:$AK$9999)-ROW($AK$2)+1),ROWS($P$3:Q12))),"")} | R12: {=IFERROR( INDEX($AI$2:$AI$9999,SMALL(IF($AF$2:$AF$9999=$P$2, ROW($AI$2:$AI$9999)-ROW($AI$2)+1),ROWS($R$3:R12))),"")} | S12: {=IFERROR( INDEX($AH$2:$AH$9999,SMALL(IF($AF$2:$AF$9999=$S$2, ROW($AH$2:$AH$9999)-ROW($AH$2)+1),ROWS($S$3:S12))),"")} | T12: {=IFERROR( INDEX($AK$2:$AK$9999,SMALL(IF($AF$2:$AF$9999=$S$2, ROW($AK$2:$AK$9999)-ROW($AK$2)+1),ROWS($S$3:T12))),"")} | U12: {=IFERROR( INDEX($AI$2:$AI$9999,SMALL(IF($AF$2:$AF$9999=$S$2, ROW($AI$2:$AI$9999)-ROW($AI$2)+1),ROWS($U$3:U12))),"")} | V12: {=IFERROR( INDEX($AH$2:$AH$9999,SMALL(IF($AF$2:$AF$9999=$V$2, ROW($AH$2:$AH$9999)-ROW($AH$2)+1),ROWS($V$3:V12))),"")} | W12: {=IFERROR( INDEX($AK$2:$AK$9999,SMALL(IF($AF$2:$AF$9999=$V$2, ROW($AK$2:$AK$9999)-ROW($AK$2)+1),ROWS($V$3:W12))),"")} | X12: {=IFERROR( INDEX($AI$2:$AI$9999,SMALL(IF($AF$2:$AF$9999=$V$2, ROW($AI$2:$AI$9999)-ROW($AI$2)+1),ROWS($X$3:X12))),"")} | Y12: {=IFERROR( INDEX($AH$2:$AH$9999,SMALL(IF($AF$2:$AF$9999=$Y$2, ROW($AH$2:$AH$9999)-ROW($AH$2)+1),ROWS($Y$3:Y12))),"")} | Z12: {=IFERROR( INDEX($AK$2:$AK$9999,SMALL(IF($AF$2:$AF$9999=$Y$2, ROW($AK$2:$AK$9999)-ROW($AK$2)+1),ROWS($Y$3:Z12))),"")} | AA12: {=IFERROR( INDEX($AI$2:$AI$9999,SMALL(IF($AF$2:$AF$9999=$Y$2, ROW($AI$2:$AI$9999)-ROW($AI$2)+1),ROWS($AA$3:AA12))),"")} | AB12: {=IFERROR( INDEX($AH$2:$AH$9999,SMALL(IF($AF$2:$AF$9999=$AB$2, ROW($AH$2:$AH$9999)-ROW($AH$2)+1),ROWS($AB$3:AB12))),"")} | AC12: {=IFERROR( INDEX($AK$2:$AK$9999,SMALL(IF($AF$2:$AF$9999=$AB$2, ROW($AK$2:$AK$9999)-ROW($AK$2)+1),ROWS($AB$3:AC12))),"")} | AD12: {=IFERROR( INDEX($AI$2:$AI$9999,SMALL(IF($AF$2:$AF$9999=$AB$2, ROW($AI$2:$AI$9999)-ROW($AI$2)+1),ROWS($AD$3:AD12))),"")} | AE12: ='(1)예금승인내역'!H642 -> 45348 | AF12: =VALUE(AE12) -> 45348 | AG12: ='(1)예금승인내역'!G642 -> 45316 | AH12: ='(1)예금승인내역'!F642 -> ㈜와이투솔루션 | AI12: ='(1)예금승인내역'!L642 -> 1 | AJ12: ='(1)예금승인내역'!AG642 -> 0.0515 | AK12: ='(1)예금승인내역'!K642 -> 정기예금
A13: {=IFERROR( INDEX($AH$2:$AH$9999,SMALL(IF($AF$2:$AF$9999=$A$2, ROW($AH$2:$AH$9999)-ROW($AH$2)+1),ROWS(A$3:$A13))),"")} | B13: {=IFERROR( INDEX($AK$2:$AK$9999,SMALL(IF($AF$2:$AF$9999=$A$2, ROW($AK$2:$AK$9999)-ROW($AK$2)+1),ROWS($A$3:B13))),"")} | C13: {=IFERROR( INDEX($AI$2:$AI$9999,SMALL(IF($AF$2:$AF$9999=$A$2, ROW($AI$2:$AI$9999)-ROW($AI$2)+1),ROWS($A$3:C13))),"")} | D13: {=IFERROR( INDEX($AH$2:$AH$9999,SMALL(IF($AF$2:$AF$9999=$D$2, ROW($AH$2:$AH$9999)-ROW($AH$2)+1),ROWS($D$3:D13))),"")} | E13: {=IFERROR( INDEX($AK$2:$AK$9999,SMALL(IF($AF$2:$AF$9999=$D$2, ROW($AK$2:$AK$9999)-ROW($AK$2)+1),ROWS($D$3:E13))),"")} | F13: {=IFERROR( INDEX($AI$2:$AI$9999,SMALL(IF($AF$2:$AF$9999=$D$2, ROW($AI$2:$AI$9999)-ROW($AI$2)+1),ROWS($F$3:F13))),"")} | G13: {=IFERROR( INDEX($AH$2:$AH$9999,SMALL(IF($AF$2:$AF$9999=$G$2, ROW($AH$2:$AH$9999)-ROW($AH$2)+1),ROWS($G$3:G13))),"")} | H13: {=IFERROR( INDEX($AK$2:$AK$9999,SMALL(IF($AF$2:$AF$9999=$G$2, ROW($AK$2:$AK$9999)-ROW($AK$2)+1),ROWS($G$3:H13))),"")} | I13: {=IFERROR( INDEX($AI$2:$AI$9999,SMALL(IF($AF$2:$AF$9999=$G$2, ROW($AI$2:$AI$9999)-ROW($AI$2)+1),ROWS($I$3:I13))),"")} | J13: {=IFERROR( INDEX($AH$2:$AH$9999,SMALL(IF($AF$2:$AF$9999=$J$2, ROW($AH$2:$AH$9999)-ROW($AH$2)+1),ROWS($J$3:J13))),"")} | K13: {=IFERROR( INDEX($AK$2:$AK$9999,SMALL(IF($AF$2:$AF$9999=$J$2, ROW($AK$2:$AK$9999)-ROW($AK$2)+1),ROWS($J$3:K13))),"")} | L13: {=IFERROR( INDEX($AI$2:$AI$9999,SMALL(IF($AF$2:$AF$9999=$J$2, ROW($AI$2:$AI$9999)-ROW($AI$2)+1),ROWS($L$3:L13))),"")} | M13: {=IFERROR( INDEX($AH$2:$AH$9999,SMALL(IF($AF$2:$AF$9999=$M$2, ROW($AH$2:$AH$9999)-ROW($AH$2)+1),ROWS($M$3:M13))),"")} | N13: {=IFERROR( INDEX($AK$2:$AK$9999,SMALL(IF($AF$2:$AF$9999=$M$2, ROW($AK$2:$AK$9999)-ROW($AK$2)+1),ROWS($M$3:N13))),"")} | O13: {=IFERROR( INDEX($AI$2:$AI$9999,SMALL(IF($AF$2:$AF$9999=$M$2, ROW($AI$2:$AI$9999)-ROW($AI$2)+1),ROWS($O$3:O13))),"")} | P13: {=IFERROR( INDEX($AH$2:$AH$9999,SMALL(IF($AF$2:$AF$9999=$P$2, ROW($AH$2:$AH$9999)-ROW($AH$2)+1),ROWS($P$3:P13))),"")} | Q13: {=IFERROR( INDEX($AK$2:$AK$9999,SMALL(IF($AF$2:$AF$9999=$P$2, ROW($AK$2:$AK$9999)-ROW($AK$2)+1),ROWS($P$3:Q13))),"")} | R13: {=IFERROR( INDEX($AI$2:$AI$9999,SMALL(IF($AF$2:$AF$9999=$P$2, ROW($AI$2:$AI$9999)-ROW($AI$2)+1),ROWS($R$3:R13))),"")} | S13: {=IFERROR( INDEX($AH$2:$AH$9999,SMALL(IF($AF$2:$AF$9999=$S$2, ROW($AH$2:$AH$9999)-ROW($AH$2)+1),ROWS($S$3:S13))),"")} | T13: {=IFERROR( INDEX($AK$2:$AK$9999,SMALL(IF($AF$2:$AF$9999=$S$2, ROW($AK$2:$AK$9999)-ROW($AK$2)+1),ROWS($S$3:T13))),"")} | U13: {=IFERROR( INDEX($AI$2:$AI$9999,SMALL(IF($AF$2:$AF$9999=$S$2, ROW($AI$2:$AI$9999)-ROW($AI$2)+1),ROWS($U$3:U13))),"")} | V13: {=IFERROR( INDEX($AH$2:$AH$9999,SMALL(IF($AF$2:$AF$9999=$V$2, ROW($AH$2:$AH$9999)-ROW($AH$2)+1),ROWS($V$3:V13))),"")} | W13: {=IFERROR( INDEX($AK$2:$AK$9999,SMALL(IF($AF$2:$AF$9999=$V$2, ROW($AK$2:$AK$9999)-ROW($AK$2)+1),ROWS($V$3:W13))),"")} | X13: {=IFERROR( INDEX($AI$2:$AI$9999,SMALL(IF($AF$2:$AF$9999=$V$2, ROW($AI$2:$AI$9999)-ROW($AI$2)+1),ROWS($X$3:X13))),"")} | Y13: {=IFERROR( INDEX($AH$2:$AH$9999,SMALL(IF($AF$2:$AF$9999=$Y$2, ROW($AH$2:$AH$9999)-ROW($AH$2)+1),ROWS($Y$3:Y13))),"")} | Z13: {=IFERROR( INDEX($AK$2:$AK$9999,SMALL(IF($AF$2:$AF$9999=$Y$2, ROW($AK$2:$AK$9999)-ROW($AK$2)+1),ROWS($Y$3:Z13))),"")} | AA13: {=IFERROR( INDEX($AI$2:$AI$9999,SMALL(IF($AF$2:$AF$9999=$Y$2, ROW($AI$2:$AI$9999)-ROW($AI$2)+1),ROWS($AA$3:AA13))),"")} | AB13: {=IFERROR( INDEX($AH$2:$AH$9999,SMALL(IF($AF$2:$AF$9999=$AB$2, ROW($AH$2:$AH$9999)-ROW($AH$2)+1),ROWS($AB$3:AB13))),"")} | AC13: {=IFERROR( INDEX($AK$2:$AK$9999,SMALL(IF($AF$2:$AF$9999=$AB$2, ROW($AK$2:$AK$9999)-ROW($AK$2)+1),ROWS($AB$3:AC13))),"")} | AD13: {=IFERROR( INDEX($AI$2:$AI$9999,SMALL(IF($AF$2:$AF$9999=$AB$2, ROW($AI$2:$AI$9999)-ROW($AI$2)+1),ROWS($AD$3:AD13))),"")} | AE13: ='(1)예금승인내역'!H643 -> 45348 | AF13: =VALUE(AE13) -> 45348 | AG13: ='(1)예금승인내역'!G643 -> 45316 | AH13: ='(1)예금승인내역'!F643 -> ㈜와이투솔루션 | AI13: ='(1)예금승인내역'!L643 -> 1 | AJ13: ='(1)예금승인내역'!AG643 -> 0.0515 | AK13: ='(1)예금승인내역'!K643 -> 정기예금
A14: {=IFERROR( INDEX($AH$2:$AH$9999,SMALL(IF($AF$2:$AF$9999=$A$2, ROW($AH$2:$AH$9999)-ROW($AH$2)+1),ROWS(A$3:$A14))),"")} | B14: {=IFERROR( INDEX($AK$2:$AK$9999,SMALL(IF($AF$2:$AF$9999=$A$2, ROW($AK$2:$AK$9999)-ROW($AK$2)+1),ROWS($A$3:B14))),"")} | C14: {=IFERROR( INDEX($AI$2:$AI$9999,SMALL(IF($AF$2:$AF$9999=$A$2, ROW($AI$2:$AI$9999)-ROW($AI$2)+1),ROWS($A$3:C14))),"")} | D14: {=IFERROR( INDEX($AH$2:$AH$9999,SMALL(IF($AF$2:$AF$9999=$D$2, ROW($AH$2:$AH$9999)-ROW($AH$2)+1),ROWS($D$3:D14))),"")} | E14: {=IFERROR( INDEX($AK$2:$AK$9999,SMALL(IF($AF$2:$AF$9999=$D$2, ROW($AK$2:$AK$9999)-ROW($AK$2)+1),ROWS($D$3:E14))),"")} | F14: {=IFERROR( INDEX($AI$2:$AI$9999,SMALL(IF($AF$2:$AF$9999=$D$2, ROW($AI$2:$AI$9999)-ROW($AI$2)+1),ROWS($F$3:F14))),"")} | G14: {=IFERROR( INDEX($AH$2:$AH$9999,SMALL(IF($AF$2:$AF$9999=$G$2, ROW($AH$2:$AH$9999)-ROW($AH$2)+1),ROWS($G$3:G14))),"")} | H14: {=IFERROR( INDEX($AK$2:$AK$9999,SMALL(IF($AF$2:$AF$9999=$G$2, ROW($AK$2:$AK$9999)-ROW($AK$2)+1),ROWS($G$3:H14))),"")} | I14: {=IFERROR( INDEX($AI$2:$AI$9999,SMALL(IF($AF$2:$AF$9999=$G$2, ROW($AI$2:$AI$9999)-ROW($AI$2)+1),ROWS($I$3:I14))),"")} | J14: {=IFERROR( INDEX($AH$2:$AH$9999,SMALL(IF($AF$2:$AF$9999=$J$2, ROW($AH$2:$AH$9999)-ROW($AH$2)+1),ROWS($J$3:J14))),"")} | K14: {=IFERROR( INDEX($AK$2:$AK$9999,SMALL(IF($AF$2:$AF$9999=$J$2, ROW($AK$2:$AK$9999)-ROW($AK$2)+1),ROWS($J$3:K14))),"")} | L14: {=IFERROR( INDEX($AI$2:$AI$9999,SMALL(IF($AF$2:$AF$9999=$J$2, ROW($AI$2:$AI$9999)-ROW($AI$2)+1),ROWS($L$3:L14))),"")} | M14: {=IFERROR( INDEX($AH$2:$AH$9999,SMALL(IF($AF$2:$AF$9999=$M$2, ROW($AH$2:$AH$9999)-ROW($AH$2)+1),ROWS($M$3:M14))),"")} | N14: {=IFERROR( INDEX($AK$2:$AK$9999,SMALL(IF($AF$2:$AF$9999=$M$2, ROW($AK$2:$AK$9999)-ROW($AK$2)+1),ROWS($M$3:N14))),"")} | O14: {=IFERROR( INDEX($AI$2:$AI$9999,SMALL(IF($AF$2:$AF$9999=$M$2, ROW($AI$2:$AI$9999)-ROW($AI$2)+1),ROWS($O$3:O14))),"")} | P14: {=IFERROR( INDEX($AH$2:$AH$9999,SMALL(IF($AF$2:$AF$9999=$P$2, ROW($AH$2:$AH$9999)-ROW($AH$2)+1),ROWS($P$3:P14))),"")} | Q14: {=IFERROR( INDEX($AK$2:$AK$9999,SMALL(IF($AF$2:$AF$9999=$P$2, ROW($AK$2:$AK$9999)-ROW($AK$2)+1),ROWS($P$3:Q14))),"")} | R14: {=IFERROR( INDEX($AI$2:$AI$9999,SMALL(IF($AF$2:$AF$9999=$P$2, ROW($AI$2:$AI$9999)-ROW($AI$2)+1),ROWS($R$3:R14))),"")} | S14: {=IFERROR( INDEX($AH$2:$AH$9999,SMALL(IF($AF$2:$AF$9999=$S$2, ROW($AH$2:$AH$9999)-ROW($AH$2)+1),ROWS($S$3:S14))),"")} | T14: {=IFERROR( INDEX($AK$2:$AK$9999,SMALL(IF($AF$2:$AF$9999=$S$2, ROW($AK$2:$AK$9999)-ROW($AK$2)+1),ROWS($S$3:T14))),"")} | U14: {=IFERROR( INDEX($AI$2:$AI$9999,SMALL(IF($AF$2:$AF$9999=$S$2, ROW($AI$2:$AI$9999)-ROW($AI$2)+1),ROWS($U$3:U14))),"")} | V14: {=IFERROR( INDEX($AH$2:$AH$9999,SMALL(IF($AF$2:$AF$9999=$V$2, ROW($AH$2:$AH$9999)-ROW($AH$2)+1),ROWS($V$3:V14))),"")} | W14: {=IFERROR( INDEX($AK$2:$AK$9999,SMALL(IF($AF$2:$AF$9999=$V$2, ROW($AK$2:$AK$9999)-ROW($AK$2)+1),ROWS($V$3:W14))),"")} | X14: {=IFERROR( INDEX($AI$2:$AI$9999,SMALL(IF($AF$2:$AF$9999=$V$2, ROW($AI$2:$AI$9999)-ROW($AI$2)+1),ROWS($X$3:X14))),"")} | Y14: {=IFERROR( INDEX($AH$2:$AH$9999,SMALL(IF($AF$2:$AF$9999=$Y$2, ROW($AH$2:$AH$9999)-ROW($AH$2)+1),ROWS($Y$3:Y14))),"")} | Z14: {=IFERROR( INDEX($AK$2:$AK$9999,SMALL(IF($AF$2:$AF$9999=$Y$2, ROW($AK$2:$AK$9999)-ROW($AK$2)+1),ROWS($Y$3:Z14))),"")} | AA14: {=IFERROR( INDEX($AI$2:$AI$9999,SMALL(IF($AF$2:$AF$9999=$Y$2, ROW($AI$2:$AI$9999)-ROW($AI$2)+1),ROWS($AA$3:AA14))),"")} | AB14: {=IFERROR( INDEX($AH$2:$AH$9999,SMALL(IF($AF$2:$AF$9999=$AB$2, ROW($AH$2:$AH$9999)-ROW($AH$2)+1),ROWS($AB$3:AB14))),"")} | AC14: {=IFERROR( INDEX($AK$2:$AK$9999,SMALL(IF($AF$2:$AF$9999=$AB$2, ROW($AK$2:$AK$9999)-ROW($AK$2)+1),ROWS($AB$3:AC14))),"")} | AD14: {=IFERROR( INDEX($AI$2:$AI$9999,SMALL(IF($AF$2:$AF$9999=$AB$2, ROW($AI$2:$AI$9999)-ROW($AI$2)+1),ROWS($AD$3:AD14))),"")} | AE14: ='(1)예금승인내역'!H644 -> 45357 | AF14: =VALUE(AE14) -> 45357 | AG14: ='(1)예금승인내역'!G644 -> 45328 | AH14: ='(1)예금승인내역'!F644 -> 한국비철㈜ | AI14: ='(1)예금승인내역'!L644 -> 9.7 | AJ14: ='(1)예금승인내역'!AG644 -> 0.0435 | AK14: ='(1)예금승인내역'!K644 -> MMDA
... A30: {=IFERROR( INDEX($AH$2:$AH$9999,SMALL(IF($AF$2:$AF$9999=$A$2, ROW($AH$2:$AH$9999)-ROW($AH$2)+1),ROWS(A$3:$A30))),"")} | B30: {=IFERROR( INDEX($AK$2:$AK$9999,SMALL(IF($AF$2:$AF$9999=$A$2, ROW($AK$2:$AK$9999)-ROW($AK$2)+1),ROWS($A$3:B30))),"")} | C30: {=IFERROR( INDEX($AI$2:$AI$9999,SMALL(IF($AF$2:$AF$9999=$A$2, ROW($AI$2:$AI$9999)-ROW($AI$2)+1),ROWS($A$3:C30))),"")} | D30: {=IFERROR( INDEX($AH$2:$AH$9999,SMALL(IF($AF$2:$AF$9999=$D$2, ROW($AH$2:$AH$9999)-ROW($AH$2)+1),ROWS($D$3:D30))),"")} | E30: {=IFERROR( INDEX($AK$2:$AK$9999,SMALL(IF($AF$2:$AF$9999=$D$2, ROW($AK$2:$AK$9999)-ROW($AK$2)+1),ROWS($D$3:E30))),"")} | F30: {=IFERROR( INDEX($AI$2:$AI$9999,SMALL(IF($AF$2:$AF$9999=$D$2, ROW($AI$2:$AI$9999)-ROW($AI$2)+1),ROWS($F$3:F30))),"")} | G30: {=IFERROR( INDEX($AH$2:$AH$9999,SMALL(IF($AF$2:$AF$9999=$G$2, ROW($AH$2:$AH$9999)-ROW($AH$2)+1),ROWS($G$3:G30))),"")} | H30: {=IFERROR( INDEX($AK$2:$AK$9999,SMALL(IF($AF$2:$AF$9999=$G$2, ROW($AK$2:$AK$9999)-ROW($AK$2)+1),ROWS($G$3:H30))),"")} | I30: {=IFERROR( INDEX($AI$2:$AI$9999,SMALL(IF($AF$2:$AF$9999=$G$2, ROW($AI$2:$AI$9999)-ROW($AI$2)+1),ROWS($I$3:I30))),"")} | J30: {=IFERROR( INDEX($AH$2:$AH$9999,SMALL(IF($AF$2:$AF$9999=$J$2, ROW($AH$2:$AH$9999)-ROW($AH$2)+1),ROWS($J$3:J30))),"")} | K30: {=IFERROR( INDEX($AK$2:$AK$9999,SMALL(IF($AF$2:$AF$9999=$J$2, ROW($AK$2:$AK$9999)-ROW($AK$2)+1),ROWS($J$3:K30))),"")} | L30: {=IFERROR( INDEX($AI$2:$AI$9999,SMALL(IF($AF$2:$AF$9999=$J$2, ROW($AI$2:$AI$9999)-ROW($AI$2)+1),ROWS($L$3:L30))),"")} | M30: {=IFERROR( INDEX($AH$2:$AH$9999,SMALL(IF($AF$2:$AF$9999=$M$2, ROW($AH$2:$AH$9999)-ROW($AH$2)+1),ROWS($M$3:M30))),"")} | N30: {=IFERROR( INDEX($AK$2:$AK$9999,SMALL(IF($AF$2:$AF$9999=$M$2, ROW($AK$2:$AK$9999)-ROW($AK$2)+1),ROWS($M$3:N30))),"")} | O30: {=IFERROR( INDEX($AI$2:$AI$9999,SMALL(IF($AF$2:$AF$9999=$M$2, ROW($AI$2:$AI$9999)-ROW($AI$2)+1),ROWS($O$3:O30))),"")} | P30: {=IFERROR( INDEX($AH$2:$AH$9999,SMALL(IF($AF$2:$AF$9999=$P$2, ROW($AH$2:$AH$9999)-ROW($AH$2)+1),ROWS($P$3:P30))),"")} | Q30: {=IFERROR( INDEX($AK$2:$AK$9999,SMALL(IF($AF$2:$AF$9999=$P$2, ROW($AK$2:$AK$9999)-ROW($AK$2)+1),ROWS($P$3:Q30))),"")} | R30: {=IFERROR( INDEX($AI$2:$AI$9999,SMALL(IF($AF$2:$AF$9999=$P$2, ROW($AI$2:$AI$9999)-ROW($AI$2)+1),ROWS($R$3:R30))),"")} | S30: {=IFERROR( INDEX($AH$2:$AH$9999,SMALL(IF($AF$2:$AF$9999=$S$2, ROW($AH$2:$AH$9999)-ROW($AH$2)+1),ROWS($S$3:S30))),"")} | T30: {=IFERROR( INDEX($AK$2:$AK$9999,SMALL(IF($AF$2:$AF$9999=$S$2, ROW($AK$2:$AK$9999)-ROW($AK$2)+1),ROWS($S$3:T30))),"")} | U30: {=IFERROR( INDEX($AI$2:$AI$9999,SMALL(IF($AF$2:$AF$9999=$S$2, ROW($AI$2:$AI$9999)-ROW($AI$2)+1),ROWS($U$3:U30))),"")} | V30: {=IFERROR( INDEX($AH$2:$AH$9999,SMALL(IF($AF$2:$AF$9999=$V$2, ROW($AH$2:$AH$9999)-ROW($AH$2)+1),ROWS($V$3:V30))),"")} | W30: {=IFERROR( INDEX($AK$2:$AK$9999,SMALL(IF($AF$2:$AF$9999=$V$2, ROW($AK$2:$AK$9999)-ROW($AK$2)+1),ROWS($V$3:W30))),"")} | X30: {=IFERROR( INDEX($AI$2:$AI$9999,SMALL(IF($AF$2:$AF$9999=$V$2, ROW($AI$2:$AI$9999)-ROW($AI$2)+1),ROWS($X$3:X30))),"")} | Y30: {=IFERROR( INDEX($AH$2:$AH$9999,SMALL(IF($AF$2:$AF$9999=$Y$2, ROW($AH$2:$AH$9999)-ROW($AH$2)+1),ROWS($Y$3:Y30))),"")} | Z30: {=IFERROR( INDEX($AK$2:$AK$9999,SMALL(IF($AF$2:$AF$9999=$Y$2, ROW($AK$2:$AK$9999)-ROW($AK$2)+1),ROWS($Y$3:Z30))),"")} | AA30: {=IFERROR( INDEX($AI$2:$AI$9999,SMALL(IF($AF$2:$AF$9999=$Y$2, ROW($AI$2:$AI$9999)-ROW($AI$2)+1),ROWS($AA$3:AA30))),"")} | AB30: {=IFERROR( INDEX($AH$2:$AH$9999,SMALL(IF($AF$2:$AF$9999=$AB$2, ROW($AH$2:$AH$9999)-ROW($AH$2)+1),ROWS($AB$3:AB30))),"")} | AC30: {=IFERROR( INDEX($AK$2:$AK$9999,SMALL(IF($AF$2:$AF$9999=$AB$2, ROW($AK$2:$AK$9999)-ROW($AK$2)+1),ROWS($AB$3:AC30))),"")} | AD30: {=IFERROR( INDEX($AI$2:$AI$9999,SMALL(IF($AF$2:$AF$9999=$AB$2, ROW($AI$2:$AI$9999)-ROW($AI$2)+1),ROWS($AD$3:AD30))),"")} | AE30: ='(1)예금승인내역'!H660 -> 45384 | AF30: =VALUE(AE30) -> 45384 | AG30: ='(1)예금승인내역'!G660 -> 45370 | AH30: ='(1)예금승인내역'!F660 -> 한국석유공사 | AI30: ='(1)예금승인내역'!L660 -> 10 | AJ30: ='(1)예금승인내역'!AG660 -> 0.0523 | AK30: ='(1)예금승인내역'!K660 -> 정기예금
A31: {=IFERROR( INDEX($AH$2:$AH$9999,SMALL(IF($AF$2:$AF$9999=$A$2, ROW($AH$2:$AH$9999)-ROW($AH$2)+1),ROWS(A$3:$A31))),"")} | C31: {=IFERROR( INDEX($AI$2:$AI$9999,SMALL(IF($AF$2:$AF$9999=$A$2, ROW($AI$2:$AI$9999)-ROW($AI$2)+1),ROWS($A$3:C31))),"")} | D31: {=IFERROR( INDEX($AH$2:$AH$9999,SMALL(IF($AF$2:$AF$9999=$D$2, ROW($AH$2:$AH$9999)-ROW($AH$2)+1),ROWS($D$3:D31))),"")} | F31: {=IFERROR( INDEX($AI$2:$AI$9999,SMALL(IF($AF$2:$AF$9999=$D$2, ROW($AI$2:$AI$9999)-ROW($AI$2)+1),ROWS($F$3:F31))),"")} | G31: {=IFERROR( INDEX($AH$2:$AH$9999,SMALL(IF($AF$2:$AF$9999=$G$2, ROW($AH$2:$AH$9999)-ROW($AH$2)+1),ROWS($G$3:G31))),"")} | I31: {=IFERROR( INDEX($AI$2:$AI$9999,SMALL(IF($AF$2:$AF$9999=$G$2, ROW($AI$2:$AI$9999)-ROW($AI$2)+1),ROWS($I$3:I31))),"")} | J31: {=IFERROR( INDEX($AH$2:$AH$9999,SMALL(IF($AF$2:$AF$9999=$J$2, ROW($AH$2:$AH$9999)-ROW($AH$2)+1),ROWS($J$3:J31))),"")} | L31: {=IFERROR( INDEX($AI$2:$AI$9999,SMALL(IF($AF$2:$AF$9999=$J$2, ROW($AI$2:$AI$9999)-ROW($AI$2)+1),ROWS($L$3:L31))),"")} | M31: {=IFERROR( INDEX($AH$2:$AH$9999,SMALL(IF($AF$2:$AF$9999=$M$2, ROW($AH$2:$AH$9999)-ROW($AH$2)+1),ROWS($M$3:M31))),"")} | O31: {=IFERROR( INDEX($AI$2:$AI$9999,SMALL(IF($AF$2:$AF$9999=$M$2, ROW($AI$2:$AI$9999)-ROW($AI$2)+1),ROWS($O$3:O31))),"")} | P31: {=IFERROR( INDEX($AH$2:$AH$9999,SMALL(IF($AF$2:$AF$9999=$P$2, ROW($AH$2:$AH$9999)-ROW($AH$2)+1),ROWS($P$3:P31))),"")} | R31: {=IFERROR( INDEX($AI$2:$AI$9999,SMALL(IF($AF$2:$AF$9999=$P$2, ROW($AI$2:$AI$9999)-ROW($AI$2)+1),ROWS($R$3:R31))),"")} | S31: {=IFERROR( INDEX($AH$2:$AH$9999,SMALL(IF($AF$2:$AF$9999=$S$2, ROW($AH$2:$AH$9999)-ROW($AH$2)+1),ROWS($S$3:S31))),"")} | U31: {=IFERROR( INDEX($AI$2:$AI$9999,SMALL(IF($AF$2:$AF$9999=$S$2, ROW($AI$2:$AI$9999)-ROW($AI$2)+1),ROWS($U$3:U31))),"")} | V31: {=IFERROR( INDEX($AH$2:$AH$9999,SMALL(IF($AF$2:$AF$9999=$V$2, ROW($AH$2:$AH$9999)-ROW($AH$2)+1),ROWS($V$3:V31))),"")} | X31: {=IFERROR( INDEX($AI$2:$AI$9999,SMALL(IF($AF$2:$AF$9999=$V$2, ROW($AI$2:$AI$9999)-ROW($AI$2)+1),ROWS($X$3:X31))),"")} | Y31: {=IFERROR( INDEX($AH$2:$AH$9999,SMALL(IF($AF$2:$AF$9999=$Y$2, ROW($AH$2:$AH$9999)-ROW($AH$2)+1),ROWS($Y$3:Y31))),"")} | AA31: {=IFERROR( INDEX($AI$2:$AI$9999,SMALL(IF($AF$2:$AF$9999=$Y$2, ROW($AI$2:$AI$9999)-ROW($AI$2)+1),ROWS($AA$3:AA31))),"")} | AB31: {=IFERROR( INDEX($AH$2:$AH$9999,SMALL(IF($AF$2:$AF$9999=$AB$2, ROW($AH$2:$AH$9999)-ROW($AH$2)+1),ROWS($AB$3:AB31))),"")} | AD31: {=IFERROR( INDEX($AI$2:$AI$9999,SMALL(IF($AF$2:$AF$9999=$AB$2, ROW($AI$2:$AI$9999)-ROW($AI$2)+1),ROWS($AD$3:AD31))),"")} | AE31: ='(1)예금승인내역'!H661 -> 45408 | AF31: =VALUE(AE31) -> 45408 | AG31: ='(1)예금승인내역'!G661 -> 45377 | AH31: ='(1)예금승인내역'!F661 -> ㈜와이투솔루션 | AI31: ='(1)예금승인내역'!L661 -> 8 | AJ31: ='(1)예금승인내역'!AG661 -> 0.0523 | AK31: ='(1)예금승인내역'!K661 -> 정기예금
C32: =SUM(C3:C31) -> 20.7 | F32: =SUM(F3:F31) -> 7.84 | I32: =SUM(I3:I31) -> 2 | L32: =SUM(L3:L31) -> 0 | O32: =SUM(O3:O31) -> 43.12 | R32: =SUM(R3:R31) -> 0 | U32: =SUM(U3:U31) -> 0 | X32: =SUM(X3:X31) -> 9.67 | AA32: =SUM(AA3:AA31) -> 2 | AD32: =SUM(AD3:AD31) -> 0 | AE32: ='(1)예금승인내역'!H662 -> 45408 | AF32: =VALUE(AE32) -> 45408 | AG32: ='(1)예금승인내역'!G662 -> 45377 | AH32: ='(1)예금승인내역'!F662 -> ㈜와이투솔루션 | AI32: ='(1)예금승인내역'!L662 -> 1 | AJ32: ='(1)예금승인내역'!AG662 -> 0.0523 | AK32: ='(1)예금승인내역'!K662 -> 정기예금
AE33: ='(1)예금승인내역'!H663 -> 45408 | AF33: =VALUE(AE33) -> 45408 | AG33: ='(1)예금승인내역'!G663 -> 45377 | AH33: ='(1)예금승인내역'!F663 -> ㈜와이투솔루션 | AI33: ='(1)예금승인내역'!L663 -> 1 | AJ33: ='(1)예금승인내역'!AG663 -> 0.0523 | AK33: ='(1)예금승인내역'!K663 -> 정기예금
A34: 46079 | AE34: ='(1)예금승인내역'!H664 -> 45406 | AF34: =VALUE(AE34) -> 45406 | AG34: ='(1)예금승인내역'!G664 -> 45386 | AH34: ='(1)예금승인내역'!F664 -> 한국석유공사 | AI34: ='(1)예금승인내역'!L664 -> 100 | AJ34: ='(1)예금승인내역'!AG664 -> 0.05 | AK34: ='(1)예금승인내역'!K664 -> 정기예금
A35: 1. 2월 27일(금) 김상범 MMDA 1백만불 - 요청오면 금리 3.15% 로 승인 부탁해 | AE35: ='(1)예금승인내역'!H665 -> 45419 | AF35: =VALUE(AE35) -> 45419 | AG35: ='(1)예금승인내역'!G665 -> 45387 | AH35: ='(1)예금승인내역'!F665 -> 한국비철㈜ | AI35: ='(1)예금승인내역'!L665 -> 7 | AJ35: ='(1)예금승인내역'!AG665 -> 0.052 | AK35: ='(1)예금승인내역'!K665 -> 정기예금
A36: 2. 울산지점 김미경팀장님 1개월 3.4 제시 | AE36: ='(1)예금승인내역'!H666 -> 45419 | AF36: =VALUE(AE36) -> 45419 | AG36: ='(1)예금승인내역'!G666 -> 45387 | AH36: ='(1)예금승인내역'!F666 -> 한국비철㈜ | AI36: ='(1)예금승인내역'!L666 -> 1 | AJ36: ='(1)예금승인내역'!AG666 -> 0.052 | AK36: ='(1)예금승인내역'!K666 -> 정기예금
AE37: ='(1)예금승인내역'!H667 -> 45426 | AF37: =VALUE(AE37) -> 45426 | AG37: ='(1)예금승인내역'!G667 -> 45397 | AH37: ='(1)예금승인내역'!F667 -> 오스템임플란트㈜ | AI37: ='(1)예금승인내역'!L667 -> 2 | AJ37: ='(1)예금승인내역'!AG667 -> 0.0435 | AK37: ='(1)예금승인내역'!K667 -> MMDA
AE38: ='(1)예금승인내역'!H668 -> 45492 | AF38: =VALUE(AE38) -> 45492 | AG38: ='(1)예금승인내역'!G668 -> 45401 | AH38: ='(1)예금승인내역'!F668 -> 에스엠상선㈜ | AI38: ='(1)예금승인내역'!L668 -> 10 | AJ38: ='(1)예금승인내역'!AG668 -> 0.0533 | AK38: ='(1)예금승인내역'!K668 -> 정기예금
AE39: ='(1)예금승인내역'!H669 -> 45450 | AF39: =VALUE(AE39) -> 45450 | AG39: ='(1)예금승인내역'!G669 -> 45419 | AH39: ='(1)예금승인내역'!F669 -> 한국비철㈜ | AI39: ='(1)예금승인내역'!L669 -> 7 | AJ39: ='(1)예금승인내역'!AG669 -> 0.052 | AK39: ='(1)예금승인내역'!K669 -> 정기예금
AE40: ='(1)예금승인내역'!H670 -> 45450 | AF40: =VALUE(AE40) -> 45450 | AG40: ='(1)예금승인내역'!G670 -> 45419 | AH40: ='(1)예금승인내역'!F670 -> 한국비철㈜ | AI40: ='(1)예금승인내역'!L670 -> 1 | AJ40: ='(1)예금승인내역'!AG670 -> 0.052 | AK40: ='(1)예금승인내역'!K670 -> 정기예금
AE41: ='(1)예금승인내역'!H671 -> 45450 | AF41: =VALUE(AE41) -> 45450 | AG41: ='(1)예금승인내역'!G671 -> 45420 | AH41: ='(1)예금승인내역'!F671 -> 한국비철㈜ | AI41: ='(1)예금승인내역'!L671 -> 2 | AJ41: ='(1)예금승인내역'!AG671 -> 0.0535 | AK41: ='(1)예금승인내역'!K671 -> MMDA
AE42: ='(1)예금승인내역'!H672 -> 45457 | AF42: =VALUE(AE42) -> 45457 | AG42: ='(1)예금승인내역'!G672 -> 45426 | AH42: ='(1)예금승인내역'!F672 -> 오스템임플란트㈜ | AI42: ='(1)예금승인내역'!L672 -> 2 | AJ42: ='(1)예금승인내역'!AG672 -> 0.0435 | AK42: ='(1)예금승인내역'!K672 -> MMDA
AE43: ='(1)예금승인내역'!H673 -> 45518 | AF43: =VALUE(AE43) -> 45518 | AG43: ='(1)예금승인내역'!G673 -> 45426 | AH43: ='(1)예금승인내역'!F673 -> 대성산업㈜ | AI43: ='(1)예금승인내역'!L673 -> 3.5 | AJ43: ='(1)예금승인내역'!AG673 -> 0.0533 | AK43: ='(1)예금승인내역'!K673 -> 정기예금
AE44: ='(1)예금승인내역'!H674 -> 45559 | AF44: =VALUE(AE44) -> 45559 | AG44: ='(1)예금승인내역'!G674 -> 45436 | AH44: ='(1)예금승인내역'!F674 -> 일양약품㈜ | AI44: ='(1)예금승인내역'!L674 -> 3 | AJ44: ='(1)예금승인내역'!AG674 -> 0.0535 | AK44: ='(1)예금승인내역'!K674 -> 정기예금
AE45: ='(1)예금승인내역'!H675 -> 45503 | AF45: =VALUE(AE45) -> 45503 | AG45: ='(1)예금승인내역'!G675 -> 45439 | AH45: ='(1)예금승인내역'!F675 -> 에스엠상선㈜ | AI45: ='(1)예금승인내역'!L675 -> 10 | AJ45: ='(1)예금승인내역'!AG675 -> 0.053 | AK45: ='(1)예금승인내역'!K675 -> 정기예금
AE46: ='(1)예금승인내역'!H676 -> 45470 | AF46: =VALUE(AE46) -> 45470 | AG46: ='(1)예금승인내역'!G676 -> 45439 | AH46: ='(1)예금승인내역'!F676 -> ㈜와이투솔루션 | AI46: ='(1)예금승인내역'!L676 -> 10 | AJ46: ='(1)예금승인내역'!AG676 -> 0.0523 | AK46: ='(1)예금승인내역'!K676 -> 정기예금
AE47: ='(1)예금승인내역'!H677 -> 45470 | AF47: =VALUE(AE47) -> 45470 | AG47: ='(1)예금승인내역'!G677 -> 45439 | AH47: ='(1)예금승인내역'!F677 -> ㈜와이투솔루션 | AI47: ='(1)예금승인내역'!L677 -> 2 | AJ47: ='(1)예금승인내역'!AG677 -> 0.0523 | AK47: ='(1)예금승인내역'!K677 -> 정기예금
AE48: ='(1)예금승인내역'!H678 -> 45476 | AF48: =VALUE(AE48) -> 45476 | AG48: ='(1)예금승인내역'!G678 -> 45446 | AH48: ='(1)예금승인내역'!F678 -> ㈜이수스페셜티케미컬 | AI48: ='(1)예금승인내역'!L678 -> 2 | AJ48: ='(1)예금승인내역'!AG678 -> 0.054 | AK48: ='(1)예금승인내역'!K678 -> MMDA
... AE357: ='(1)예금승인내역'!H987 -> 45964 | AF357: =VALUE(AE357) -> 45964 | AG357: ='(1)예금승인내역'!G987 -> 45931 | AH357: ='(1)예금승인내역'!F987 -> 와이투솔루션 | AI357: ='(1)예금승인내역'!L987 -> 1 | AJ357: ='(1)예금승인내역'!AG987 -> 0.0385 | AK357: ='(1)예금승인내역'!K987 -> 정기예금
AE358: ='(1)예금승인내역'!H990 -> 45964 | AF358: =VALUE(AE358) -> 45964 | AG358: ='(1)예금승인내역'!G990 -> 45931 | AH358: ='(1)예금승인내역'!F990 -> ㈜지엠메탈 | AI358: ='(1)예금승인내역'!L990 -> 1.25 | AJ358: ='(1)예금승인내역'!AG990 -> 0.035 | AK358: ='(1)예금승인내역'!K990 -> MMDA
AE359: ='(1)예금승인내역'!H991 -> 45964 | AF359: =VALUE(AE359) -> 45964 | AG359: ='(1)예금승인내역'!G991 -> 45931 | AH359: ='(1)예금승인내역'!F991 -> 국제금속 | AI359: ='(1)예금승인내역'!L991 -> 9 | AJ359: ='(1)예금승인내역'!AG991 -> 0.034 | AK359: ='(1)예금승인내역'!K991 -> MMDA
AE360: ='(1)예금승인내역'!H992 -> 45966 | AF360: =VALUE(AE360) -> 45966 | AG360: ='(1)예금승인내역'!G992 -> 45931 | AH360: ='(1)예금승인내역'!F992 -> 에스엠상선㈜ | AI360: ='(1)예금승인내역'!L992 -> 10 | AJ360: ='(1)예금승인내역'!AG992 -> 0.0395 | AK360: ='(1)예금승인내역'!K992 -> 정기예금
AE361: ='(1)예금승인내역'!H993 -> 45947 | AF361: =VALUE(AE361) -> 45947 | AG361: ='(1)예금승인내역'!G993 -> 45940 | AH361: ='(1)예금승인내역'!F993 -> ㈜일지테크 | AI361: ='(1)예금승인내역'!L993 -> 1.5 | AJ361: ='(1)예금승인내역'!AG993 -> 0.035 | AK361: ='(1)예금승인내역'!K993 -> 정기예금
AE362: ='(1)예금승인내역'!H994 -> 45947 | AF362: =VALUE(AE362) -> 45947 | AG362: ='(1)예금승인내역'!G994 -> 45940 | AH362: ='(1)예금승인내역'!F994 -> ㈜일지테크 | AI362: ='(1)예금승인내역'!L994 -> 2 | AJ362: ='(1)예금승인내역'!AG994 -> 0.035 | AK362: ='(1)예금승인내역'!K994 -> 정기예금
AE363: ='(1)예금승인내역'!H995 -> 45947 | AF363: =VALUE(AE363) -> 45947 | AG363: ='(1)예금승인내역'!G995 -> 45940 | AH363: ='(1)예금승인내역'!F995 -> ㈜일지테크 | AI363: ='(1)예금승인내역'!L995 -> 2 | AJ363: ='(1)예금승인내역'!AG995 -> 0.035 | AK363: ='(1)예금승인내역'!K995 -> 정기예금
AE364: ='(1)예금승인내역'!H996 -> 45947 | AF364: =VALUE(AE364) -> 45947 | AG364: ='(1)예금승인내역'!G996 -> 45940 | AH364: ='(1)예금승인내역'!F996 -> ㈜일지테크 | AI364: ='(1)예금승인내역'!L996 -> 2 | AJ364: ='(1)예금승인내역'!AG996 -> 0.035 | AK364: ='(1)예금승인내역'!K996 -> 정기예금
AE365: ='(1)예금승인내역'!H997 -> 45947 | AF365: =VALUE(AE365) -> 45947 | AG365: ='(1)예금승인내역'!G997 -> 45940 | AH365: ='(1)예금승인내역'!F997 -> ㈜일지테크 | AI365: ='(1)예금승인내역'!L997 -> 2 | AJ365: ='(1)예금승인내역'!AG997 -> 0.035 | AK365: ='(1)예금승인내역'!K997 -> 정기예금
AE366: ='(1)예금승인내역'!H998 -> 45971 | AF366: =VALUE(AE366) -> 45971 | AG366: ='(1)예금승인내역'!G998 -> 45940 | AH366: ='(1)예금승인내역'!F998 -> ㈜현대그린푸드 | AI366: ='(1)예금승인내역'!L998 -> 2 | AJ366: ='(1)예금승인내역'!AG998 -> 0.035 | AK366: ='(1)예금승인내역'!K998 -> MMDA
AE367: ='(1)예금승인내역'!H999 -> 45971 | AF367: =VALUE(AE367) -> 45971 | AG367: ='(1)예금승인내역'!G999 -> 45940 | AH367: ='(1)예금승인내역'!F999 -> ㈜이수스페셜티케미컬 | AI367: ='(1)예금승인내역'!L999 -> 3.17 | AJ367: ='(1)예금승인내역'!AG999 -> 0.035 | AK367: ='(1)예금승인내역'!K999 -> MMDA
AE368: ='(1)예금승인내역'!H1000 -> 45974 | AF368: =VALUE(AE368) -> 45974 | AG368: ='(1)예금승인내역'!G1000 -> 45943 | AH368: ='(1)예금승인내역'!F1000 -> 한국비철㈜ | AI368: ='(1)예금승인내역'!L1000 -> 11.6 | AJ368: ='(1)예금승인내역'!AG1000 -> 0.038 | AK368: ='(1)예금승인내역'!K1000 -> 정기예금
AE369: ='(1)예금승인내역'!H1001 -> 45974 | AF369: =VALUE(AE369) -> 45974 | AG369: ='(1)예금승인내역'!G1001 -> 45943 | AH369: ='(1)예금승인내역'!F1001 -> 한국비철㈜ (해지) | AI369: ='(1)예금승인내역'!L1001 -> 1.6 | AJ369: ='(1)예금승인내역'!AG1001 -> 0.038 | AK369: ='(1)예금승인내역'!K1001 -> 정기예금
... AE386: ='(1)예금승인내역'!H1018 -> 45961 | AF386: =VALUE(AE386) -> 45961 | AG386: ='(1)예금승인내역'!G1018 -> 45954 | AH386: ='(1)예금승인내역'!F1018 -> ㈜일지테크 | AI386: ='(1)예금승인내역'!L1018 -> 1.5 | AJ386: ='(1)예금승인내역'!AG1018 -> 0.035 | AK386: ='(1)예금승인내역'!K1018 -> 정기예금
AE387: ='(1)예금승인내역'!H1018 -> 45961 | AF387: =VALUE(AE387) -> 45961 | AG387: ='(1)예금승인내역'!G1018 -> 45954 | AH387: ='(1)예금승인내역'!F1018 -> ㈜일지테크 | AI387: ='(1)예금승인내역'!L1018 -> 1.5 | AJ387: ='(1)예금승인내역'!AG1018 -> 0.035 | AK387: ='(1)예금승인내역'!K1018 -> 정기예금
AE388: ='(1)예금승인내역'!H1019 -> 45961 | AF388: =VALUE(AE388) -> 45961 | AG388: ='(1)예금승인내역'!G1019 -> 45954 | AH388: ='(1)예금승인내역'!F1019 -> ㈜일지테크 | AI388: ='(1)예금승인내역'!L1019 -> 2 | AJ388: ='(1)예금승인내역'!AG1019 -> 0.035 | AK388: ='(1)예금승인내역'!K1019 -> 정기예금
AE389: ='(1)예금승인내역'!H1020 -> 45961 | AF389: =VALUE(AE389) -> 45961 | AG389: ='(1)예금승인내역'!G1020 -> 45954 | AH389: ='(1)예금승인내역'!F1020 -> ㈜일지테크 | AI389: ='(1)예금승인내역'!L1020 -> 2 | AJ389: ='(1)예금승인내역'!AG1020 -> 0.035 | AK389: ='(1)예금승인내역'!K1020 -> 정기예금
AE390: ='(1)예금승인내역'!H1021 -> 45961 | AF390: =VALUE(AE390) -> 45961 | AG390: ='(1)예금승인내역'!G1021 -> 45954 | AH390: ='(1)예금승인내역'!F1021 -> ㈜일지테크 | AI390: ='(1)예금승인내역'!L1021 -> 2 | AJ390: ='(1)예금승인내역'!AG1021 -> 0.035 | AK390: ='(1)예금승인내역'!K1021 -> 정기예금
AE391: ='(1)예금승인내역'!H1022 -> 45961 | AF391: =VALUE(AE391) -> 45961 | AG391: ='(1)예금승인내역'!G1022 -> 45954 | AH391: ='(1)예금승인내역'!F1022 -> ㈜일지테크 | AI391: ='(1)예금승인내역'!L1022 -> 2 | AJ391: ='(1)예금승인내역'!AG1022 -> 0.035 | AK391: ='(1)예금승인내역'!K1022 -> 정기예금
AE392: ='(1)예금승인내역'!H1023 -> 45961 | AF392: =VALUE(AE392) -> 45961 | AG392: ='(1)예금승인내역'!G1023 -> 45954 | AH392: ='(1)예금승인내역'!F1023 -> ㈜일지테크 | AI392: ='(1)예금승인내역'!L1023 -> 2 | AJ392: ='(1)예금승인내역'!AG1023 -> 0.035 | AK392: ='(1)예금승인내역'!K1023 -> 정기예금
AE393: ='(1)예금승인내역'!H1024 -> 45988 | AF393: =VALUE(AE393) -> 45988 | AG393: ='(1)예금승인내역'!G1024 -> 45957 | AH393: ='(1)예금승인내역'!F1024 -> ㈜와이투솔루션 | AI393: ='(1)예금승인내역'!L1024 -> 1 | AJ393: ='(1)예금승인내역'!AG1024 -> 0.034 | AK393: ='(1)예금승인내역'!K1024 -> MMDA
AE394: ='(1)예금승인내역'!H1025 -> 45992 | AF394: =VALUE(AE394) -> 45992 | AG394: ='(1)예금승인내역'!G1025 -> 45959 | AH394: ='(1)예금승인내역'!F1025 -> 디오㈜ | AI394: ='(1)예금승인내역'!L1025 -> 2 | AJ394: ='(1)예금승인내역'!AG1025 -> 0.037 | AK394: ='(1)예금승인내역'!K1025 -> 정기예금
AE395: ='(1)예금승인내역'!H1026 -> 45992 | AF395: =VALUE(AE395) -> 45992 | AG395: ='(1)예금승인내역'!G1026 -> 45959 | AH395: ='(1)예금승인내역'!F1026 -> 미래에셋컨설팅 | AI395: ='(1)예금승인내역'!L1026 -> 2 | AJ395: ='(1)예금승인내역'!AG1026 -> 0.037 | AK395: ='(1)예금승인내역'!K1026 -> 정기예금
AE396: ='(1)예금승인내역'!H1027 -> 45992 | AF396: =VALUE(AE396) -> 45992 | AG396: ='(1)예금승인내역'!G1027 -> 45959 | AH396: ='(1)예금승인내역'!F1027 -> 한화에어로스페이스 | AI396: ='(1)예금승인내역'!L1027 -> 10 | AJ396: ='(1)예금승인내역'!AG1027 -> 0.0375 | AK396: ='(1)예금승인내역'!K1027 -> 정기예금
AE397: ='(1)예금승인내역'!H1028 -> 46052 | AF397: =VALUE(AE397) -> 46052 | AG397: ='(1)예금승인내역'!G1028 -> 45960 | AH397: ='(1)예금승인내역'!F1028 -> 와이엠에스에이 | AI397: ='(1)예금승인내역'!L1028 -> 4 | AJ397: ='(1)예금승인내역'!AG1028 -> 0.0372 | AK397: ='(1)예금승인내역'!K1028 -> 정기예금
AE398: ='(1)예금승인내역'!H1029 -> 45968 | AF398: =VALUE(AE398) -> 45968 | AG398: ='(1)예금승인내역'!G1029 -> 45961 | AH398: ='(1)예금승인내역'!F1029 -> ㈜일지테크 | AI398: ='(1)예금승인내역'!L1029 -> 1.5 | AJ398: ='(1)예금승인내역'!AG1029 -> 0.035 | AK398: ='(1)예금승인내역'!K1029 -> 정기예금
... AE423: ='(1)예금승인내역'!H1054 -> 46006 | AF423: =VALUE(AE423) -> 46006 | AG423: ='(1)예금승인내역'!G1054 -> 45974 | AH423: ='(1)예금승인내역'!F1054 -> 주식회사 한국비앤씨 | AI423: ='(1)예금승인내역'!L1054 -> 7.12 | AJ423: ='(1)예금승인내역'!AG1054 -> 0.0335 | AK423: ='(1)예금승인내역'!K1054 -> MMDA
AE424: ='(1)예금승인내역'!H1054 -> 46006 | AF424: =VALUE(AE424) -> 46006 | AG424: ='(1)예금승인내역'!G1054 -> 45974 | AH424: ='(1)예금승인내역'!F1054 -> 주식회사 한국비앤씨 | AI424: ='(1)예금승인내역'!L1054 -> 7.12 | AJ424: ='(1)예금승인내역'!AG1054 -> 0.0335 | AK424: ='(1)예금승인내역'!K1054 -> MMDA
AE425: ='(1)예금승인내역'!H1055 -> 46066 | AF425: =VALUE(AE425) -> 46066 | AG425: ='(1)예금승인내역'!G1055 -> 45974 | AH425: ='(1)예금승인내역'!F1055 -> 해내다컨트리클럽 | AI425: ='(1)예금승인내역'!L1055 -> 1.44 | AJ425: ='(1)예금승인내역'!AG1055 -> 0.0377 | AK425: ='(1)예금승인내역'!K1055 -> 정기예금
AE426: ='(1)예금승인내역'!H1056 -> 46066 | AF426: =VALUE(AE426) -> 46066 | AG426: ='(1)예금승인내역'!G1056 -> 45974 | AH426: ='(1)예금승인내역'!F1056 -> 동아홀딩스 | AI426: ='(1)예금승인내역'!L1056 -> 1.44 | AJ426: ='(1)예금승인내역'!AG1056 -> 0.0377 | AK426: ='(1)예금승인내역'!K1056 -> 정기예금
AE427: ='(1)예금승인내역'!H1057 -> 45982 | AF427: =VALUE(AE427) -> 45982 | AG427: ='(1)예금승인내역'!G1057 -> 45975 | AH427: ='(1)예금승인내역'!F1057 -> ㈜일지테크 | AI427: ='(1)예금승인내역'!L1057 -> 2 | AJ427: ='(1)예금승인내역'!AG1057 -> 0.0342 | AK427: ='(1)예금승인내역'!K1057 -> 정기예금
AE428: ='(1)예금승인내역'!H1058 -> 45989 | AF428: =VALUE(AE428) -> 45989 | AG428: ='(1)예금승인내역'!G1058 -> 45975 | AH428: ='(1)예금승인내역'!F1058 -> ㈜일지테크 | AI428: ='(1)예금승인내역'!L1058 -> 4.5 | AJ428: ='(1)예금승인내역'!AG1058 -> 0.0345 | AK428: ='(1)예금승인내역'!K1058 -> 정기예금
AE429: ='(1)예금승인내역'!H1059 -> 45989 | AF429: =VALUE(AE429) -> 45989 | AG429: ='(1)예금승인내역'!G1059 -> 45975 | AH429: ='(1)예금승인내역'!F1059 -> ㈜일지테크 | AI429: ='(1)예금승인내역'!L1059 -> 3 | AJ429: ='(1)예금승인내역'!AG1059 -> 0.0345 | AK429: ='(1)예금승인내역'!K1059 -> 정기예금
AE430: ='(1)예금승인내역'!H1060 -> 46066 | AF430: =VALUE(AE430) -> 46066 | AG430: ='(1)예금승인내역'!G1060 -> 45975 | AH430: ='(1)예금승인내역'!F1060 -> 동아홀딩스 | AI430: ='(1)예금승인내역'!L1060 -> 3.61 | AJ430: ='(1)예금승인내역'!AG1060 -> 0.0377 | AK430: ='(1)예금승인내역'!K1060 -> 정기예금
AE431: ='(1)예금승인내역'!H1061 -> 46008 | AF431: =VALUE(AE431) -> 46008 | AG431: ='(1)예금승인내역'!G1061 -> 45978 | AH431: ='(1)예금승인내역'!F1061 -> 대원지에스아이 | AI431: ='(1)예금승인내역'!L1061 -> 1.5 | AJ431: ='(1)예금승인내역'!AG1061 -> 0.037 | AK431: ='(1)예금승인내역'!K1061 -> 정기예금
AE432: ='(1)예금승인내역'!H1062 -> 46072 | AF432: =VALUE(AE432) -> 46072 | AG432: ='(1)예금승인내역'!G1062 -> 45979 | AH432: ='(1)예금승인내역'!F1062 -> ㈜비알팜 | AI432: ='(1)예금승인내역'!L1062 -> 1 | AJ432: ='(1)예금승인내역'!AG1062 -> 0.0385 | AK432: ='(1)예금승인내역'!K1062 -> 정기예금
AE433: ='(1)예금승인내역'!H1063 -> 46013 | AF433: =VALUE(AE433) -> 46013 | AG433: ='(1)예금승인내역'!G1063 -> 45981 | AH433: ='(1)예금승인내역'!F1063 -> 오스템임플란트㈜ | AI433: ='(1)예금승인내역'!L1063 -> 4 | AJ433: ='(1)예금승인내역'!AG1063 -> 0.034 | AK433: ='(1)예금승인내역'!K1063 -> MMDA
AE434: ='(1)예금승인내역'!H1064 -> 46013 | AF434: =VALUE(AE434) -> 46013 | AG434: ='(1)예금승인내역'!G1064 -> 45981 | AH434: ='(1)예금승인내역'!F1064 -> 오스템임플란트㈜ | AI434: ='(1)예금승인내역'!L1064 -> 4.4 | AJ434: ='(1)예금승인내역'!AG1064 -> 0.034 | AK434: ='(1)예금승인내역'!K1064 -> MMDA
AE435: ='(1)예금승인내역'!H1065 -> 46013 | AF435: =VALUE(AE435) -> 46013 | AG435: ='(1)예금승인내역'!G1065 -> 45981 | AH435: ='(1)예금승인내역'!F1065 -> 동화인더스트리 | AI435: ='(1)예금승인내역'!L1065 -> 1.01 | AJ435: ='(1)예금승인내역'!AG1065 -> 0.0373 | AK435: ='(1)예금승인내역'!K1065 -> 정기예금
... AE458: ='(1)예금승인내역'!H1088 -> 46037 | AF458: =VALUE(AE458) -> 46037 | AG458: ='(1)예금승인내역'!G1088 -> 46006 | AH458: ='(1)예금승인내역'!F1088 -> 한국비철㈜ | AI458: ='(1)예금승인내역'!L1088 -> 7.2 | AJ458: ='(1)예금승인내역'!AG1088 -> 0.035 | AK458: ='(1)예금승인내역'!K1088 -> 정기예금
AE459: ='(1)예금승인내역'!H1090 -> 46037 | AF459: =VALUE(AE459) -> 46037 | AG459: ='(1)예금승인내역'!G1090 -> 46006 | AH459: ='(1)예금승인내역'!F1090 -> 주식회사 한국비앤씨 | AI459: ='(1)예금승인내역'!L1090 -> 7.31 | AJ459: ='(1)예금승인내역'!AG1090 -> 0.0315 | AK459: ='(1)예금승인내역'!K1090 -> MMDA
AE460: ='(1)예금승인내역'!H1091 -> 46097 | AF460: =VALUE(AE460) -> 46097 | AG460: ='(1)예금승인내역'!G1091 -> 46007 | AH460: ='(1)예금승인내역'!F1091 -> ㈜ 동아홀딩스 | AI460: ='(1)예금승인내역'!L1091 -> 2.17 | AJ460: ='(1)예금승인내역'!AG1091 -> 0.0365 | AK460: ='(1)예금승인내역'!K1091 -> 정기예금
AE461: ='(1)예금승인내역'!H1092 -> 46097 | AF461: =VALUE(AE461) -> 46097 | AG461: ='(1)예금승인내역'!G1092 -> 46007 | AH461: ='(1)예금승인내역'!F1092 -> 해내다컨트리클럽 | AI461: ='(1)예금승인내역'!L1092 -> 3.622 | AJ461: ='(1)예금승인내역'!AG1092 -> 0.0365 | AK461: ='(1)예금승인내역'!K1092 -> 정기예금
AE462: ='(1)예금승인내역'!H1093 -> 46041 | AF462: =VALUE(AE462) -> 46041 | AG462: ='(1)예금승인내역'!G1093 -> 46008 | AH462: ='(1)예금승인내역'!F1093 -> 대원지에스아이 | AI462: ='(1)예금승인내역'!L1093 -> 1.5 | AJ462: ='(1)예금승인내역'!AG1093 -> 0.035 | AK462: ='(1)예금승인내역'!K1093 -> 정기예금
AE463: ='(1)예금승인내역'!H1094 -> 46098 | AF463: =VALUE(AE463) -> 46098 | AG463: ='(1)예금승인내역'!G1094 -> 46008 | AH463: ='(1)예금승인내역'!F1094 -> 거림테크주식회사 | AI463: ='(1)예금승인내역'!L1094 -> 1 | AJ463: ='(1)예금승인내역'!AG1094 -> 0.037 | AK463: ='(1)예금승인내역'!K1094 -> 정기예금
AE464: ='(1)예금승인내역'!H1095 -> 46098 | AF464: =VALUE(AE464) -> 46098 | AG464: ='(1)예금승인내역'!G1095 -> 46008 | AH464: ='(1)예금승인내역'!F1095 -> 거림테크주식회사 | AI464: ='(1)예금승인내역'!L1095 -> 1 | AJ464: ='(1)예금승인내역'!AG1095 -> 0.037 | AK464: ='(1)예금승인내역'!K1095 -> 정기예금
AE465: ='(1)예금승인내역'!H1096 -> 46041 | AF465: =VALUE(AE465) -> 46041 | AG465: ='(1)예금승인내역'!G1096 -> 46010 | AH465: ='(1)예금승인내역'!F1096 -> 와이엠에스에이 | AI465: ='(1)예금승인내역'!L1096 -> 1.43 | AJ465: ='(1)예금승인내역'!AG1096 -> 0.032 | AK465: ='(1)예금승인내역'!K1096 -> MMDA
AE466: ='(1)예금승인내역'!H1097 -> 46041 | AF466: =VALUE(AE466) -> 46041 | AG466: ='(1)예금승인내역'!G1097 -> 46010 | AH466: ='(1)예금승인내역'!F1097 -> ㈜약진통상 | AI466: ='(1)예금승인내역'!L1097 -> 10.53 | AJ466: ='(1)예금승인내역'!AG1097 -> 0.032 | AK466: ='(1)예금승인내역'!K1097 -> MMDA
AE467: ='(1)예금승인내역'!H1098 -> 46044 | AF467: =VALUE(AE467) -> 46044 | AG467: ='(1)예금승인내역'!G1098 -> 46013 | AH467: ='(1)예금승인내역'!F1098 -> 오스템임플란트㈜ | AI467: ='(1)예금승인내역'!L1098 -> 4 | AJ467: ='(1)예금승인내역'!AG1098 -> 0.032 | AK467: ='(1)예금승인내역'!K1098 -> MMDA
AE468: ='(1)예금승인내역'!H1099 -> 46104 | AF468: =VALUE(AE468) -> 46104 | AG468: ='(1)예금승인내역'!G1099 -> 46013 | AH468: ='(1)예금승인내역'!F1099 -> ㈜비앤에프 | AI468: ='(1)예금승인내역'!L1099 -> 2 | AJ468: ='(1)예금승인내역'!AG1099 -> 0.037 | AK468: ='(1)예금승인내역'!K1099 -> 정기예금
AE469: ='(1)예금승인내역'!H1100 -> 46049 | AF469: =VALUE(AE469) -> 46049 | AG469: ='(1)예금승인내역'!G1100 -> 46015 | AH469: ='(1)예금승인내역'!F1100 -> 김상범 | AI469: ='(1)예금승인내역'!L1100 -> 1 | AJ469: ='(1)예금승인내역'!AG1100 -> 0.032 | AK469: ='(1)예금승인내역'!K1100 -> MMDA
AE470: ='(1)예금승인내역'!H1101 -> 46027 | AF470: =VALUE(AE470) -> 46027 | AG470: ='(1)예금승인내역'!G1101 -> 46017 | AH470: ='(1)예금승인내역'!F1101 -> ㈜일지테크 | AI470: ='(1)예금승인내역'!L1101 -> 10 | AJ470: ='(1)예금승인내역'!AG1101 -> 0.032 | AK470: ='(1)예금승인내역'!K1101 -> 정기예금
... AE479: ='(1)예금승인내역'!H1110 -> 46055 | AF479: =VALUE(AE479) -> 46055 | AG479: ='(1)예금승인내역'!G1110 -> 46024 | AH479: ='(1)예금승인내역'!F1110 -> 디오㈜ | AI479: ='(1)예금승인내역'!L1110 -> 2 | AJ479: ='(1)예금승인내역'!AG1110 -> 0.035 | AK479: ='(1)예금승인내역'!K1110 -> 정기예금
AE480: ='(1)예금승인내역'!H1110 -> 46055 | AF480: =VALUE(AE480) -> 46055 | AG480: ='(1)예금승인내역'!G1110 -> 46024 | AH480: ='(1)예금승인내역'!F1110 -> 디오㈜ | AI480: ='(1)예금승인내역'!L1110 -> 2 | AJ480: ='(1)예금승인내역'!AG1110 -> 0.035 | AK480: ='(1)예금승인내역'!K1110 -> 정기예금
AE481: ='(1)예금승인내역'!H1111 -> 46055 | AF481: =VALUE(AE481) -> 46055 | AG481: ='(1)예금승인내역'!G1111 -> 46024 | AH481: ='(1)예금승인내역'!F1111 -> 거림테크주식회사 | AI481: ='(1)예금승인내역'!L1111 -> 1.46 | AJ481: ='(1)예금승인내역'!AG1111 -> 0.03 | AK481: ='(1)예금승인내역'!K1111 -> MMDA
AE482: ='(1)예금승인내역'!H1112 -> 46391 | AF482: =VALUE(AE482) -> 46391 | AG482: ='(1)예금승인내역'!G1112 -> 46024 | AH482: ='(1)예금승인내역'!F1112 -> 윤만수 | AI482: ='(1)예금승인내역'!L1112 -> 2 | AJ482: ='(1)예금승인내역'!AG1112 -> 0.0345 | AK482: ='(1)예금승인내역'!K1112 -> 정기예금
AE483: ='(1)예금승인내역'!H1113 -> 46055 | AF483: =VALUE(AE483) -> 46055 | AG483: ='(1)예금승인내역'!G1113 -> 46024 | AH483: ='(1)예금승인내역'!F1113 -> ㈜ 광성 | AI483: ='(1)예금승인내역'!L1113 -> 4 | AJ483: ='(1)예금승인내역'!AG1113 -> 0.032 | AK483: ='(1)예금승인내역'!K1113 -> MMDA
AE484: ='(1)예금승인내역'!H1114 -> 46038 | AF484: =VALUE(AE484) -> 46038 | AG484: ='(1)예금승인내역'!G1114 -> 46027 | AH484: ='(1)예금승인내역'!F1114 -> ㈜일지테크 | AI484: ='(1)예금승인내역'!L1114 -> 10.02 | AJ484: ='(1)예금승인내역'!AG1114 -> 0.032 | AK484: ='(1)예금승인내역'!K1114 -> 정기예금
AE485: ='(1)예금승인내역'!H1115 -> 46038 | AF485: =VALUE(AE485) -> 46038 | AG485: ='(1)예금승인내역'!G1115 -> 46027 | AH485: ='(1)예금승인내역'!F1115 -> ㈜일지테크 | AI485: ='(1)예금승인내역'!L1115 -> 10.02 | AJ485: ='(1)예금승인내역'!AG1115 -> 0.032 | AK485: ='(1)예금승인내역'!K1115 -> 정기예금
AE486: ='(1)예금승인내역'!H1116 -> 46038 | AF486: =VALUE(AE486) -> 46038 | AG486: ='(1)예금승인내역'!G1116 -> 46027 | AH486: ='(1)예금승인내역'!F1116 -> ㈜일지테크 | AI486: ='(1)예금승인내역'!L1116 -> 12.62 | AJ486: ='(1)예금승인내역'!AG1116 -> 0.032 | AK486: ='(1)예금승인내역'!K1116 -> 정기예금
AE487: ='(1)예금승인내역'!H1117 -> 46038 | AF487: =VALUE(AE487) -> 46038 | AG487: ='(1)예금승인내역'!G1117 -> 46027 | AH487: ='(1)예금승인내역'!F1117 -> ㈜일지테크 | AI487: ='(1)예금승인내역'!L1117 -> 6.5 | AJ487: ='(1)예금승인내역'!AG1117 -> 0.032 | AK487: ='(1)예금승인내역'!K1117 -> 정기예금
AE488: ='(1)예금승인내역'!H1118 -> 46058 | AF488: =VALUE(AE488) -> 46058 | AG488: ='(1)예금승인내역'!G1118 -> 46027 | AH488: ='(1)예금승인내역'!F1118 -> 동화인더스트리 | AI488: ='(1)예금승인내역'!L1118 -> 3 | AJ488: ='(1)예금승인내역'!AG1118 -> 0.0352 | AK488: ='(1)예금승인내역'!K1118 -> 정기예금
AE489: ='(1)예금승인내역'!H1119 -> 46058 | AF489: =VALUE(AE489) -> 46058 | AG489: ='(1)예금승인내역'!G1119 -> 46027 | AH489: ='(1)예금승인내역'!F1119 -> 동화인더스트리 | AI489: ='(1)예금승인내역'!L1119 -> 2 | AJ489: ='(1)예금승인내역'!AG1119 -> 0.0352 | AK489: ='(1)예금승인내역'!K1119 -> 정기예금
AE490: ='(1)예금승인내역'!H1120 -> 46065 | AF490: =VALUE(AE490) -> 46065 | AG490: ='(1)예금승인내역'!G1120 -> 46034 | AH490: ='(1)예금승인내역'!F1120 -> ㈜이수스페셜티케미컬 | AI490: ='(1)예금승인내역'!L1120 -> 13.3 | AJ490: ='(1)예금승인내역'!AG1120 -> 0.032 | AK490: ='(1)예금승인내역'!K1120 -> MMDA
AE491: ='(1)예금승인내역'!H1121 -> 46065 | AF491: =VALUE(AE491) -> 46065 | AG491: ='(1)예금승인내역'!G1121 -> 46034 | AH491: ='(1)예금승인내역'!F1121 -> ㈜현대그린푸드 | AI491: ='(1)예금승인내역'!L1121 -> 2 | AJ491: ='(1)예금승인내역'!AG1121 -> 0.032 | AK491: ='(1)예금승인내역'!K1121 -> MMDA
... AE549: ='(1)예금승인내역'!H1179 -> 46146 | AF549: =VALUE(AE549) -> 46146 | AG549: ='(1)예금승인내역'!G1179 -> 46113 | AH549: ='(1)예금승인내역'!F1179 -> 국제금속 | AI549: ='(1)예금승인내역'!L1179 -> 6.54 | AJ549: ='(1)예금승인내역'!AG1179 -> 0.032 | AK549: ='(1)예금승인내역'!K1179 -> MMDA
AE550: ='(1)예금승인내역'!H1175 -> 46132 | AF550: =VALUE(AE550) -> 46132 | AG550: ='(1)예금승인내역'!G1175 -> 46101 | AH550: ='(1)예금승인내역'!F1175 -> ㈜약진통상 | AI550: ='(1)예금승인내역'!L1175 -> 14.4 | AJ550: ='(1)예금승인내역'!AG1175 -> 0.0322 | AK550: ='(1)예금승인내역'!K1175 -> MMDA
...

Sheet ★예금금리상담
A1: 예금 금리 상담 일지 (사전)
A2: 순번 | B2: 상담일자 | C2: 상담지점 | D2: 상담직원 | E2: 업체명 | F2: 예정일 | G2: 기간 | H2: 금리 | I2: 금액 | J2: 예금과목 | K2: 상담내용
A3: 1 | B3: 43886 | C3: 부산영업부 | D3: 과장 김은아 | E3: 파산관리재단 | F3: 3월 초 | G3: 3M | H3: 0.014 | I3: 1.48 | J3: 정기예금 | K3: 파산대리인 (법원 요청 후 신규되는 건이라 사전에 금리 확정 해야한다고 하여 보수적으로 금리 제시) 나중에 전화와서 1백만 미만으로 여러건 신규 예정이라고 하여 이진범과장님과 통화하였고 1백만불 미만으로 신규될 시 외사부에서 1.40%으로 승인하기로 함
A4: 2 | B4: 43886 | C4: 센텀시티지점 | D4: 대리 김진화 | E4: 현대 2차 계열사 | F4: 알 수 없음 | G4: 1M 2M 3M 6M | H4: 1.40% 1.40% 1.40% 1.45% | J4: 정기예금 | K4: 신규일자 알 수 없으므로 항상 보수적으로 제시하는 업체임
A5: 3 | B5: 43887 | C5: 성서영업부 | D5: 차장 권미정 | E5: ㈜나인플러스 | F5: 43889 | G5: 3M | H5: 1.40%~ 1.45% | I5: 1.04 | J5: 정기예금 | K5: 1.40~1.45 수준이고 2월 28일에 다시 확인 요청
A6: 4 | B6: 43887 | C6: 중동지점 | D6: 대리 김진아 | E6: ㈜동화인더스트리 | F6: 43889 | G6: 1M 3M 6M | H6: 1.40% 1.42~3% 1.45% | I6: 2건 6M | J6: 정기예금 | K6: 1.40~1.45 수준이고 2월 28일에 다시 확인 요청
A7: 5 | B7: 43888 | C7: 경산공단영업부 | D7: 계장 정재경 | E7: 구본일 (일지테크) | F7: 43889 | G7: 3M | H7: 0.014 | J7: 정기예금 | K7: 기존 갱신할 때와 비교시 LIBOR 및 고시금리 30bp정도 하락 감안하여 1.70% →1.40% 제시하였으며 2월 28일에 다시 확인 요청
A8: 6 | B8: 43893 | C8: 강남영업부 | D8: 부지점장 문명숙 | E8: 한전 | F8: 43895 | G8: 3M MMDA | H8: 1.00% 0.80% | I8: 30M 20M | J8: 정기예금 MMDA | K8: 금리인하 기대에 따른 시장금리 및 기본고시금리 하락 반영, MMDA는 80M 요청했으나 20M으로 제한.
A9: 7 | B9: 43896 | C9: 강남영업부 | D9: 부지점장 박진호 | E9: 쿠팡 | F9: 43896 | G9: 1M | H9: 0.0096 | I9: 10M | J9: 정기예금 | K9: 이탈
A10: 8 | B10: 43901 | C10: 여의도지점 | D10: 부지점장 박후임 | F10: 3월 중 | G10: 1M 2M 3M | H10: 0.55% 0.55% 0.55% | I10: 10M | J10: 정기예금
A11: 9 | B11: 43902 | C11: 서울영업부 | D11: 대리 최예령 | G11: 1M 3M | H11: 0.55% 0.55% | J11: 정기예금 | K11: 현재 가격 문의 (예정 금액이나 일자 없음)
A12: 10 | B12: 43903 | C12: 강남영업부 | D12: 부지점장 문명숙 | E12: 한전 | F12: 43906 | G12: 3M | H12: 0.005 | I12: 20M | J12: 정기예금 | K12: 30개 문의하였으나 20개로 제한 (다음주 월요일 신규 예정 건으로 0.55 -> 0.50으로 제안)
A13: 11 | B13: 43908 | C13: 센텀시티지점 | D13: 대리 김진화 | E13: 현대 2차 계열사 | F13: 알 수 없음 | G13: 1M 2M 3M 6M | H13: 0.40% 0.40% 0.65% 0.60% | I13: 3M | J13: 정기예금
A14: 12 | B14: 43909 | C14: 서울영업부 | D14: 차장 정상국 | E14: 삼호중공업 | F14: 43909 | G14: 1M 2M 3M 6M | H14: 0.65% 0.75% 0.90% 0.60% | I14: 25M | J14: 정기예금 | K14: 정기예금 1개월 0.65% 신규확정
A15: 13 | B15: 43909 | C15: 강남영업부 | D15: 부지점장 박진호 | F15: 43909 | G15: MMDA 1M | H15: 0.65% 0.00% | J15: MMDA 정기예금
A16: 14 | B16: 43913 | C16: 성서공단영업부 | D16: 차장 한지숙 | E16: 보림엘텍 | F16: 43914 | G16: 1M | H16: 0.008 | I16: 1M | J16: 정기예금 | K16: 3-23 10:35 기준 SMBC 동경 1.10%
A17: 15 | B17: 43914 | C17: 성서공단영업부 | D17: 차장 한지숙 | E17: 보림엘텍 | F17: 43914 | G17: 1M 3M | H17: 0.80% 1.10% | I17: 1M 3M | J17: 정기예금 | K17: 3-24 10:35 기준 - 1개월 SMBC 동경 1.10% , 3개월 SMBC 동경 1.40%
A18: 16 | B18: 43928 | C18: 센텀시티지점 | D18: 대리 김진화 | E18: 현대 2차 계열사 | F18: 미정 | G18: 1M 2M 3M 6M | H18: 0.50% 0.60% 0.95% 0.90% | I18: 3M | J18: 정기예금
A19: 17 | B19: 43928 | C19: 강남영업부 | D19: 부지점장 박진호 | E19: SK하이닉스 | G19: 1주 MMDA | H19: 0% 0% | I19: 50M | J19: 정기예금 MMDA | K19: 20백만불 까지 제한 안내. 최근 금리 하락으로 금리제시 불가능. 기본고시 금리도 없음.
A20: 18 | B20: 43928 | C20: 서울영업부 | D20: 대리 김예슬 | E20: 무림피앤피 | G20: 2주 1개월 | H20: 0.05% 0.50% | J20: 정기예금
A21: 19 | B21: 43938 | C21: 센텀시티지점 | D21: 대리 김진화 | E21: 현대 2차 계열사 | F21: 미정 | G21: 1M 2M 3M 6M | H21: 0.50% 0.70% 0.80% 0.74% | I21: 3MIO | J21: 정기예금
A22: 20 | B22: 43941 | C22: 강남영업부 | D22: 대리 박경희 | E22: 쿠팡 | F22: 미정 | G22: 1M | H22: 0.005 | I22: 20MM | J22: 정기예금 | K22: EUR/USD 스왑운용보다 머니마켓 USD운용 금리가 높음
A23: 21 | B23: 43942 | C23: 성서공단영업부 | D23: 차장 한지숙 | E23: 보림엘텍 | F23: 43945 | G23: 1M | H23: 0.0045 | I23: 1MM | J23: 정기예금 | K23: 4-21 10시 기준 1개월 LBBW 0.66
A24: 22 | B24: 43944 | C24: 명가타운지점 | D24: 지점장 조은주 | E24: 이재형 | F24: 2020-04-27 만기건 | G24: 12M | H24: 1.00~1.05% | I24: 3MM | J24: 정기예금 | K24: 중개사 운용가능 금리조사 1.25%기준 제시
A25: 23 | B25: 43944 | C25: 서울영업부 | D25: 차장 정상국 | F25: 미정 | G25: 1M 3M | H25: 0.40% 0.40% | I25: 10MM | J25: 정기예금 | K25: 단순 금리 조사
A26: 24 | B26: 43945 | C26: 성서공단영업부 | D26: 차장 한지숙 | E26: 보림엘텍 | F26: 43945 | G26: 1M 3M | H26: 0.40% 0.40% | I26: 1MM | J26: 정기예금 | K26: 4-24 9시25분 기준 1개월
A27: 25 | B27: 43945 | C27: 덕산지점 | D27: 대리 하경숙 | E27: 민커뮤니케이션 | F27: 43948 | G27: 1M 3M | H27: 0.40% 0.40% | I27: 1MM | J27: 정기예금 | K27: 4-24 9시25분 기준 1개월
A28: 26 | B28: 43959 | C28: 센텀시티지점 | D28: 대리 김진화 | E28: 현대 2차 계열사 | F28: 미정 | G28: 1M 2M 3M 6M | H28: 0.00% 0.15% 0.20% 0.3117% | I28: 3MIO | J28: 정기예금
A29: 27 | B29: 43966 | C29: 센텀시티지점 | D29: 대리 김진화 | E29: 현대 2차 계열사 | F29: 미정 | G29: 1M 2M 3M 6M | H29: 0.05% 0.10% 0.10% 0.2895% | I29: 3MIO | J29: 정기예금
A30: 28 | B30: 43970 | C30: 부산영업부 | D30: 과장 김은아 | E30: 파산관리재단 | F30: 43973 | G30: 05-22 ~ 07.13 | H30: 0 | I30: 3MIO | J30: 정기예금 | K30: 미국기준금리 인하에 따른 리보금리 하락으로 기본고시금리도 없으며 마니마켓 두달이내 운용금리도 없음
A31: 29 | B31: 43976 | C31: 성서공단영업부 | D31: 차장 한지숙 | E31: 보림엘텍 | F31: 43977 | G31: 1M 3M 6M | H31: 0.00% 0.10% 0.1961%기본고시 | I31: 1MIO | J31: 정기예금 | K31: 5-25 13시57분 기준
A32: 30 | B32: 43976 | C32: 센텀시티지점 | D32: 대리 김진화 | E32: 현대 2차 계열사 | F32: 미정 | G32: 1M 2M 3M 6M | H32: 0.00% 0.05% 0.10% 0.1961%기본고시 | I32: 3MIO | J32: 정기예금 | K32: 5-25 15시16분 기준
A33: 31 | B33: 43977 | C33: 성서공단영업부 | D33: 차장 한지숙 | E33: 보림엘텍 | F33: 43977 | G33: 1M 3M 6M | H33: 0.00% 0.10% 0.20% | I33: 1MIO | J33: 정기예금 | K33: 5-26 11:00 기준
A34: 32 | B34: 43977 | C34: 경산공단영업부 | D34: 계장 정재경 | E34: 구본일 (일지테크) | F34: 43979 | G34: 3M 6M | H34: 0.10% 0.20% | I34: 1MIO | J34: 정기예금 | K34: 5-26 13:10 기준
A35: 33 | B35: 43977 | C35: 중동지점 | D35: 대리 권현경 | E35: ㈜동화인더스트리 | F35: 43979 | G35: 1M 3M 6M | H35: 0.00% 0.10% 0.20% | I35: 2건 6M | J35: 정기예금 | K35: 5-26 14:00 기준
A36: 34 | B36: 43980 | C36: 중동지점 | D36: 대리 권현경 | E36: ㈜동화인더스트리 | F36: 미정 | G36: 1M 2M 3M 6M | H36: 0.05% 0.08% 0.25% 0.50% | I36: 2건 6M | J36: 정기예금 | K36: 5-29 15:15 기준
A37: 35 | B37: 43983 | C37: 센텀시티지점 | D37: 대리 김진화 | E37: 현대 2차 계열사 | F37: 미정 | G37: 1M 2M 3M 6M | H37: 0.05% 0.10% 0.10% 0.20% | I37: 3MIO | J37: 정기예금 | K37: 6-1 10:30 기준
A38: 34 | B38: 43985 | C38: 중동지점 | D38: 대리 권현경 | E38: ㈜동화인더스트리 | F38: 미정 | G38: 1M 3M 6M | H38: 0.15% 0.23% 0.55% | I38: 4MIO | J38: 정기예금 | K38: 6-3 09:30 기준 (1M-미즈호서울, 3M-SMTB HK, 6M-국민홍콩)
A39: 35 | B39: 43986 | C39: 중동지점 | D39: 대리 권현경 | E39: ㈜동화인더스트리 | F39: 미정 | G39: 1M 3M 6M | H39: 0.20% 0.25% 0.55% | I39: 4MIO | J39: 정기예금 | K39: 6-4 13:45 기준 (SMTB HK)
A40: 36 | B40: 43990 | C40: 중동지점 | D40: 대리 권현경 | E40: ㈜동화인더스트리 | F40: 미정 | G40: 1M 3M 6M | H40: 0.15% 0.26% 0.55% | I40: 4MIO | J40: 정기예금
A41: 37 | B41: 43991 | C41: 중동지점 | D41: 대리 권현경 | E41: ㈜동화인더스트리 | F41: 미정 | G41: 1M 3M 6M | H41: 0.15% 0.26% 0.20% | I41: 4MIO | J41: 정기예금
A42: 38 | B42: 43991 | C42: 본점영업부 | D42: 과장 김준동 | F42: 미정 | G42: 3M 6M | H42: 0.08% 0.55% | I42: 1MIO | J42: 정기예금 | K42: 6-9 13.45 기준 (3M-LBBW SL, 6M-국민 홍콩)
A43: 39 | B43: 43993 | C43: 중동지점 | D43: 대리 권현경 | E43: ㈜동화인더스트리 | F43: 미정 | G43: 1M 3M 6M | H43: 0.15% 0.26% 0.58% | I43: 4MIO | J43: 정기예금 | K43: 6-11 10:05 기준 (1m,3m-SMTB HK , 6M-국민 홍콩)
A44: 40 | B44: 43993 | C44: 포항공단지점 | D44: 계장 김현진 | F44: 미정 | G44: 3M | H44: 0.0026 | I44: 1MIO | J44: 정기예금 | K44: 6-11 10:05 기준 (3m-SMTB HK)
A45: 41 | B45: 43997 | C45: 중동지점 | D45: 대리 권현경 | E45: ㈜동화인더스트리 | F45: 미정 | G45: 1M 3M 6M | H45: 0.10% 0.09% 0.58% | I45: 4MIO | J45: 정기예금 | K45: 6-15 15:30 기준 (1m-시즈오카,3m-LBBW , 6M-국민 홍콩)
A46: 42 | B46: 43997 | C46: 센텀시티지점 | D46: 대리 김진화 | E46: 현대 2차 계열사 | F46: 미정 | G46: 1M 2M 3M 6M | H46: 0.00% 0.09% 0.09% 0.20% | I46: 3MIO | J46: 정기예금 | K46: 6-15 15:00 기준 (2M-산업싱가폴, 3m-LBBW , 6M-SMBC)
A47: 43 | B47: 43998 | C47: 달성공단영업부 | D47: 계장 박동진 계장 박계령 | G47: 3M | H47: 0.002 | I47: 2.5MIO | K47: 6-16 17:55 기준 (3M-산업싱가폴 0.4)
A48: 44 | B48: 44011 | C48: 센텀시티지점 | D48: 대리 김진화 | E48: 현대 2차 계열사 | F48: 미정 | G48: 1M 2M 3M 6M | H48: 0.00% 0.00% 0.05% 0.15% | I48: 3MIO | J48: 정기예금 | K48: 6-29 09:30 기준 (SMBC 동경)
A49: 45 | B49: 44019 | C49: 본점영업부 | D49: 과장 김준동 | F49: 미정 | G49: 3M 6M | H49: 0.05% 0.15% | I49: 4MIO | J49: 정기예금 | K49: 7-7 13:05 기준 (SMBC)
A50: 46 | B50: 44020 | C50: 중동지점 | D50: 대리 권현경 | E50: ㈜동화인더스트리 | F50: 44025 | G50: 1M 3M 6M | H50: 0.05% 0.05% 0.15% | I50: 4MIO | J50: 정기예금 | K50: 7-8 09:30 기준 (1m-SMTB HK, 3m-SMBC , 6M-SMBC)
A51: 47 | B51: 44020 | C51: 달성공단영업부 | D51: 계장 박계령 | E51: ㈜동아홀딩스 | F51: 44020 | G51: 1M 3M | H51: 0.05% 0.05% | I51: 2MIO | K51: 7-8 09:30 기준 (1m-SMTB HK, 3m-SMBC)
A52: 48 | B52: 44022 | C52: 중동지점 | D52: 대리 권현경 | E52: ㈜동화인더스트리 | F52: 44025 | G52: 1M 3M 6M | H52: 0.05% 0.05% 0.10% | I52: 4MIO | J52: 정기예금 | K52: 7-10 09:30 기준 (1m-SMTB HK, 3m-SMBC , 6M-SMBC)
A53: 49 | B53: 44025 | C53: 중동지점 | D53: 대리 김진아 | E53: ㈜동화인더스트리 | F53: 44025 | G53: 1M 3M 6M | H53: 0.05% 0.10% 0.10% | I53: 4MIO | J53: 정기예금 | K53: 7-13 09:25 기준 (1m-SMTB HK, 3m-SMTB HK , 6M-SMBC TK)
A54: 50 | B54: 44026 | C54: 서울영업부 | D54: 차장 정상국 | E54: 현대미포조선 | F54: 44028 | G54: 1M 2M 3M 6M | H54: 0.08% 0.00% 0.05% 0.28% | I54: 10MIO | J54: 정기예금 | K54: 7-14 14:25 기준 (1m-SMTB HK, 3m-SMBC TK, 6M-산업 싱가폴)
A55: 51 | B55: 44027 | C55: 센텀시티지점 | D55: 대리 김진화 | E55: 현대 2차 계열사 | F55: 미정 | G55: 1M 2M 3M 6M | H55: 0.00% 0.00% 0.10% 0.10% | I55: 3MIO | J55: 정기예금 | K55: 7-15 10:45 기준 (3m-시즈오카 동경, 6M-SMBC 동경)
A56: 52 | B56: 44027 | C56: 서대구지점 | D56: 계장 이초롱 | F56: 44027 | G56: 1M 2M 3M 6M | H56: 0.00% 0.00% 0.10% 0.10% | I56: 2MIO | J56: 정기예금 | K56: 7-15 10:45 기준 (3m-시즈오카 동경, 6M-SMBC 동경)
A57: 53 | B57: 44032 | C57: 센텀시티지점 | D57: 대리 김진화 | E57: 현대 2차 계열사 | F57: 미정 | G57: 1M 2M 3M 6M | H57: 0.04% 0.05% 0.10% 0.10% | I57: 3MIO | J57: 정기예금 | K57: 7-20 12:15 기준 (1m-smtb hk ,2m- smtb hk, 3m-시즈오카 동경, 6M-SMBC 동경)
A58: 54 | B58: 44033 | C58: 강남영업부 | D58: 부지점장 박진호 | F58: 미정 | G58: 3M | H58: 0.001 | I58: 1~2MIO | J58: 정기예금 | K58: 7-21 14:30 기준 (3m-시즈오카 동경)
A59: 55 | B59: 44034 | C59: 성서비지니스센터 | D59: 계장 백승엽 | F59: 44034 | G59: 3M | H59: 0.001 | I59: 1MIO | J59: 정기예금 | K59: 7-22 11:00 기준 (3m-시즈오카 동경)
A60: 56 | B60: 44039 | C60: 센텀시티지점 | D60: 대리 김진화 | E60: 현대 2차 계열사 | F60: 미정 | G60: 1M 2M 3M 6M | H60: 0.00% 0.00% 0.10% 0.10% | I60: 3MIO | J60: 정기예금 | K60: 7-20 12:15 기준 (3m-시즈오카 동경, 6M-SMBC 동경)
A61: 57 | B61: 44046 | C61: 센텀시티지점 | D61: 대리 김진화 | E61: 현대 2차 계열사 | F61: 미정 | G61: 1M 2M 3M 6M | H61: 0.00% 0.08% 0.08% 0.10% | I61: 3MIO | J61: 정기예금 | K61: 8-3 13:10 기준
A62: 58 | B62: 44055 | C62: 중동지점 | D62: 대리 권현경 | E62: 동아인더스트리 | F62: 44056 | G62: 1M 3M 6M | H62: 0.00% 0.08% 0.08% | I62: 4MIO | J62: 정기예금 | K62: 8-13 09:30 기준
A63: 59 | B63: 44062 | C63: 센텀시티지점 | D63: 대리 김진화 | E63: 현대 2차 계열사 | F63: 미정 | G63: 1M 2M 3M 6M | H63: 0.00% 0.08% 0.08% 0.08% | I63: 3MIO | J63: 정기예금 | K63: 7-20 12:15 기준 (3m-시즈오카 동경, 6M-SMBC 동경)
A64: 60 | B64: 44068 | C64: 성서공단영업부 | D64: 차장 한지숙 | E64: 보림엘텍 | F64: 44069 | G64: 1M 2M 3M | H64: 0.02% 0.12% 0.08% | I64: 1MIO | J64: 정기예금 | K64: 8-25 11:30 기준 (1m-SMTB HK, 2M-SMTB HK, 3M-시즈오카 동경)
A65: 61 | B65: 44090 | C65: 센텀시티지점 | D65: 대리 김진화 | E65: 현대 2차 계열사 | F65: 미정 | G65: 1M 2M 3M 6M | H65: 0.08% 0.12% 0.10% 0.05% | I65: 3MIO | J65: 정기예금 | K65: 9-16 10:50 기준 (1m-SMTB HK, 2M- SMTB HK, 3m-미즈호 서울, 6M-SMBC 동경)
A66: 62 | B66: 44099 | C66: 센텀시티지점 | D66: 대리 김진화 | E66: 현대 2차 계열사 | F66: 미정 | G66: 1M 2M 3M 6M | H66: 0.00% 0.01% 0.10% 0.03% | I66: 3MIO | J66: 정기예금 | K66: 9-25 16:30 기준 (2M- 시즈오카 동경, 3m-미즈호 서울, 6M-SMBC 동경)
A67: 63 | B67: 44110 | C67: 서대구지점 | D67: 계장 이초롱 | F67: 미정 | G67: 1M 2M 3M 6M | H67: 0.05% 0.06% 0.14% 0.02% | I67: 2MIO | J67: 정기예금 | K67: 10-06 12:50기준 (1m- smtb hk, 2m- smtb hk, 3m-smtb hk, 6M-SMBC 동경)
A68: 64 | B68: 44111 | C68: 달성공단영업부 | D68: 계장 박계령 | E68: ㈜동아홀딩스 | F68: 44112 | G68: 3M | H68: 0.0005 | I68: 2MIO | K68: 10-07 10:30 기준 (3m-미즈호 서울)
A69: 65 | B69: 44112 | C69: 달성공단영업부 | D69: 계장 박계령 | E69: ㈜동아홀딩스 | F69: 44112 | G69: 3M | H69: 0.001 | I69: 2MIO | K69: 10-08 14:00 기준 (3m-미즈호 서울)
A70: 66 | B70: 44120 | C70: 센텀시티지점 | D70: 대리 김진화 | E70: 현대 2차 계열사 | F70: 미정 | G70: 1M 2M 3M 6M | H70: 0.01% 0.03% 0.15% 0.13% | I70: 3MIO | J70: 정기예금 | K70: 10-16 09:30 기준 (1m-SMTB HK, 2M- SMTB HK, 3m-SMTB HK, 6M-미즈호서울)
A71: 67 | B71: 44126 | C71: 성서비지니스센터 | D71: 대리 이세웅 | E71: 코닉스 | F71: 44126 | G71: 3M | H71: 0.0013 | I71: 1MIO | J71: 정기예금 | K71: 10-22 10:20 기준 (3m-smtbhk)
A72: 68 | B72: 44127 | C72: 센텀시티지점 | D72: 대리 김진화 | E72: 현대 2차 계열사 | F72: 미정 | G72: 1M 2M 3M 6M | H72: 0.00% 0.00% 0.12% 0.20% | I72: 3MIO | J72: 정기예금 | K72: 10-23 10:25 기준 (3m-SMTB HK, 6M-산업홍콩법인)
A73: 69 | B73: 44140 | C73: 달성공단영업부 | D73: 계장 박계령 | G73: 1M 2M 3M 6M 12M | H73: 0.00% 0.14% 0.10% 0.20% - | I73: 3MIO | K73: 11-05 15:30 기준 (2M- SMTB HK, 3m-SMTB HK, 6M-산업홍콩)
A74: 70 | B74: 44145 | C74: 센텀시티지점 | D74: 대리 김진화 | E74: 현대 2차 계열사 | F74: 미정 | G74: 1M 2M 3M 6M | H74: 0.00% 0.05% 0.10% 0.01% | I74: 3MIO | J74: 정기예금 | K74: 11-10 13:40 기준 (2m - 레조나 동경, 3m-SMTB HK, 6M-smbc)
A75: 71 | B75: 44165 | C75: 센텀시티지점 | D75: 대리 김진화 | E75: 현대 2차 계열사 | F75: 미정 | G75: 1M 2M 3M 6M | H75: 0.10% 0.07% 0.07% 0.01% | I75: 3MIO | J75: 정기예금 | K75: 11-30 14:00 기준 (1m - 시즈오카동경 & smtbhk, 2m - 시즈오카 동경, 3m - 시즈오카 동경 , 6M - smbc)
A76: 72 | B76: 44181 | C76: 센텀시티지점 | D76: 대리 김진화 | E76: 현대 2차 계열사 | F76: 미정 | G76: 2M 3M 6M | H76: 0.10% 0.05% 0.00% | I76: 3MIO | J76: 정기예금 | K76: 12-16 13:30 기준 (2m - 시즈오카 동경, 3m - 시즈오카 동경)
A77: 73 | B77: 44182 | C77: 달성공단영업부 | D77: 계장 박계령 | F77: 44182 | G77: 3M | H77: 0.0005 | I77: 2.5MIO | J77: 정기예금 | K77: 12-17 16:20 기준 (3m-시즈오카동경 0.25)
A78: 74 | B78: 44183 | C78: 중산지점 | D78: 부지점장 오창용 | F78: 44186 | G78: 1M 2M 3M 6M | H78: 0.15% 0.10% 0.05% 0.01% | J78: 정기예금 | K78: 12-18 09:30 기준 (1m - 시즈오카동경 0.40, 2m - 시즈오카 동경 0.35, 3m - 시즈오카 동경 0.25 , 6M - smbc 0.21)
A79: 75 | B79: 44188 | C79: 성서3단지영업부 | D79: 계장 김재욱 | G79: 1M 2M 3M 6M | H79: 0.10% 0.10% 0.05% 0.00% | I79: 3MIO | J79: 정기예금 | K79: 12-23 17:00 기준 (1m - 시즈오카동경 0.35, 2m - 시즈오카 동경 0.30, 3m - 시즈오카 동경 0.25) 1년 문의하였으나 6개월뒤 리셋설명 + 6개월 우대금리 없음을 설명함
A80: 76 | B80: 44189 | C80: 성서3단지영업부 | D80: 부지점장 최익록 | G80: 1M 2M 3M 6M | H80: 0.10% 0.10% 0.05% 0.00% | I80: 3MIO | J80: 정기예금 | K80: 12-24 09:30 기준 (1m - 시즈오카동경 0.35, 2m - 시즈오카 동경 0.30, 3m - 시즈오카 동경 0.25) 1년 문의하였으나 6개월뒤 리셋설명 + 6개월 우대금리 없음을 설명함
A81: 77 | B81: 44189 | C81: 센텀시티지점 | D81: 대리 김진화 | E81: 현대 2차 계열사 | F81: 미정 | G81: 2M 3M 6M | H81: 0.10% 0.05% 0.01% | I81: 3MIO | J81: 정기예금 | K81: 12-24 15:00 기준 (2m - 시즈오카 동경, 3m - 시즈오카 동경, 6m - smbc 동경)
A82: 78 | B82: 44204 | C82: 달성공단영업부 | D82: 계장 박계령 | F82: 44204 | G82: 3M | H82: 0.0005 | I82: 2.5MIO | J82: 정기예금 | K82: 01-08 15:00 기준 (3m-시즈오카동경 0.25)
A83: 79 | B83: 44221 | C83: 성서비지니스센터 | D83: 대리 이세웅 | E83: 코닉스 | F83: 44221 | G83: 3M | H83: 0.0008 | I83: 1MIO | J83: 정기예금 | K83: 1-25 09:30 기준 (3m-시즈오카 동경 0.28)
A84: 80 | B84: 44229 | C84: 강남영업부 | D84: 부지점장 박효정 | F84: 미정 | G84: MMDA 1M 2M 3M | H84: 0.00% 0.00% 0.05% 0.06% | I84: 5MIO | K84: 2-2 16:30 2m - 시즈오카 동경 0.25 , 3m - 시즈오카 동경 0.26)
A85: 81 | B85: 44236 | C85: 강남영업부 | D85: 금융지점장 문명숙 | F85: 미정 | G85: 3M 6M 12M | H85: 0.05% 0.00% 0.00% | K85: 2-9 10:30 3m - 시즈오카 동경 0.25 6개월 12개월 운용가능 금리 없음. 12개월 정기예금은 6개월 뒤 리셋관련 내용 설명드림.
A86: 82 | B86: 44246 | C86: 강남영업부 | D86: 부지점장 박효정 | F86: 미정 | G86: 1M 2M 3M | H86: 0.00% 0.05% 0.05% | I86: 5MIO | K86: 2-19 09:30 2m - 시즈오카 동경 0.25 , 3m - 시즈오카 동경 0.25)
A87: 83 | B87: 44260 | C87: 중동지점 | D87: 대리 김진아 | E87: ㈜동화인더스트리 | F87: 미정 | G87: 1M 2M 3M 6M | H87: 0.00% 0.05% 0.06% 0.00% | I87: 2MIO | J87: 정기예금 | K87: 3-5 14:00기준 (2m-시즈오카 동경 0.26, 3m-시즈오카 동경 0.26)
A88: 84 | B88: 44265 | C88: 중동지점 | D88: 대리 권현경 | E88: ㈜동화인더스트리 | F88: 미정 | G88: 1M 3M 6M | H88: 0.05% 0.05% 0.00% | I88: 2MIO | J88: 정기예금 | K88: 3-10 14:00기준 (1m-시즈오카 동경 0.25, 3m-lbbw 0.25)
A89: 85 | B89: 44284 | C89: 달성공단영업부 | D89: 차장 곽동욱 | E89: 인터불고 | F89: 미정 | G89: 3M | H89: 0.0005 | I89: 1MIO | J89: 정기예금 | K89: 03-29 14:30 기준 (3m-미즈호 홍콩 0.25)
A90: 86 | B90: 44287 | C90: 중동지점 | D90: 대리 권현경 | F90: 미정 | G90: 1M 3M 6M | H90: 0.00% 0.07% 0.00% | J90: 정기예금 | K90: 4-1 13:00기준 (3m-미즈호 서울 0.27)
A91: 87 | B91: 44294 | C91: 달성공단영업부 | D91: 계장 박계령 | F91: 44294 | G91: 3M | H91: 0.0005 | I91: 2MIO | J91: 정기예금 | K91: 4-8 17:00 기준 (3m-보콤서울 & 광주은행 0.28)
A92: 88 | B92: 44343 | C92: 파동지점 | D92: 부지점장 마경진 | G92: 1M 3M 6M 12M | H92: 0.00% 0.03% 0.05% 0.00% | I92: 5~10 | K92: 콜론운용금리 없으나 eur/usd swap 재원 활용으로 3개월 6개월 금리 제시
A93: 89 | B93: 44364 | C93: 달성공단영업부 | D93: 차장 이선영 | E93: 인터불고 | F93: 44364 | G93: 3M | H93: 0.0003 | I93: 2.5MIO | J93: 정기예금 | K93: 콜론운용금리 없으나 eur/usd swap 재원 활용으로 3개월 금리 제시
A94: 90 | B94: 44383 | C94: 여의도지점 | D94: 부지점장 박후임 | F94: 미정 | G94: 3M | H94: 0.0003 | I94: 4MIO | J94: 정기예금 | K94: 콜론운용금리 없으나 eur/usd swap 재원 활용으로 3개월 금리 제시 & 타행평균금리(0.0339) 반영
A95: 91 | B95: 44399 | C95: 성서비지니스센터 | D95: 대리 이세웅 | E95: 코닉스 | F95: 44403 | G95: 3M | H95: 0.0003 | I95: 1MIO | J95: 정기예금 | K95: 콜론운용금리 없으나 eur/usd swap 재원 활용가능 1개월 금리 제시 & 타행평균금리(0.03313) 반영
A96: 92 | B96: 44445 | C96: 중동지점 | D96: 대리 박준형 | E96: ㈜동화인더스트리 | F96: 미정 | G96: 3M | H96: 0.0003 | I96: 2MIO | J96: 정기예금 | K96: 소액 매칭 없음 (콜론운용금리 없으나 eur/usd swap 재원 활용가능 1~3개월 운용금리 & 타행평균금리(0.03183) 반영)
A97: 93 | B97: 44494 | C97: 성서비지니스센터 | D97: 대리 이세웅 | E97: 코닉스 | F97: 44495 | G97: 3M | H97: 0.0003 | I97: 1MIO | J97: 정기예금 | K97: 콜론운용금리 없으나 eur/usd swap 재원 활용으로 3개월 금리 제시 & 타행평균금리(0.03014) 반영
A98: 94 | B98: 44586 | C98: 성서비지니스센터 | D98: 대리 이세웅 | E98: 코닉스 | F98: 44587 | G98: 3M | H98: 0.001 | I98: 1MIO | J98: 정기예금 | K98: 1-25 15:00 기준 (3m - 0.30 시즈오카 동경)
A99: 95 | B99: 44614 | C99: 양산지점 | D99: 지점장 박명환 | F99: 2022-3월 중 | G99: 1M 2M 3M 6M 9M 12M | H99: 0.00% 0.20% 0.30% 0.50% 0.65% 0.85% | I99: 5MIO | K99: 02-22 09:15 기준 (2M-시즈오카 0.40, 3m-시즈오카 0.50, 6M-시즈오카 0.85, 9M-SMTB HK 1.00, 12M-시즈오카 1.15)
A100: 96 | B100: 44636 | C100: 달성공단영업부 | D100: 차장 이선영 | E100: 인터불고 | F100: 44637 | G100: 3M | H100: 0.005 | I100: 2.5MIO | J100: 정기예금 | K100: 3-16 11:00 기준 (3m - 0.72 LBBW SL)
...

Sheet 결재용
C4: 외화예금 우대금리 승인명세
C5: 45931
P6: 담당 | Q6: 부장
A8: 번호 | B8: 신규/연장 | C8: 상품 | D8: 지점명 | E8: 고객명 | F8: 통화 | G8: 금액 | H8: 시작일자 | I8: 만기일자 | J8: 월수 | K8: 일수 | L8: 종합수익관리시스템 | O8: 고시금리 | P8: 우대금리 | Q8: 적용금리
L9: 내부금리 | M9: 지준비용률 | N9: 자금마진율
A11: 1 | B11: 연장 | C11: =K24 -> 정기예금 | D11: =C24 -> 중동지점 | E11: =F24 -> 동화인더스트리 | F11: USD | G11: =L24*1000000 -> 2000000 | H11: =G24 -> 46085 | I11: =H24 -> 46118 | J11: =J24 -> 1 | K11: =I11-H11 -> 33 | L11: =V24 -> 0.039655 | M11: =W24 -> 0.000793 | N11: =X24 -> 0.002586 | O11: =AE24 -> 0.030277 | P11: =AF24 -> 0.004223 | Q11: =AG24 -> 0.0345
A13: 2 | B13: 연장 | C13: =K26 -> 정기예금 | D13: =C26 -> 경산공단영업부 | E13: =F26 -> ㈜일지테크 | F13: USD | G13: =L26*1000000 -> 2000000 | H13: =G26 -> 45940 | I13: =H26 -> 45947 | J13: =J26 -> 0 | K13: =I13-H13 -> 7 | L13: =V26 -> 0.043565 | M13: =W26 -> 0.00305 | N13: =X26 -> 0.003739 | O13: =AE26 -> 0.031876 | P13: =AF26 -> 0.003124 | Q13: =AG26 -> 0.035
A15: 3 | B15: 연장 | C15: =K28 -> 정기예금 | D15: =C28 -> 경산공단영업부 | E15: =F28 -> ㈜일지테크 | F15: USD | G15: =L28*1000000 -> 2000000 | H15: =G28 -> 45940 | I15: =H28 -> 45947 | J15: =J28 -> 0 | K15: =I15-H15 -> 7 | L15: =V28 -> 0.043565 | M15: =W28 -> 0.00305 | N15: =X28 -> 0.003739 | O15: =AE28 -> 0.031876 | P15: =AF28 -> 0.003124 | Q15: =AG28 -> 0.035
A17: 4 | B17: 연장 | C17: =K30 -> MMDA | D17: =C30 -> 성남영업부 | E17: =F30 -> ㈜이수스페셜티케미컬 | F17: USD | G17: =L30*1000000 -> 3170000 | H17: =G30 -> 45940 | I17: =H30 -> 45971 | J17: =J30 -> 1 | K17: =I17-H17 -> 31 | L17: =V30 -> 0.044165 | M17: =W30 -> 0.003092 | N17: =X30 -> 0.004297 | O17: =AE30 -> 0.029876 | P17: =AF30 -> 0.005124 | Q17: =AG30 -> 0.035
A19: 5 | B19: 연장 | C19: =K32 -> 0 | D19: =C32 -> 0 | E19: =F32 -> 0 | F19: USD | G19: =L32*1000000 -> 0 | H19: =G32 -> 0 | I19: =H32 -> 0 | J19: =J32 -> 0 | K19: =I19-H19 -> 0 | L19: =V32 -> 0 | M19: =W32 -> 0 | N19: =X32 -> 0 | O19: =AE32 -> 0 | P19: =AF32 -> 0 | Q19: =AG32 -> 0
A21: 6 | B21: 연장 | C21: =K34 -> 0 | D21: =C34 -> 0 | E21: =F34 -> 0 | F21: USD | G21: =L34*1000000 -> 0 | H21: =G34 -> 0 | I21: =H34 -> 0 | J21: =J34 -> 0 | K21: =I21-H21 -> 0 | L21: =V34 -> 0 | M21: =W34 -> 0 | N21: =X34 -> 0 | O21: =AE34 -> 0 | P21: =AF34 -> 0 | Q21: =AG34 -> 0
A23: ↓ | B23: 값붙여넣기
A24: 632 | B24: 46085 | C24: 중동지점 | D24: 지점장 최재호 | E24: 대리 정준우 | F24: 동화인더스트리 | G24: 46085 | H24: 46118 | I24: 33 | J24: 1 | K24: 정기예금 | L24: 2 | O24: 1M | P24: 0.0367115 | R24: m | V24: 0.039655 | W24: 0.000793 | X24: 0.002586 | Y24: 0.030277 | Z24: 0.00172 | AA24: 0.002 | AB24: -0.00172 | AC24: -0.00372 | AD24: 0.0345 | AE24: 0.030277 | AF24: 0.004223 | AG24: 0.0345 | AH24: 46085 | AI24: 1 | AJ24: Y | AK24: 1m 3.75%
A25: 633 | B25: 46085 | C25: 죽전지점 | D25: 지점장 서민석 | E25: 과장 안영은 | F25: 거림테크주식회사 | G25: 46085 | H25: 46177 | I25: 92 | J25: 3 | K25: 정기예금 | L25: 2 | O25: 3M | P25: 0.0366804 | R25: m | V25: 0.041067 | W25: 0.000821 | X25: 0.00247 | Y25: 0.030946 | Z25: 0.00172 | AA25: 0.002 | AB25: -0.00172 | AC25: -0.00372 | AD25: 0.036 | AE25: 0.030946 | AF25: 0.005054 | AG25: 0.036 | AH25: 46085 | AI25: 2 | AJ25: Y | AK25: 3M 3.85%
A26: 468 | B26: 45940 | C26: 경산공단영업부 | D26: 지점장 박대연 | E26: 과장 최정식 | F26: ㈜일지테크 | G26: 45940 | H26: 45947 | I26: 7 | J26: 0 | K26: 정기예금 | L26: 2 | O26: 1W | P26: 0.0410504 | R26: m | V26: 0.043565 | W26: 0.00305 | X26: 0.003739 | Y26: 0.031876 | Z26: 0.00172 | AA26: 0.002 | AB26: -0.00172 | AC26: -0.00372 | AD26: 0.035 | AE26: 0.031876 | AF26: 0.003124 | AG26: 0.035 | AH26: 45940 | AI26: 3 | AJ26: Y | AK26: mmda 4.08
A27: 469 | B27: 45940 | C27: 경산공단영업부 | D27: 지점장 박대연 | E27: 과장 최정식 | F27: ㈜일지테크 | G27: 45940 | H27: 45947 | I27: 7 | J27: 0 | K27: 정기예금 | L27: 2 | O27: 1W | P27: 0.0410504 | R27: m | V27: 0.043565 | W27: 0.00305 | X27: 0.003739 | Y27: 0.031876 | Z27: 0.00172 | AA27: 0.002 | AB27: -0.00172 | AC27: -0.00372 | AD27: 0.035 | AE27: 0.031876 | AF27: 0.003124 | AG27: 0.035 | AH27: 45940 | AI27: 4 | AJ27: Y | AK27: mmda 4.08
A28: 470 | B28: 45940 | C28: 경산공단영업부 | D28: 지점장 박대연 | E28: 과장 최정식 | F28: ㈜일지테크 | G28: 45940 | H28: 45947 | I28: 7 | J28: 0 | K28: 정기예금 | L28: 2 | O28: 1W | P28: 0.0410504 | R28: m | V28: 0.043565 | W28: 0.00305 | X28: 0.003739 | Y28: 0.031876 | Z28: 0.00172 | AA28: 0.002 | AB28: -0.00172 | AC28: -0.00372 | AD28: 0.035 | AE28: 0.031876 | AF28: 0.003124 | AG28: 0.035 | AH28: 45940 | AI28: 5 | AJ28: Y | AK28: mmda 4.08
A29: 471 | B29: 45940 | C29: 성남영업부 | D29: 기업지점장 차찬호 | E29: 과장 장윤영 | F29: ㈜현대그린푸드 | G29: 45940 | H29: 45971 | I29: 31 | J29: 1 | K29: MMDA | L29: 2 | O29: 1M | P29: 0.0404771 | R29: m | V29: 0.044165 | W29: 0.003092 | X29: 0.004297 | Y29: 0.029876 | Z29: 0.00172 | AA29: 0.002 | AB29: -0.00172 | AC29: -0.00372 | AD29: 0.035 | AE29: 0.029876 | AF29: 0.005124 | AG29: 0.035 | AH29: 45940 | AI29: 6 | AJ29: Y | AK29: mmda 4.08
A30: 472 | B30: 45940 | C30: 성남영업부 | D30: 기업지점장 차찬호 | E30: 대리 김다예 | F30: ㈜이수스페셜티케미컬 | G30: 45940 | H30: 45971 | I30: 31 | J30: 1 | K30: MMDA | L30: 3.17 | O30: 1M | P30: 0.0404771 | R30: m | V30: 0.044165 | W30: 0.003092 | X30: 0.004297 | Y30: 0.029876 | Z30: 0.00172 | AA30: 0.002 | AB30: -0.00172 | AC30: -0.00372 | AD30: 0.035 | AE30: 0.029876 | AF30: 0.005124 | AG30: 0.035 | AH30: 45940 | AI30: 7 | AJ30: Y | AK30: mmda 4.08

Sheet FXSWAP계산기
B2: 입력란 | J2: 거래 내역 | P2: 통화등록란
B3: =IF($C$6="Buy/Sell",1,2) -> 2 | C3: =VLOOKUP($C$7,$R$7:$AA$43,2,FALSE) -> E | F3: =C3&B3 -> E2 | P3: Near
R4: 1 | S4: 2 | T4: 3 | U4: 4 | V4: 5 | W4: 6 | X4: 7 | Y4: 8 | Z4: 9 | AA4: 10
T5: =IF(AND($C$3="A",$B$3=1),1,-1) -> -1 | U5: =IF(AND($C$3="A",$B$3=1),-1,1) -> 1 | V5: =IF(AND($C$3="A",$B$3=1),-1,1) -> 1 | W5: =IF(AND($C$3="A",$B$3=1),1,-1) -> -1
B6: 거래방향 | C6: Sell/Buy | J6: =M7&"/"&M10 -> USD/KRW | P6: 표시법 | Q6: 가격표시 | R6: 통화 | S6: 구분 | T6: Near Cur1 | U6: Near Cur2 | V6: Far Cur1 | W6: Far Cur2
B7: 거래통화 | C7: KRW | J7: Near Leg | K7: 1 | L7: =IF($L$8>0,"B",IF($L$8<0,"S","")) -> B | M7: =IF($C$3="A",$C$7,"USD") -> USD | P7: European | R7: KRW | S7: =LEFT(P7,1) -> E | T7: =IFERROR(IF(AND(R7=$C$7,S7="A"),$C$9,IF(AND(R7=$C$7,S7="E"),$C$9*$C$12,""))*$T$5,"") -> -1380000000 | U7: =IFERROR(IF(AND(R7=$C$7,S7="A"),$C$9*$C$12,IF(AND(R7=$C$7,S7="E"),$C$9,""))*$U$5,"") -> 1000000 | V7: =IFERROR(IF(AND(R7=$C$7,S7="A"),$C$9,IF(AND(R7=$C$7,S7="E"),$C$9*$C$14,""))*$V$5,"") -> 1380279000 | W7: =IFERROR(IF(AND(R7=$C$7,S7="A"),$C$9*$C$14,IF(AND(R7=$C$7,S7="E"),$C$9,""))*$W$5,"") -> -1000000
F8: USD | G8: =C7 -> KRW | L8: =IF($C$7="KRW",VLOOKUP($C$7,$R$7:$AA$43,4,FALSE),VLOOKUP($C$7,$R$7:$AA$43,3,FALSE)) -> 1000000 | P8: American | R8: EUR | S8: =LEFT(P8,1) -> A | T8: =IFERROR(IF(AND(R8=$C$7,S8="A"),$C$9,IF(AND(R8=$C$7,S8="E"),$C$9/$C$12,""))*$T$5,"") | U8: =IFERROR(IF(AND(R8=$C$7,S8="A"),$C$9*$C$12,IF(AND(R8=$C$7,S8="E"),$C$9,""))*$U$5,"") | V8: =IFERROR(IF(AND(R8=$C$7,S8="A"),$C$9,IF(AND(R8=$C$7,S8="E"),$C$9/$C$14,""))*$V$5,"") | W8: =IFERROR(IF(AND(R8=$C$7,S8="A"),$C$9*$C$14,IF(AND(R8=$C$7,S8="E"),$C$9,""))*$W$5,"")
B9: =IF($C$7="KRW","USD",C7) -> USD | C9: 1000000 | F9: =IF($C$3="A",L11,L8) -> 1000000 | G9: =IF($C$3="A",L8,L11) -> -1380000000 | K9: Rate | L9: =$C$12 -> 1380 | P9: European | R9: JPY | S9: =LEFT(P9,1) -> E | T9: =IFERROR(IF(AND(R9=$C$7,S9="A"),$C$9,IF(AND(R9=$C$7,S9="E"),$C$9/$C$12,""))*$T$5,"") | U9: =IFERROR(IF(AND(R9=$C$7,S9="A"),$C$9*$C$12,IF(AND(R9=$C$7,S9="E"),$C$9,""))*$U$5,"") | V9: =IFERROR(IF(AND(R9=$C$7,S9="A"),$C$9,IF(AND(R9=$C$7,S9="E"),$C$9/$C$14,""))*$V$5,"") | W9: =IFERROR(IF(AND(R9=$C$7,S9="A"),$C$9*$C$14,IF(AND(R9=$C$7,S9="E"),$C$9,""))*$W$5,"")
B10: Near Date | C10: 45491 | K10: 2 | L10: =IF($L$11>0,"B",IF($L$11<0,"S","")) -> S | M10: =IF($C$3="E",$C$7,"USD") -> KRW | P10: American | R10: AUD | S10: =LEFT(P10,1) -> A | T10: =IFERROR(IF(AND(R10=$C$7,S10="A"),$C$9,IF(AND(R10=$C$7,S10="E"),$C$9/$C$12,""))*$T$5,"") | U10: =IFERROR(IF(AND(R10=$C$7,S10="A"),$C$9*$C$12,IF(AND(R10=$C$7,S10="E"),$C$9,""))*$U$5,"") | V10: =IFERROR(IF(AND(R10=$C$7,S10="A"),$C$9,IF(AND(R10=$C$7,S10="E"),$C$9/$C$14,""))*$V$5,"") | W10: =IFERROR(IF(AND(R10=$C$7,S10="A"),$C$9*$C$14,IF(AND(R10=$C$7,S10="E"),$C$9,""))*$W$5,"")
B11: Far Date | C11: 45856 | L11: =IF($C$7="KRW",VLOOKUP($C$7,$R$7:$AA$43,3,FALSE),VLOOKUP($C$7,$R$7:$AA$43,4,FALSE)) -> -1380000000 | P11: European | R11: CHF | S11: =LEFT(P11,1) -> E | T11: =IFERROR(IF(AND(R11=$C$7,S11="A"),$C$9,IF(AND(R11=$C$7,S11="E"),$C$9/$C$12,""))*$T$5,"") | U11: =IFERROR(IF(AND(R11=$C$7,S11="A"),$C$9*$C$12,IF(AND(R11=$C$7,S11="E"),$C$9,""))*$U$5,"") | V11: =IFERROR(IF(AND(R11=$C$7,S11="A"),$C$9,IF(AND(R11=$C$7,S11="E"),$C$9/$C$14,""))*$V$5,"") | W11: =IFERROR(IF(AND(R11=$C$7,S11="A"),$C$9*$C$14,IF(AND(R11=$C$7,S11="E"),$C$9,""))*$W$5,"")
B12: Near Leg Rate | C12: 1380 | J12: Far Leg | K12: 1 | L12: =IF($L$13>0,"B",IF($L$13<0,"S","")) -> S | M12: =M7 -> USD | P12: European | R12: DKK | S12: =LEFT(P12,1) -> E | T12: =IFERROR(IF(AND(R12=$C$7,S12="A"),$C$9,IF(AND(R12=$C$7,S12="E"),$C$9/$C$12,""))*$T$5,"") | U12: =IFERROR(IF(AND(R12=$C$7,S12="A"),$C$9*$C$12,IF(AND(R12=$C$7,S12="E"),$C$9,""))*$U$5,"") | V12: =IFERROR(IF(AND(R12=$C$7,S12="A"),$C$9,IF(AND(R12=$C$7,S12="E"),$C$9/$C$14,""))*$V$5,"") | W12: =IFERROR(IF(AND(R12=$C$7,S12="A"),$C$9*$C$14,IF(AND(R12=$C$7,S12="E"),$C$9,""))*$W$5,"")
B13: Swap Point | C13: 27.9 | F13: =IF($C$7="KRW",$C$13*100,$C$13) -> 2790 | L13: =IF($C$7="KRW",VLOOKUP($C$7,$R$7:$AA$43,6,FALSE),VLOOKUP($C$7,$R$7:$AA$43,5,FALSE)) -> -1000000 | P13: American | R13: GBP | S13: =LEFT(P13,1) -> A | T13: =IFERROR(IF(AND(R13=$C$7,S13="A"),$C$9,IF(AND(R13=$C$7,S13="E"),$C$9/$C$12,""))*$T$5,"") | U13: =IFERROR(IF(AND(R13=$C$7,S13="A"),$C$9*$C$12,IF(AND(R13=$C$7,S13="E"),$C$9,""))*$U$5,"") | V13: =IFERROR(IF(AND(R13=$C$7,S13="A"),$C$9,IF(AND(R13=$C$7,S13="E"),$C$9/$C$14,""))*$V$5,"") | W13: =IFERROR(IF(AND(R13=$C$7,S13="A"),$C$9*$C$14,IF(AND(R13=$C$7,S13="E"),$C$9,""))*$W$5,"")
B14: Far Leg Rate | C14: =C12+F13/10000 -> 1380.279 | K14: Rate | L14: =$C$14 -> 1380.279 | P14: European | R14: SAR | S14: =LEFT(P14,1) -> E | T14: =IFERROR(IF(AND(R14=$C$7,S14="A"),$C$9,IF(AND(R14=$C$7,S14="E"),$C$9/$C$12,""))*$T$5,"") | U14: =IFERROR(IF(AND(R14=$C$7,S14="A"),$C$9*$C$12,IF(AND(R14=$C$7,S14="E"),$C$9,""))*$U$5,"") | V14: =IFERROR(IF(AND(R14=$C$7,S14="A"),$C$9,IF(AND(R14=$C$7,S14="E"),$C$9/$C$14,""))*$V$5,"") | W14: =IFERROR(IF(AND(R14=$C$7,S14="A"),$C$9*$C$14,IF(AND(R14=$C$7,S14="E"),$C$9,""))*$W$5,"")
K15: 2 | L15: =IF($L$16>0,"B",IF($L$16<0,"S","")) -> B | M15: =M10 -> KRW | P15: European | R15: SEK | S15: =LEFT(P15,1) -> E | T15: =IFERROR(IF(AND(R15=$C$7,S15="A"),$C$9,IF(AND(R15=$C$7,S15="E"),$C$9/$C$12,""))*$T$5,"") | U15: =IFERROR(IF(AND(R15=$C$7,S15="A"),$C$9*$C$12,IF(AND(R15=$C$7,S15="E"),$C$9,""))*$U$5,"") | V15: =IFERROR(IF(AND(R15=$C$7,S15="A"),$C$9,IF(AND(R15=$C$7,S15="E"),$C$9/$C$14,""))*$V$5,"") | W15: =IFERROR(IF(AND(R15=$C$7,S15="A"),$C$9*$C$14,IF(AND(R15=$C$7,S15="E"),$C$9,""))*$W$5,"")
B16: 고금리 통화 | C16: =IF(C13>0,M10,IF(C13=0,"동일",M7)) -> KRW | L16: =IF($C$7="KRW",VLOOKUP($C$7,$R$7:$AA$43,5,FALSE),VLOOKUP($C$7,$R$7:$AA$43,6,FALSE)) -> 1380279000 | P16: European | R16: SGD | S16: =LEFT(P16,1) -> E | T16: =IFERROR(IF(AND(R16=$C$7,S16="A"),$C$9,IF(AND(R16=$C$7,S16="E"),$C$9/$C$12,""))*$T$5,"") | U16: =IFERROR(IF(AND(R16=$C$7,S16="A"),$C$9*$C$12,IF(AND(R16=$C$7,S16="E"),$C$9,""))*$U$5,"") | V16: =IFERROR(IF(AND(R16=$C$7,S16="A"),$C$9,IF(AND(R16=$C$7,S16="E"),$C$9/$C$14,""))*$V$5,"") | W16: =IFERROR(IF(AND(R16=$C$7,S16="A"),$C$9*$C$14,IF(AND(R16=$C$7,S16="E"),$C$9,""))*$W$5,"")
B17: 저금리 통화 | C17: =IF(C13>0,M7,IF(C13=0,"동일",M10)) -> USD | J17: 기간 | L17: =C11-C10 -> 365 | P17: European | R17: THB | S17: =LEFT(P17,1) -> E | T17: =IFERROR(IF(AND(R17=$C$7,S17="A"),$C$9,IF(AND(R17=$C$7,S17="E"),$C$9/$C$12,""))*$T$5,"") | U17: =IFERROR(IF(AND(R17=$C$7,S17="A"),$C$9*$C$12,IF(AND(R17=$C$7,S17="E"),$C$9,""))*$U$5,"") | V17: =IFERROR(IF(AND(R17=$C$7,S17="A"),$C$9,IF(AND(R17=$C$7,S17="E"),$C$9/$C$14,""))*$V$5,"") | W17: =IFERROR(IF(AND(R17=$C$7,S17="A"),$C$9*$C$14,IF(AND(R17=$C$7,S17="E"),$C$9,""))*$W$5,"")
J18: 스왑포인트 | L18: =C13 -> 27.9 | P18: American | R18: NZD | S18: =LEFT(P18,1) -> A | T18: =IFERROR(IF(AND(R18=$C$7,S18="A"),$C$9,IF(AND(R18=$C$7,S18="E"),$C$9/$C$12,""))*$T$5,"") | U18: =IFERROR(IF(AND(R18=$C$7,S18="A"),$C$9*$C$12,IF(AND(R18=$C$7,S18="E"),$C$9,""))*$U$5,"") | V18: =IFERROR(IF(AND(R18=$C$7,S18="A"),$C$9,IF(AND(R18=$C$7,S18="E"),$C$9/$C$14,""))*$V$5,"") | W18: =IFERROR(IF(AND(R18=$C$7,S18="A"),$C$9*$C$14,IF(AND(R18=$C$7,S18="E"),$C$9,""))*$W$5,"")
B19: USD/KRW 환율 | C19: 1380 | J19: 스왑 비이자손익 | L19: =IF($C$3="A",M10,IF($C$3="E",M7,"")) -> USD | M19: =IF($C$7="KRW",(($L$11+$L$16)/$C$19),IF($C$3="A",(L16+L11),IF($C$3="E",(L8+L13),""))) -> 202.17391 | P19: European | R19: HKD | S19: =LEFT(P19,1) -> E | T19: =IFERROR(IF(AND(R19=$C$7,S19="A"),$C$9,IF(AND(R19=$C$7,S19="E"),$C$9/$C$12,""))*$T$5,"") | U19: =IFERROR(IF(AND(R19=$C$7,S19="A"),$C$9*$C$12,IF(AND(R19=$C$7,S19="E"),$C$9,""))*$U$5,"") | V19: =IFERROR(IF(AND(R19=$C$7,S19="A"),$C$9,IF(AND(R19=$C$7,S19="E"),$C$9/$C$14,""))*$V$5,"") | W19: =IFERROR(IF(AND(R19=$C$7,S19="A"),$C$9*$C$14,IF(AND(R19=$C$7,S19="E"),$C$9,""))*$W$5,"")
B20: USD 운용금리 | C20: 0.0532 | E20: 1 | F20: =ABS($F$9*C20/365*$L$17) -> 53200 | G20: =IF($F$3="A1",-$F$21,IF($F$3="A2",$F$20,IF($F$3="E1",$F$20,IF($F$3="E2",-$F$21,"")))) -> -53500 | L20: KRW | M20: =$M$19*$C$19 -> 279000 | P20: European | R20: NOK | S20: =LEFT(P20,1) -> E | T20: =IFERROR(IF(AND(R20=$C$7,S20="A"),$C$9,IF(AND(R20=$C$7,S20="E"),$C$9/$C$12,""))*$T$5,"") | U20: =IFERROR(IF(AND(R20=$C$7,S20="A"),$C$9*$C$12,IF(AND(R20=$C$7,S20="E"),$C$9,""))*$U$5,"") | V20: =IFERROR(IF(AND(R20=$C$7,S20="A"),$C$9,IF(AND(R20=$C$7,S20="E"),$C$9/$C$14,""))*$V$5,"") | W20: =IFERROR(IF(AND(R20=$C$7,S20="A"),$C$9*$C$14,IF(AND(R20=$C$7,S20="E"),$C$9,""))*$W$5,"")
B21: USD 조달금리 | C21: 0.0535 | E21: 2 | F21: =ABS($F$9*C21/365*$L$17) -> 53500 | J21: 연환산금리 | L21: =ABS($M$19*360/$L$17/IF($C$7="KRW",$L$8,$L$11)) -> 0.00019940441 | P21: European | R21: CAD | S21: =LEFT(P21,1) -> E | T21: =IFERROR(IF(AND(R21=$C$7,S21="A"),$C$9,IF(AND(R21=$C$7,S21="E"),$C$9/$C$12,""))*$T$5,"") | U21: =IFERROR(IF(AND(R21=$C$7,S21="A"),$C$9*$C$12,IF(AND(R21=$C$7,S21="E"),$C$9,""))*$U$5,"") | V21: =IFERROR(IF(AND(R21=$C$7,S21="A"),$C$9,IF(AND(R21=$C$7,S21="E"),$C$9/$C$14,""))*$V$5,"") | W21: =IFERROR(IF(AND(R21=$C$7,S21="A"),$C$9*$C$14,IF(AND(R21=$C$7,S21="E"),$C$9,""))*$W$5,"")
B22: USD SOFR | C22: 0.0528201 | E22: 3 | F22: =ABS($F$9*C22/365*$L$17) -> 52820.1 | J22: 순 손익 (운용 - 조달 ± 스왑) | L22: =IF($C$3="A",M10,IF($C$3="E",M7,"")) -> USD | M22: =IF($C$7="KRW",(($L$11+$L$16)/$C$19),IF($C$3="A",(L16+L11),IF($C$3="E",(L8+L13),"")))+G20 -> -53297.826 | S22: =LEFT(P22,1) | T22: =IFERROR(IF(AND(R22=$C$7,S22="A"),$C$9,IF(AND(R22=$C$7,S22="E"),$C$9/$C$12,""))*$T$5,"") | U22: =IFERROR(IF(AND(R22=$C$7,S22="A"),$C$9*$C$12,IF(AND(R22=$C$7,S22="E"),$C$9,""))*$U$5,"") | V22: =IFERROR(IF(AND(R22=$C$7,S22="A"),$C$9,IF(AND(R22=$C$7,S22="E"),$C$9/$C$14,""))*$V$5,"") | W22: =IFERROR(IF(AND(R22=$C$7,S22="A"),$C$9*$C$14,IF(AND(R22=$C$7,S22="E"),$C$9,""))*$W$5,"")
L23: KRW | M23: =$M$22*$C$19 -> -73551000 | S23: =LEFT(P23,1) | T23: =IFERROR(IF(AND(R23=$C$7,S23="A"),$C$9,IF(AND(R23=$C$7,S23="E"),$C$9/$C$12,""))*$T$5,"") | U23: =IFERROR(IF(AND(R23=$C$7,S23="A"),$C$9*$C$12,IF(AND(R23=$C$7,S23="E"),$C$9,""))*$U$5,"") | V23: =IFERROR(IF(AND(R23=$C$7,S23="A"),$C$9,IF(AND(R23=$C$7,S23="E"),$C$9/$C$14,""))*$V$5,"") | W23: =IFERROR(IF(AND(R23=$C$7,S23="A"),$C$9*$C$14,IF(AND(R23=$C$7,S23="E"),$C$9,""))*$W$5,"")
B24: =C7 -> KRW | C24: 0.035 | E24: 4 | J24: 연환산금리 | L24: =ABS($M$22*360/$L$17/$L$11) -> 3.809255e-05 | S24: =LEFT(P24,1) | T24: =IFERROR(IF(AND(R24=$C$7,S24="A"),$C$9,IF(AND(R24=$C$7,S24="E"),$C$9/$C$12,""))*$T$5,"") | U24: =IFERROR(IF(AND(R24=$C$7,S24="A"),$C$9*$C$12,IF(AND(R24=$C$7,S24="E"),$C$9,""))*$U$5,"") | V24: =IFERROR(IF(AND(R24=$C$7,S24="A"),$C$9,IF(AND(R24=$C$7,S24="E"),$C$9/$C$14,""))*$V$5,"") | W24: =IFERROR(IF(AND(R24=$C$7,S24="A"),$C$9*$C$14,IF(AND(R24=$C$7,S24="E"),$C$9,""))*$W$5,"")
B25: =C7 -> KRW | C25: 0.035 | E25: 5 | S25: =LEFT(P25,1) | T25: =IFERROR(IF(AND(R25=$C$7,S25="A"),$C$9,IF(AND(R25=$C$7,S25="E"),$C$9/$C$12,""))*$T$5,"") | U25: =IFERROR(IF(AND(R25=$C$7,S25="A"),$C$9*$C$12,IF(AND(R25=$C$7,S25="E"),$C$9,""))*$U$5,"") | V25: =IFERROR(IF(AND(R25=$C$7,S25="A"),$C$9,IF(AND(R25=$C$7,S25="E"),$C$9/$C$14,""))*$V$5,"") | W25: =IFERROR(IF(AND(R25=$C$7,S25="A"),$C$9*$C$14,IF(AND(R25=$C$7,S25="E"),$C$9,""))*$W$5,"")
S26: =LEFT(P26,1) | T26: =IFERROR(IF(AND(R26=$C$7,S26="A"),$C$9,IF(AND(R26=$C$7,S26="E"),$C$9/$C$12,""))*$T$5,"") | U26: =IFERROR(IF(AND(R26=$C$7,S26="A"),$C$9*$C$12,IF(AND(R26=$C$7,S26="E"),$C$9,""))*$U$5,"") | V26: =IFERROR(IF(AND(R26=$C$7,S26="A"),$C$9,IF(AND(R26=$C$7,S26="E"),$C$9/$C$14,""))*$V$5,"") | W26: =IFERROR(IF(AND(R26=$C$7,S26="A"),$C$9*$C$14,IF(AND(R26=$C$7,S26="E"),$C$9,""))*$W$5,"")
B27: ※ Swap Point 입력 방법 | S27: =LEFT(P27,1) | T27: =IFERROR(IF(AND(R27=$C$7,S27="A"),$C$9,IF(AND(R27=$C$7,S27="E"),$C$9/$C$12,""))*$T$5,"") | U27: =IFERROR(IF(AND(R27=$C$7,S27="A"),$C$9*$C$12,IF(AND(R27=$C$7,S27="E"),$C$9,""))*$U$5,"") | V27: =IFERROR(IF(AND(R27=$C$7,S27="A"),$C$9,IF(AND(R27=$C$7,S27="E"),$C$9/$C$14,""))*$V$5,"") | W27: =IFERROR(IF(AND(R27=$C$7,S27="A"),$C$9*$C$14,IF(AND(R27=$C$7,S27="E"),$C$9,""))*$W$5,"")
B28: USD/KRW : 0,000.01 = 100bp 로 입력 | S28: =LEFT(P28,1) | T28: =IFERROR(IF(AND(R28=$C$7,S28="A"),$C$9,IF(AND(R28=$C$7,S28="E"),$C$9/$C$12,""))*$T$5,"") | U28: =IFERROR(IF(AND(R28=$C$7,S28="A"),$C$9*$C$12,IF(AND(R28=$C$7,S28="E"),$C$9,""))*$U$5,"") | V28: =IFERROR(IF(AND(R28=$C$7,S28="A"),$C$9,IF(AND(R28=$C$7,S28="E"),$C$9/$C$14,""))*$V$5,"") | W28: =IFERROR(IF(AND(R28=$C$7,S28="A"),$C$9*$C$14,IF(AND(R28=$C$7,S28="E"),$C$9,""))*$W$5,"")
B29: 그 외통화 : 0.00010000 = 1bp 로 입력 | S29: =LEFT(P29,1) | T29: =IFERROR(IF(AND(R29=$C$7,S29="A"),$C$9,IF(AND(R29=$C$7,S29="E"),$C$9/$C$12,""))*$T$5,"") | U29: =IFERROR(IF(AND(R29=$C$7,S29="A"),$C$9*$C$12,IF(AND(R29=$C$7,S29="E"),$C$9,""))*$U$5,"") | V29: =IFERROR(IF(AND(R29=$C$7,S29="A"),$C$9,IF(AND(R29=$C$7,S29="E"),$C$9/$C$14,""))*$V$5,"") | W29: =IFERROR(IF(AND(R29=$C$7,S29="A"),$C$9*$C$14,IF(AND(R29=$C$7,S29="E"),$C$9,""))*$W$5,"") | X29: =IF(S29="E",$C$9,"") | Y29: =IF(S29="A",$C$9,"") | Z29: =IFERROR(X29*$C$14,"") | AA29: =IFERROR(Y29*$C$14,"")
S30: =LEFT(P30,1) | T30: =IFERROR(IF(AND(R30=$C$7,S30="A"),$C$9,IF(AND(R30=$C$7,S30="E"),$C$9/$C$12,""))*$T$5,"") | U30: =IFERROR(IF(AND(R30=$C$7,S30="A"),$C$9*$C$12,IF(AND(R30=$C$7,S30="E"),$C$9,""))*$U$5,"") | V30: =IFERROR(IF(AND(R30=$C$7,S30="A"),$C$9,IF(AND(R30=$C$7,S30="E"),$C$9/$C$14,""))*$V$5,"") | W30: =IFERROR(IF(AND(R30=$C$7,S30="A"),$C$9*$C$14,IF(AND(R30=$C$7,S30="E"),$C$9,""))*$W$5,"") | X30: =IF(S30="E",$C$9,"") | Y30: =IF(S30="A",$C$9,"") | Z30: =IFERROR(X30*$C$14,"") | AA30: =IFERROR(Y30*$C$14,"")
S31: =LEFT(P31,1) | T31: =IFERROR(IF(AND(R31=$C$7,S31="A"),$C$9,IF(AND(R31=$C$7,S31="E"),$C$9/$C$12,""))*$T$5,"") | U31: =IFERROR(IF(AND(R31=$C$7,S31="A"),$C$9*$C$12,IF(AND(R31=$C$7,S31="E"),$C$9,""))*$U$5,"") | V31: =IFERROR(IF(AND(R31=$C$7,S31="A"),$C$9,IF(AND(R31=$C$7,S31="E"),$C$9/$C$14,""))*$V$5,"") | W31: =IFERROR(IF(AND(R31=$C$7,S31="A"),$C$9*$C$14,IF(AND(R31=$C$7,S31="E"),$C$9,""))*$W$5,"") | X31: =IF(S31="E",$C$9,"") | Y31: =IF(S31="A",$C$9,"") | Z31: =IFERROR(X31*$C$14,"") | AA31: =IFERROR(Y31*$C$14,"")
S32: =LEFT(P32,1) | T32: =IFERROR(IF(AND(R32=$C$7,S32="A"),$C$9,IF(AND(R32=$C$7,S32="E"),$C$9/$C$12,""))*$T$5,"") | U32: =IFERROR(IF(AND(R32=$C$7,S32="A"),$C$9*$C$12,IF(AND(R32=$C$7,S32="E"),$C$9,""))*$U$5,"") | V32: =IFERROR(IF(AND(R32=$C$7,S32="A"),$C$9,IF(AND(R32=$C$7,S32="E"),$C$9/$C$14,""))*$V$5,"") | W32: =IFERROR(IF(AND(R32=$C$7,S32="A"),$C$9*$C$14,IF(AND(R32=$C$7,S32="E"),$C$9,""))*$W$5,"") | X32: =IF(S32="E",$C$9,"") | Y32: =IF(S32="A",$C$9,"") | Z32: =IFERROR(X32*$C$14,"") | AA32: =IFERROR(Y32*$C$14,"")
S33: =LEFT(P33,1) | T33: =IFERROR(IF(AND(R33=$C$7,S33="A"),$C$9,IF(AND(R33=$C$7,S33="E"),$C$9/$C$12,""))*$T$5,"") | U33: =IFERROR(IF(AND(R33=$C$7,S33="A"),$C$9*$C$12,IF(AND(R33=$C$7,S33="E"),$C$9,""))*$U$5,"") | V33: =IFERROR(IF(AND(R33=$C$7,S33="A"),$C$9,IF(AND(R33=$C$7,S33="E"),$C$9/$C$14,""))*$V$5,"") | W33: =IFERROR(IF(AND(R33=$C$7,S33="A"),$C$9*$C$14,IF(AND(R33=$C$7,S33="E"),$C$9,""))*$W$5,"") | X33: =IF(S33="E",$C$9,"") | Y33: =IF(S33="A",$C$9,"") | Z33: =IFERROR(X33*$C$14,"") | AA33: =IFERROR(Y33*$C$14,"")
S34: =LEFT(P34,1) | T34: =IFERROR(IF(AND(R34=$C$7,S34="A"),$C$9,IF(AND(R34=$C$7,S34="E"),$C$9/$C$12,""))*$T$5,"") | U34: =IFERROR(IF(AND(R34=$C$7,S34="A"),$C$9*$C$12,IF(AND(R34=$C$7,S34="E"),$C$9,""))*$U$5,"") | V34: =IFERROR(IF(AND(R34=$C$7,S34="A"),$C$9,IF(AND(R34=$C$7,S34="E"),$C$9/$C$14,""))*$V$5,"") | W34: =IFERROR(IF(AND(R34=$C$7,S34="A"),$C$9*$C$14,IF(AND(R34=$C$7,S34="E"),$C$9,""))*$W$5,"") | X34: =IF(S34="E",$C$9,"") | Y34: =IF(S34="A",$C$9,"") | Z34: =IFERROR(X34*$C$14,"") | AA34: =IFERROR(Y34*$C$14,"")
S35: =LEFT(P35,1) | T35: =IFERROR(IF(AND(R35=$C$7,S35="A"),$C$9,IF(AND(R35=$C$7,S35="E"),$C$9/$C$12,""))*$T$5,"") | U35: =IFERROR(IF(AND(R35=$C$7,S35="A"),$C$9*$C$12,IF(AND(R35=$C$7,S35="E"),$C$9,""))*$U$5,"") | V35: =IFERROR(IF(AND(R35=$C$7,S35="A"),$C$9,IF(AND(R35=$C$7,S35="E"),$C$9/$C$14,""))*$V$5,"") | W35: =IFERROR(IF(AND(R35=$C$7,S35="A"),$C$9*$C$14,IF(AND(R35=$C$7,S35="E"),$C$9,""))*$W$5,"") | X35: =IF(S35="E",$C$9,"") | Y35: =IF(S35="A",$C$9,"") | Z35: =IFERROR(X35*$C$14,"") | AA35: =IFERROR(Y35*$C$14,"")
S36: =LEFT(P36,1) | T36: =IFERROR(IF(AND(R36=$C$7,S36="A"),$C$9,IF(AND(R36=$C$7,S36="E"),$C$9/$C$12,""))*$T$5,"") | U36: =IFERROR(IF(AND(R36=$C$7,S36="A"),$C$9*$C$12,IF(AND(R36=$C$7,S36="E"),$C$9,""))*$U$5,"") | V36: =IFERROR(IF(AND(R36=$C$7,S36="A"),$C$9,IF(AND(R36=$C$7,S36="E"),$C$9/$C$14,""))*$V$5,"") | W36: =IFERROR(IF(AND(R36=$C$7,S36="A"),$C$9*$C$14,IF(AND(R36=$C$7,S36="E"),$C$9,""))*$W$5,"") | X36: =IF(S36="E",$C$9,"") | Y36: =IF(S36="A",$C$9,"") | Z36: =IFERROR(X36*$C$14,"") | AA36: =IFERROR(Y36*$C$14,"")
S37: =LEFT(P37,1) | T37: =IFERROR(IF(AND(R37=$C$7,S37="A"),$C$9,IF(AND(R37=$C$7,S37="E"),$C$9/$C$12,""))*$T$5,"") | U37: =IFERROR(IF(AND(R37=$C$7,S37="A"),$C$9*$C$12,IF(AND(R37=$C$7,S37="E"),$C$9,""))*$U$5,"") | V37: =IFERROR(IF(AND(R37=$C$7,S37="A"),$C$9,IF(AND(R37=$C$7,S37="E"),$C$9/$C$14,""))*$V$5,"") | W37: =IFERROR(IF(AND(R37=$C$7,S37="A"),$C$9*$C$14,IF(AND(R37=$C$7,S37="E"),$C$9,""))*$W$5,"") | X37: =IF(S37="E",$C$9,"") | Y37: =IF(S37="A",$C$9,"") | Z37: =IFERROR(X37*$C$14,"") | AA37: =IFERROR(Y37*$C$14,"")
S38: =LEFT(P38,1) | T38: =IFERROR(IF(AND(R38=$C$7,S38="A"),$C$9,IF(AND(R38=$C$7,S38="E"),$C$9/$C$12,""))*$T$5,"") | U38: =IFERROR(IF(AND(R38=$C$7,S38="A"),$C$9*$C$12,IF(AND(R38=$C$7,S38="E"),$C$9,""))*$U$5,"") | V38: =IFERROR(IF(AND(R38=$C$7,S38="A"),$C$9,IF(AND(R38=$C$7,S38="E"),$C$9/$C$14,""))*$V$5,"") | W38: =IFERROR(IF(AND(R38=$C$7,S38="A"),$C$9*$C$14,IF(AND(R38=$C$7,S38="E"),$C$9,""))*$W$5,"") | X38: =IF(S38="E",$C$9,"") | Y38: =IF(S38="A",$C$9,"") | Z38: =IFERROR(X38*$C$14,"") | AA38: =IFERROR(Y38*$C$14,"")
S39: =LEFT(P39,1) | T39: =IFERROR(IF(AND(R39=$C$7,S39="A"),$C$9,IF(AND(R39=$C$7,S39="E"),$C$9/$C$12,""))*$T$5,"") | U39: =IFERROR(IF(AND(R39=$C$7,S39="A"),$C$9*$C$12,IF(AND(R39=$C$7,S39="E"),$C$9,""))*$U$5,"") | V39: =IFERROR(IF(AND(R39=$C$7,S39="A"),$C$9,IF(AND(R39=$C$7,S39="E"),$C$9/$C$14,""))*$V$5,"") | W39: =IFERROR(IF(AND(R39=$C$7,S39="A"),$C$9*$C$14,IF(AND(R39=$C$7,S39="E"),$C$9,""))*$W$5,"") | X39: =IF(S39="E",$C$9,"") | Y39: =IF(S39="A",$C$9,"") | Z39: =IFERROR(X39*$C$14,"") | AA39: =IFERROR(Y39*$C$14,"")
S40: =LEFT(P40,1) | T40: =IFERROR(IF(AND(R40=$C$7,S40="A"),$C$9,IF(AND(R40=$C$7,S40="E"),$C$9/$C$12,""))*$T$5,"") | U40: =IFERROR(IF(AND(R40=$C$7,S40="A"),$C$9*$C$12,IF(AND(R40=$C$7,S40="E"),$C$9,""))*$U$5,"") | V40: =IFERROR(IF(AND(R40=$C$7,S40="A"),$C$9,IF(AND(R40=$C$7,S40="E"),$C$9/$C$14,""))*$V$5,"") | W40: =IFERROR(IF(AND(R40=$C$7,S40="A"),$C$9*$C$14,IF(AND(R40=$C$7,S40="E"),$C$9,""))*$W$5,"") | X40: =IF(S40="E",$C$9,"") | Y40: =IF(S40="A",$C$9,"") | Z40: =IFERROR(X40*$C$14,"") | AA40: =IFERROR(Y40*$C$14,"")
S41: =LEFT(P41,1) | T41: =IFERROR(IF(AND(R41=$C$7,S41="A"),$C$9,IF(AND(R41=$C$7,S41="E"),$C$9/$C$12,""))*$T$5,"") | U41: =IFERROR(IF(AND(R41=$C$7,S41="A"),$C$9*$C$12,IF(AND(R41=$C$7,S41="E"),$C$9,""))*$U$5,"") | V41: =IFERROR(IF(AND(R41=$C$7,S41="A"),$C$9,IF(AND(R41=$C$7,S41="E"),$C$9/$C$14,""))*$V$5,"") | W41: =IFERROR(IF(AND(R41=$C$7,S41="A"),$C$9*$C$14,IF(AND(R41=$C$7,S41="E"),$C$9,""))*$W$5,"") | X41: =IF(S41="E",$C$9,"") | Y41: =IF(S41="A",$C$9,"") | Z41: =IFERROR(X41*$C$14,"") | AA41: =IFERROR(Y41*$C$14,"")
... S43: =LEFT(P43,1) | T43: =IFERROR(IF(AND(R43=$C$7,S43="A"),$C$9,IF(AND(R43=$C$7,S43="E"),$C$9/$C$12,""))*$T$5,"") | U43: =IFERROR(IF(AND(R43=$C$7,S43="A"),$C$9*$C$12,IF(AND(R43=$C$7,S43="E"),$C$9,""))*$U$5,"") | V43: =IFERROR(IF(AND(R43=$C$7,S43="A"),$C$9,IF(AND(R43=$C$7,S43="E"),$C$9/$C$14,""))*$V$5,"") | W43: =IFERROR(IF(AND(R43=$C$7,S43="A"),$C$9*$C$14,IF(AND(R43=$C$7,S43="E"),$C$9,""))*$W$5,"") | X43: =IF(S43="E",$C$9,"") | Y43: =IF(S43="A",$C$9,"") | Z43: =IFERROR(X43*$C$14,"") | AA43: =IFERROR(Y43*$C$14,"")

Sheet 결재용(2)
C1: 외화예금 우대금리 승인명세
C2: =H7 -> 46188
M3: 담당 | N3: 부장
A5: 번호 | B5: 신규/연장 | C5: 상품 | D5: 지점명 | E5: 고객명 | F5: 통화 | G5: 금액 | H5: 신규일자 | I5: 만기일자 | J5: 월수 | K5: 일수 | L5: 고시금리 | M5: 우대금리 | N5: 적용금리
A7: 1 | B7: 연장 | C7: =K17 -> MMDA | D7: =C17 -> 본점영업부 | E7: =F17 -> 와이엠에스에이 | F7: USD | G7: =L17*1000000 -> 8090000 | H7: =G17 -> 46188 | I7: =H17 -> 46218 | J7: =J17 -> 1 | K7: =I7-H7 -> 30 | L7: =AE17 -> 0.022743 | M7: =AF17 -> 0.009257 | N7: =AG17 -> 0.032
A8: 2 | B8: 연장 | C8: =K18 -> MMDA | D8: =C18 -> 성남영업부 | E8: =F18 -> ㈜현대그린푸드 | F8: USD | G8: =L18*1000000 -> 1430000 | H8: =G18 -> 46188 | I8: =H18 -> 46218 | J8: =J18 -> 1 | K8: =I8-H8 -> 30 | L8: =AE18 -> 0.022743 | M8: =AF18 -> 0.009257 | N8: =AG18 -> 0.032
A9: 3 | B9: 연장 | C9: =K19 -> MMDA | D9: =C19 -> 이현공단영업부 | E9: =F19 -> ㈜지엠메탈 | F9: USD | G9: =L19*1000000 -> 19000000 | H9: =G19 -> 46188 | I9: =H19 -> 46218 | J9: =J19 -> 1 | K9: =I9-H9 -> 30 | L9: =AE19 -> 0.022743 | M9: =AF19 -> 0.009257 | N9: =AG19 -> 0.032
A10: 4 | B10: 연장 | C10: =K20 -> MMDA | D10: =C20 -> 달성공단영업부 | E10: =F20 -> 한국비철㈜ | F10: USD | G10: =L20*1000000 -> 1110000 | H10: =G20 -> 46188 | I10: =H20 -> 46218 | J10: =J20 -> 1 | K10: =I10-H10 -> 30 | L10: =AE20 -> 0.022743 | M10: =AF20 -> 0.007257 | N10: =AG20 -> 0.03
A11: 5 | B11: 연장 | C11: =K21 -> MMDA | D11: =C21 -> 달성공단영업부 | E11: =F21 -> 한국비앤씨㈜ | F11: USD | G11: =L21*1000000 -> 8670000 | H11: =G21 -> 46162 | I11: =H21 -> 46195 | J11: =J21 -> 1 | K11: =I11-H11 -> 33 | L11: =AE21 -> 0.02216 | M11: =AF21 -> 0.00984 | N11: =AG21 -> 0.032
A12: 6 | B12: 신규 | C12: =K22 -> MMDA | D12: =C22 -> 원주금융센터 | E12: =F22 -> ㈜비알팜 | F12: USD | G12: =L22*1000000 -> 1630000 | H12: =G22 -> 46132 | I12: =H22 -> 46162 | J12: =J22 -> 1 | K12: =I12-H12 -> 30 | L12: =AE22 -> 0.023306 | M12: =AF22 -> 0.008694 | N12: =AG22 -> 0.032
A13: 7 | B13: 신규 | C13: =K23 -> 정기예금 | D13: =C23 -> 경산공단영업부 | E13: =F23 -> ㈜일지테크 | F13: USD | G13: =L23*1000000 -> 4500000 | H13: =G23 -> 45961 | I13: =H23 -> 45968 | J13: =J23 -> 0 | K13: =I13-H13 -> 7 | L13: =AE23 -> 0.03286 | M13: =AF23 -> 0.00214 | N13: =AG23 -> 0.035
A16: ↓ | B16: 값붙여넣기
A17: 705 | B17: 46188 | C17: 본점영업부 | D17: 지점장 이명훈 | E17: 계장 이향하 | F17: 와이엠에스에이 | G17: 46188 | H17: 46218 | I17: 30 | J17: 1 | K17: MMDA | L17: 8.09 | O17: 1M | P17: 0.0363312 | R17: m | V17: 0.040198 | W17: 0.002813 | X17: 0.003609 | Y17: 0.022743 | Z17: 0.00172 | AA17: 0.002 | AB17: -0.00172 | AC17: -0.00372 | AD17: 0.032 | AE17: 0.022743 | AF17: 0.009257 | AG17: 0.032 | AH17: 46188 | AI17: 1 | AJ17: Y | AK17: MMDA 3.64
A18: 706 | B18: 46188 | C18: 성남영업부 | D18: 지점장 김준석 | E18: 대리 김다예 | F18: ㈜현대그린푸드 | G18: 46188 | H18: 46218 | I18: 30 | J18: 1 | K18: MMDA | L18: 1.43 | O18: 1M | P18: 0.0363312 | R18: m | V18: 0.040198 | W18: 0.002813 | X18: 0.003609 | Y18: 0.022743 | Z18: 0.00172 | AA18: 0.002 | AB18: -0.00172 | AC18: -0.00372 | AD18: 0.032 | AE18: 0.022743 | AF18: 0.009257 | AG18: 0.032 | AH18: 46188 | AI18: 2 | AJ18: Y | AK18: MMDA 3.64
A19: 707 | B19: 46188 | C19: 이현공단영업부 | D19: 지점장 이병휘 | E19: 대리 김지은 | F19: ㈜지엠메탈 | G19: 46188 | H19: 46218 | I19: 30 | J19: 1 | K19: MMDA | L19: 19 | O19: 1M | P19: 0.0363312 | R19: m | V19: 0.040198 | W19: 0.002813 | X19: 0.003609 | Y19: 0.022743 | Z19: 0.00172 | AA19: 0.002 | AB19: -0.00172 | AC19: -0.00372 | AD19: 0.032 | AE19: 0.022743 | AF19: 0.009257 | AG19: 0.032 | AH19: 46188 | AI19: 3 | AJ19: Y | AK19: MMDA 3.64
A20: 708 | B20: 46188 | C20: 달성공단영업부 | D20: 지점장 김창현 | E20: 대리 손지민 | F20: 한국비철㈜ | G20: 46188 | H20: 46218 | I20: 30 | J20: 1 | K20: MMDA | L20: 1.11 | O20: 1M | P20: 0.0363312 | R20: m | V20: 0.040198 | W20: 0.002813 | X20: 0.005609 | Y20: 0.022743 | Z20: 0.00172 | AA20: 0.002 | AB20: -0.00172 | AC20: -0.00372 | AD20: 0.03 | AE20: 0.022743 | AF20: 0.007257 | AG20: 0.03 | AH20: 46188 | AI20: 4 | AJ20: Y | AK20: MMDA 3.64
A21: 693 | B21: 46162 | C21: 달성공단영업부 | D21: 센터장 박청동 | E21: 대리 박유경 | F21: 한국비앤씨㈜ | G21: 46162 | H21: 46195 | I21: 33 | J21: 1 | K21: MMDA | L21: 8.67 | O21: 1M | P21: 0.0359824 | R21: m | V21: 0.039972 | W21: 0.002798 | X21: 0.003398 | Y21: 0.02216 | Z21: 0.00172 | AA21: 0.002 | AB21: -0.00172 | AC21: -0.00372 | AD21: 0.032 | AE21: 0.02216 | AF21: 0.00984 | AG21: 0.032 | AH21: 46162 | AI21: 5 | AJ21: Y | AK21: mmda 3.64
A22: 670 | B22: 46132 | C22: 원주금융센터 | D22: 센터장 정병훈 | E22: 부지점장 이정화 | F22: ㈜비알팜 | G22: 46132 | H22: 46162 | I22: 30 | J22: 1 | K22: MMDA | L22: 1.63 | O22: 1M | P22: 0.0365719 | R22: m | V22: 0.040431 | W22: 0.002838 | X22: 0.003736 | Y22: 0.023306 | Z22: 0.00172 | AA22: 0.002 | AB22: -0.00172 | AC22: -0.00372 | AD22: 0.032 | AE22: 0.023306 | AF22: 0.008694 | AG22: 0.032 | AH22: 46132 | AI22: 6 | AJ22: Y | AK22: MMDA 3.64
A23: 508 | B23: 45954 | C23: 경산공단영업부 | D23: 지점장 박대연 | E23: 과장 최정식 | F23: ㈜일지테크 | G23: 45961 | H23: 45968 | I23: 7 | J23: 0 | K23: 정기예금 | L23: 4.5 | O23: 1W | P23: 0.0421083 | R23: m | V23: 0.043256 | W23: 0.003065 | X23: 0.003944 | Y23: 0.03286 | Z23: 0.00172 | AA23: 0.002 | AB23: -0.00172 | AC23: -0.00372 | AD23: 0.035 | AE23: 0.03286 | AF23: 0.00214 | AG23: 0.035 | AH23: 45961 | AI23: 7 | AJ23: Y | AK23: MMDA 3.83

Sheet (2)규정
A1: 내규 - 여신/여신관리 - 여신운용지침 - 제6장 여신의종류(기업자금대출) - 제11절 외화대출
A3: 제1관 통 칙
A4: 1. 대출종류
A5: 자금종류에 따라 다음과 같이 분류한다.
A6: 가. 특별외화대출
A7: 한국은행으로부터 외화대출용 특별수탁금을 지원받아 취급하는 대출을 말한다.
A8: 나. 일반외화대출
A9: 당행에서 조달한 외화자금으로 취급하는 대출을 말한다.
A11: 2. 대출대상(2002.8.26 신설)
A12: 가. 기업체 운영에 필요한 운전자금
A13: 나. 기업체 시설투자와 관련한 시설자금
A15: 3. 자금용도 제한(2007.8.10 신설)
... A67: (1) 약정시기
A68: 최초 여신거래약정서 징구시 약정한다. | E68: (대출 중 특별약정 체결은 불가)
A69: (2) 약정내용
A70: 여신거래약정서의 특약사항란에 (별표 1)의 내용을 기재후 날인을 받는다
A71: (3) 한도확인
A72: 통화전환에 관한 특별약정을 체결하고자 할 경우는 사전에 외화자금 담당 부서에 한도확인을 받아야 한다
A73: 다. 통화전환 가능 통화
A74: 통화전환은 외화에서 원화로만 가능하다
A75: 라. 통화전환 방법 및 조건
A76: (1) 통화전환 신청은 전환예정일의 2영업일전까지 (별표 2)의 서식에 의거 신청하여야 한다
A77: (2) 통화전환은 대출기간이내에서 1회에 한하여 신청할 수 있으며, 통화를 전환한 경우 재전환은 할 수 없다
A78: (3) 원화대출의 취급조건
A79: (가) 통화를 전환할 경우 원화대출의 이자율 등 제조건은 전환시점의 여신 관련 지침에 의한다.
A80: 다만, 대출기간은 외화대출의 당초 대출기일 이내로 약정하여야 한다
... A89: 통화전환수수료는 여신금리적용지침에 의한다
B91: 여신금리적용지침
B92: 제2장 외화대출금리
B93: 1. 금리적용
B95: 외화대출의 금리적용은 다음에 의한다.
B96: 가. 특별외화대출금
B97: (1) 적용이율 : 수탁금리 + 0.75%
B98: (2) 수탁금리는 한국은행 수탁시 적용하는 금리를 말한다.
B99: 나. 일반외화대출금 (2008.3.21 개정)
B100: (1) 적용이율 : 외화시장기준금리 + 가산금리
B101: (가) 외화시장기준금리
B102: 외화대출기준금리는 공신력 있는 통신회사(Reuters)로부터 제공받는 직전 영업일의 통화별, 기간별 금리로 결정하여 외화자금부서장이 매일 고시한다.
B103: (나) 가산금리는 여신금리시스템을 통하여 산정함을 원칙으로 한다.
... B128: 차주의 제반 거래실적, 기여도, 향후 기대수익 및 기타 신청사유 등을 감안하여 통화 전환 수수료는 감액 또는 면제 할 수 있다.
A131: 11. 준용규정
A133: 이 절에서 정하지 아니한 사항은 여신관련 규정 및 지침에서 정하는 바에 따른다
A135: 제2관 외화대출 모범규준
A136: 제1목 총 칙
A137: 1. 이 규준은 차주에 대한 위험 고지, 환헤지 안내, 차주의 환리스크 관리능력을 반영한 여신심사 등 외화대출을 취급함에 있어 준수하여야 하는 업무처리절차를 정함으로써 금융소비자의 권익을 보호하고 여심심사체계를 개선함을 목적으로 한다.
A139: 2. 이 규준에서 사용되는 용어의 정의는 다음과 같다.
A140: 가. "외화대출"이란 「외국환거래법」제3조 제1항 제14호의 "거주자"에 대하여 취급하는 「은행업감독업무시행세칙」<별표4-1>'외국환계정 회계처리기준'의 "외화대출금"중 "외화대출","외화표시 원화대출","기타" 및 "외화사모사채"를 포함한다.
A141: 나. "차주"란 외화대출을 제공받거나 외화대출에 대해 보증 또는 담보를 제공함으로써 채무를 부담하는 자로서 금융업을 영위하지 않는 자를 말한다.
A142: 다. "환헤지 상품"이란 「외국환거래규정」제1-2조 제20-2호에서 규정하는 통화를 기초자산으로 하는 파생상품으로서 외화대출의 환리스크를 부분적으로 또는 전부 회피하기 위한 것을 말한다.
A145: 제2목 금융소비자 보호 강화
A146: 1. 차주에게 외화대출 관련 리스크를 사전에 고지하고, 대출실행 이후에도 차주가 관련 리스크를 관리할 수 있도록 다음과 같은 절차를 통해 필요한 정보를 제공하여야 한다.
A147: 가. 대출 실행 이전에 외화대출의 구조 및 리스크를 충분히 설명하고 리스크 요인에 대한 질문 형식의 위험 고지 확인서(별표 1)를 차주의 자필서명을 포함하여 제출받아야 하며, 외화대출의 리스크 요인을 구체적으로 설명한 안내책자(handbook)를 차주에게 교부하여야 한다.
... A174: (3) 종합평점이 60점 미만인 경우 여신거절

Sheet 대출결재용
C4: 외화대출한도 승인명세
C5: 46182
K6: 담당 | L6: 부장
A8: 번호 | B8: 신규/연기 | C8: 상품 | D8: 지점명 | E8: 고객명 | F8: 통화 | G8: 금액 | H8: 대출일자 | I8: 만기일자 | J8: 용도 | K8: 금리 | L8: 통화전환약정
A9: 1 | B9: 연기 | C9: 운전자금 | D9: =D16 -> 대신동지점 | E9: =F16 -> 김태수 | F9: =G16 -> JPY | G9: =H16 -> 31840000 | H9: =L16 -> 46189 | I9: =M16 -> 46554 | J9: =K16 -> 운전자금 | K9: =O16 -> 0.0301 | L9: =N16 -> X
A11: 2 | B11: 연기 | C11: 외화운전자금대출 | D11: =D17 -> 월배영업부 | E11: =F17 -> 김석범 | F11: =G17 -> JPY | G11: =H17 -> 49500000 | H11: =L17 -> 45147 | I11: =M17 -> 45513 | J11: =K17 -> 운전자금 | K11: =O17 -> 0.0195 | L11: =N17 -> X
A15: ↓ | B15: 값붙여넣기
A16: 연기 | B16: 46182 | D16: 대신동지점 | E16: 이태희 | F16: 김태수 | G16: JPY | H16: 31840000 | I16: 160.16 | J16: 198801.2 | K16: 운전자금 | L16: 46189 | M16: 46554 | N16: X | O16: 0.0301 | P16: 김유빈 | Q16: 최종훈
A17: 연기 | B17: 45126 | D17: 월배영업부 | E17: 유영호 | F17: 김석범 | G17: JPY | H17: 49500000 | I17: 139.2 | J17: 355603.45 | K17: 운전자금 | L17: 45147 | M17: 45513 | N17: X | O17: 0.0195 | P17: 강석호 | Q17: 손창호

Sheet (2)대출한도,금리
A1: 신규 : 본건 운전자금 용도의 외화대출 신규신청건으로 만기까지 한도(USD) 사용을 승인함 | G1: 연기 : 본건 기사용 외화대출연기 신청건으로 만기까지 한도(USD) 사용을 승인함
A2: 신규/연기/상담 | B2: 신청일 | D2: 지점 | E2: 담당자 | F2: 업체명 | G2: 통화 | H2: 금액 | I2: 환산환율 | J2: 대미환산 | K2: 용도 | L2: 예정일 | M2: 만기일 | N2: 통화옵션 | O2: 금리 | P2: 심사 | Q2: 결재 | R2: 비고
A3: 신규 | B3: 40702 | D3: 서부산지점 | E3: 김창수 | F3: 노효선 | G3: JPY | H3: 46000000 | I3: 78.5 | J3: =H3/I3 -> 585987.26 | K3: 시설재 | L3: 40704 | M3: 41070 | O3: 4 | P3: 김진태 | Q3: 문성완
A4: 연기 | B4: 40701 | D4: 안동지점 | E4: 손무백 | F4: 정성원 | G4: JPY | H4: 20400000 | I4: 78.5 | J4: =H4/I4 -> 259872.61 | K4: 시설재 | L4: 40716 | M4: 40899 | O4: 5.16 | P4: 김진태 | Q4: 문성완
A5: 연기 | B5: 40704 | D5: 팔달영업부 | E5: 김순호 | F5: 양찬수 | G5: JPY | H5: 67000000 | I5: 78.5 | J5: =IF(I5="","",H5/I5) -> 853503.18 | K5: 운전자금 | L5: 40713 | M5: 41079 | O5: 5 | P5: 김진태 | Q5: 문성완
A6: 연기 | B6: 40704 | D6: 부산영업부 | E6: 홍현주 | F6: ㈜케이티지 | G6: JPY | H6: 100000000 | I6: 78.5 | J6: =IF(I6="","",H6/I6) -> 1273885.4 | K6: 운전자금 | L6: 40704 | M6: 41070 | O6: 3.88 | P6: 김진태 | Q6: 문성완
A7: 신규 | B7: 40707 | D7: 반야월지점 | E7: 권영섭 | F7: 김진도 | G7: JPY | H7: 15700000 | I7: 78.5 | J7: =IF(I7="","",H7/I7) -> 200000 | K7: 시설재 | L7: 40708 | M7: 41074 | O7: 3 | P7: 김진태 | Q7: 문성완
A8: 연기 | B8: 40707 | D8: 안동지점 | E8: 손무백 | F8: 정성원 | G8: JPY | H8: 20400000 | I8: 78.5 | J8: =IF(I8="","",H8/I8) -> 259872.61 | K8: 시설재 | L8: 40716 | M8: 41082 | O8: 5.14 | P8: 김진태 | Q8: 문성완
A9: 연기 | B9: 40707 | D9: 대신동영업부 | E9: 배구현 | F9: 김수현 | G9: JPY | H9: 59600000 | I9: 78.5 | J9: =IF(I9="","",H9/I9) -> 759235.67 | K9: 운전자금 | L9: 40717 | M9: 41083 | O9: 3.4 | P9: 김진태 | Q9: 문성완
A10: 신규 | B10: 40708 | D10: 유통단지지점 | E10: 손종득 | F10: 박윤희 | G10: USD | H10: 300000 | I10: 1 | J10: =IF(I10="","",H10/I10) -> 300000 | K10: 운전자금 | L10: 40708 | M10: 40800 | O10: 3 | P10: 김진태 | Q10: 문성완
A11: 연기 | B11: 40709 | D11: 성서공단영업부 | E11: 이승원 | F11: 박미희 | G11: JPY | H11: 27370000 | I11: 78.5 | J11: =IF(I11="","",H11/I11) -> 348662.42 | K11: 시설재 | L11: 40710 | M11: 41441 | O11: 2.62 | P11: 김진태 | Q11: 문성완
A12: 연기 | B12: 40709 | D12: 성서공단영업부 | E12: 이승원 | F12: 홍원화 | G12: JPY | H12: 23700000 | I12: 78.5 | J12: =IF(I12="","",H12/I12) -> 301910.83 | K12: 운전자금 | L12: 40714 | M12: 41080 | O12: 4.26 | P12: 김진태 | Q12: 문성완
A13: 연기 | B13: 40709 | D13: 칠곡지점 | E13: 김성훈 | F13: ㈜퓨전소프트 | G13: USD | H13: 2740000 | I13: 1 | J13: =IF(I13="","",H13/I13) -> 2740000 | K13: 시설재 | L13: 40714 | M13: 41080 | O13: 4.01 | P13: 김진태 | Q13: 문성완
A14: 신규 | B14: 40710 | D14: 서부산지점 | E14: 김창수 | F14: 정정일 | G14: JPY | H14: 37500000 | I14: 78.5 | J14: =IF(I14="","",H14/I14) -> 477707.01 | K14: 시설재 | L14: 40711 | M14: 41077 | O14: 4 | P14: 김진태 | Q14: 문성완
A15: 연기 | B15: 40710 | D15: 경주영업부 | E15: 예병대 | F15: ㈜서경메디텍 | G15: JPY | H15: 200000000 | I15: 78.5 | J15: =IF(I15="","",H15/I15) -> 2547770.7 | K15: 시설재 | L15: 40714 | M15: 41079 | O15: 4.66 | P15: 김진태 | Q15: 문성완
A16: 연기 | B16: 40710 | D16: 강남영업부 | E16: 정경준 | F16: 고정찬 | G16: JPY | H16: 29500000 | I16: 78.5 | J16: =IF(I16="","",H16/I16) -> 375796.18 | K16: 운전자금 | L16: 40716 | M16: 41082 | O16: 5.46 | P16: 김진태 | Q16: 문성완
... A61: 신규 | B61: 40785 | D61: 성서공단영업부 | E61: 한성곤 | F61: ㈜영일무역 | G61: JPY | H61: 16900000 | I61: 78.5 | J61: =IF(I61="","",H61/I61) -> 215286.62 | K61: 시설재자금 | L61: 40788 | M61: 41154 | O61: 3.5 | P61: 김진태 | Q61: 문성완
A62: 신규 | B62: 40785 | D62: 부산영업부 | E62: 신동준 | F62: 문혜숙 | G62: JPY | H62: 153000000 | I62: 78.5 | J62: =IF(I62="","",H62/I62) -> 1949044.6 | K62: 시설재자금 | L62: 201-08-31 | M62: 41882 | O62: 4 | P62: 김진태 | Q62: 문성완
A63: 연기 | B63: 40786 | D63: 반야월지점 | E63: 임욱희 | F63: 지앤비모터스주식회사 | G63: JPY | H63: 31000000 | I63: 78.5 | J63: =IF(I63="","",H63/I63) -> 394904.46 | K63: 시설재 | L63: 40787 | M63: 41153 | O63: 2.8 | P63: 김진태 | Q63: 문성완
A64: 신규 | B64: 40788 | D64: 관음지점 | E64: 1830188 | F64: 최규수 | G64: EUR | H64: 595200 | I64: 1.2 | J64: =IF(I64="","",H64/I64) -> 496000 | K64: 시설재 | L64: 40806 | M64: 40970 | O64: 5 | P64: 김진태 | Q64: 문성완
A65: 연기 | B65: 40788 | D65: 부산영업부 | E65: 1951485 | F65: 진정호 | G65: JPY | H65: 61100000 | I65: 78.5 | J65: =IF(I65="","",H65/I65) -> 778343.95 | K65: 시설재 | L65: 40796 | M65: 41162 | O65: 4 | P65: 김진태 | Q65: 문성완
A66: 연기 | B66: 40788 | D66: 부산영업부 | E66: 1870340 | F66: 염태수 | G66: JPY | H66: 90000000 | I66: 78.5 | J66: =IF(I66="","",H66/I66) -> 1146496.8 | K66: 시설재 | L66: 40791 | M66: 41157 | O66: 3.7 | P66: 김진태 | Q66: 문성완
A67: 연기 | B67: 40788 | D67: 부산영업부 | E67: 1870340 | F67: 염태수 | G67: JPY | H67: 52000000 | I67: 78.5 | J67: =IF(I67="","",H67/I67) -> 662420.38 | K67: 시설재 | L67: 40822 | M67: 41188 | O67: 3.7 | P67: 김진태 | Q67: 문성완
A68: 상담 | B68: 40788 | D68: 포항영업부 | E68: - | F68: 제일염화 | G68: USD | H68: 1000000 | I68: 1 | J68: =IF(I68="","",H68/I68) -> 1000000 | K68: - | L68: - | M68: - | O68: - | P68: 김진태 | Q68: 문성완
A69: 연기 | B69: 40791 | D69: 성서영업부 | E69: 1870389 | F69: (주)청우 | G69: JPY | H69: 30000000 | I69: 78.5 | J69: =IF(I69="","",H69/I69) -> 382165.61 | K69: 시설재 | L69: 40792 | M69: 41159 | O69: 3.39 | P69: 김진태 | Q69: 문성완
A70: 연기 | B70: 40791 | D70: 부산영업부 | E70: 1951485 | F70: 이규우 | G70: JPY | H70: 2500000 | I70: 78.5 | J70: =IF(I70="","",H70/I70) -> 31847.134 | K70: 시설재 | L70: 40799 | M70: 41165 | O70: 3.72 | P70: 김진태 | Q70: 문성완
A71: 연기 | B71: 40791 | D71: 광장지점 | E71: 1950586 | F71: (주)신한정밀 | G71: JPY | H71: 19200000 | I71: 78.5 | J71: =IF(I71="","",H71/I71) -> 244585.99 | K71: 시설재 | L71: 40794 | M71: 41161 | O71: 3.7 | P71: 김진태 | Q71: 문성완
A72: 연기 | B72: 40792 | D72: 죽도동지점 | E72: 2060378 | F72: 최학수 | G72: JPY | H72: 8400000 | I72: 78.5 | J72: =IF(I72="","",H72/I72) -> 107006.37 | K72: 시설재 | L72: 40798 | M72: 41164 | O72: 5.2 | P72: 김진태 | Q72: 문성완
A73: 연기 | B73: 40793 | D73: 강남영업부 | E73: 2040169 | F73: 성삼모 | G73: JPY | H73: 21000000 | I73: 78.5 | J73: =IF(I73="","",H73/I73) -> 267515.92 | K73: 시설재 | L73: 40814 | M73: 41180 | O73: 4.3 | P73: 김진태 | Q73: 문성완
A74: 연기 | B74: 40794 | D74: 부산영업부 | E74: 1951485 | F74: 이규우 | G74: JPY | H74: 25000000 | I74: 78.5 | J74: =IF(I74="","",H74/I74) -> 318471.34 | K74: 시설재 | L74: 40800 | M74: 41165 | O74: 3.72 | P74: 김진태 | Q74: 문성완
A75: 연기 | B75: 40795 | D75: 반야월지점 | E75: 임욱희 | F75: 조양래 | G75: JPY | H75: 20000000 | I75: 78.5 | J75: =IF(I75="","",H75/I75) -> 254777.07 | K75: 운전자금 | L75: 40707 | M75: 41071 | O75: 4 | P75: 김진태 | Q75: 문성완
A76: 신규 | B76: 40800 | D76: 유통단지지점 | E76: 1951097 | F76: 박윤희 | G76: USD | H76: 200000 | I76: 1 | J76: =IF(I76="","",H76/I76) -> 200000 | K76: 결제자금 | L76: 40801 | M76: 40892 | O76: 3.3 | P76: 김진태 | Q76: 문성완
A77: 연기 | B77: 40800 | D77: 부산영업부 | E77: 1951485 | F77: (주)고려케미칼 | G77: JPY | H77: 85000000 | I77: 78.5 | J77: =IF(I77="","",H77/I77) -> 1082802.5 | K77: 시설재 | L77: 40809 | M77: 41175 | O77: 4.31 | P77: 김진태 | Q77: 문성완
A78: 신규 | B78: 40801 | D78: 구미영업부 | E78: 2110571 | F78: 남미숙 | G78: USD | H78: 200000 | I78: 1 | J78: =IF(I78="","",H78/I78) -> 200000 | K78: 운전자금 | L78: 40802 | M78: 40832 | O78: 3.8 | P78: 김진태 | Q78: 문성완
A79: 신규 | B79: 40801 | D79: 구미영업부 | E79: 2110571 | F79: (주)경대물산 | G79: USD | H79: 150000 | I79: 1 | J79: =IF(I79="","",H79/I79) -> 150000 | K79: 운전자금 | L79: 40802 | M79: 40832 | O79: 3.8 | P79: 김진태 | Q79: 문성완
A80: 연기 | B80: 40801 | D80: 부산영업부 | E80: 1951485 | F80: 이영순 | G80: JPY | H80: 80300000 | I80: 78.5 | J80: =IF(I80="","",H80/I80) -> 1022929.9 | K80: 시설재 | L80: 40814 | M80: 41180 | O80: 4.85 | P80: 김진태 | Q80: 문성완
... A92: 연기 | B92: 40813 | D92: 대신동영업부 | E92: 1920116 | F92: 이상제 | G92: JPY | H92: 66000000 | I92: 78.5 | J92: =IF(I92="","",H92/I92) -> 840764.33 | K92: 해외투자 | L92: 40816 | M92: 40818 | O92: 3 | P92: 김진태 | Q92: 문성완
A93: 신규 | B93: 40814 | D93: 서울영업부 | E93: 1951325 | F93: ㈜오씨아이상사 | G93: USD | H93: 3000000 | I93: 1 | J93: =IF(I93="","",H93/I93) -> 3000000 | K93: 결제자금 | L93: 40837 | M93: 40898 | O93: 2.5 | P93: 김진태 | Q93: 문성완
A94: 연기 | B94: 40816 | D94: 성서공단영업부 | E94: 1970247 | F94: 김영호 | G94: JPY | H94: 46000000 | I94: 78.5 | J94: =IF(I94="","",H94/I94) -> 585987.26 | K94: 시설재 | L94: 40820 | M94: 41186 | O94: 5 | P94: 김진태 | Q94: 문성완
A95: 신규 | B95: 40821 | D95: 서울영업부 | E95: 1890114 | F95: ㈜풍산 | G95: USD | H95: 5000000 | I95: 1 | J95: =IF(I95="","",H95/I95) -> 5000000 | K95: 운전자금 | L95: 40823 | M95: 41189 | O95: 3.74 | P95: 김진태 | Q95: 문성완
A96: 신규 | B96: 40821 | D96: 부산영업부 | E96: 1870340 | F96: ㈜비에스비스틸 | G96: USD | H96: 2070000 | I96: 1 | J96: =IF(I96="","",H96/I96) -> 2070000 | K96: 운전자금 | L96: 40823 | M96: 41189 | O96: 3.8 | P96: 김진태 | Q96: 문성완
A97: 연기 | B97: 40821 | D97: 창원지점 | E97: 1900875 | F97: 김관우 | G97: JPY | H97: 65000000 | I97: 78.5 | J97: =IF(I97="","",H97/I97) -> 828025.48 | K97: 시설재 | L97: 40830 | M97: 41197 | O97: 5 | P97: 김진태 | Q97: 문성완
A98: 신규 | B98: 40822 | D98: 고령지점 | E98: 1960121 | F98: 김석균 | G98: USD | H98: 16000 | I98: 1 | J98: =IF(I98="","",H98/I98) -> 16000 | K98: 운전자금 | L98: 40826 | M98: 40918 | O98: 2.6 | P98: 김진태 | Q98: 문성완
A99: 연기 | B99: 40823 | D99: 성서영업부 | E99: 진영훈 | F99: ㈜JVM | G99: USD | H99: 3000000 | I99: 1 | J99: =IF(I99="","",H99/I99) -> 3000000 | K99: 시설재 | L99: 40828 | M99: 41011 | O99: 2.65 | P99: 김진태 | Q99: 문성완
A100: 연기 | B100: 40826 | D100: 월배영업부 | E100: 박제상 | F100: 박세웅 | G100: JPY | H100: 13000000 | I100: 78.5 | J100: =IF(I100="","",H100/I100) -> 165605.1 | K100: 시설재 | L100: 40826 | M100: 41192 | O100: 4 | P100: 김진태 | Q100: 문성완
A101: 연기 | B101: 40830 | D101: 반야월지점 | E101: 권영섭 | F101: ㈜기풍 | G101: JPY | H101: 12900000 | I101: 78.5 | J101: =IF(I101="","",H101/I101) -> 164331.21 | K101: 시설재 | L101: 40830 | M101: 41196 | O101: 3 | P101: 김진태 | Q101: 문성완
A102: 신규 | B102: 40834 | D102: 성서공단영업부 | E102: 1970247 | F102: ㈜신도하이텍 | G102: JPY | H102: 67000000 | I102: 78.5 | J102: =IF(I102="","",H102/I102) -> 853503.18 | K102: 시설재 | L102: 40834 | M102: 41200 | O102: 3 | P102: 김진태 | Q102: 문성완
A103: 신규 | B103: 40834 | D103: 강남영업부 | E103: 1960460 | F103: 동원산업㈜ | G103: USD | H103: 5000000 | I103: 1 | J103: =IF(I103="","",H103/I103) -> 5000000 | K103: 운전자금 | L103: 40841 | M103: 41207 | O103: 2.94 | P103: 김진태 | Q103: 문성완
A104: 신규 | B104: 40835 | D104: 반야월지점 | E104: 권영섭 | F104: 김진도 | G104: JPY | H104: 75000000 | I104: 78.5 | J104: =IF(I104="","",H104/I104) -> 955414.01 | K104: 시설재 | L104: 40841 | M104: 41207 | O104: 3 | P104: 김진태 | Q104: 문성완
A105: 신규 | B105: 40835 | D105: 노원동지점 | E105: 김규훈 | F105: 신택산업(주) | G105: USD | H105: 125000 | I105: 1 | J105: =IF(I105="","",H105/I105) -> 125000 | K105: 운전자금 | L105: 40840 | M105: 40897 | O105: 2.75 | P105: 김진태 | Q105: 문성완
A106: 연기 | B106: 40835 | D106: 신암동지점 | E106: 이원호 | F106: 인덕건설㈜ | G106: JPY | H106: 210000000 | I106: 78.5 | J106: =IF(I106="","",H106/I106) -> 2675159.2 | K106: 시설재자금 | L106: 40840 | M106: 40841 | O106: 3.85 | P106: 김진태 | Q106: 문성완
A107: 연기 | B107: 40835 | D107: 반야월지점 | E107: 권영섭 | F107: 이춘우 | G107: JPY | H107: 56000000 | I107: 78.5 | J107: =IF(I107="","",H107/I107) -> 713375.8 | K107: 시설재자금 | L107: 40837 | M107: 41203 | O107: 3 | P107: 김진태 | Q107: 문성완
A108: 연기 | B108: 40835 | D108: 대신동영업부 | E108: 박주한 | F108: 박웅 | G108: JPY | H108: 150000000 | I108: 78.5 | J108: =IF(I108="","",H108/I108) -> 1910828 | K108: 운전자금 | L108: 40842 | M108: 41057 | O108: 3.1 | P108: 김진태 | Q108: 문성완
A109: 연기 | B109: 40835 | D109: 대신동영업부 | E109: 박영삼 | F109: ㈜범양 | G109: JPY | H109: 8000000 | I109: 78.5 | J109: =IF(I109="","",H109/I109) -> 101910.83 | K109: 운전자금 | L109: 40841 | M109: 41207 | O109: 4 | P109: 김진태 | Q109: 문성완
A110: 연기 | B110: 40836 | D110: 칠곡지점 | E110: 김성훈 | F110: ㈜대구플라스틱 | G110: JPY | H110: 41000000 | I110: 78.5 | J110: =IF(I110="","",H110/I110) -> 522292.99 | K110: 시설재자금 | L110: 40842 | M110: 41208 | O110: 3.8 | P110: 김진태 | Q110: 문성완
A111: 연기 | B111: 40837 | D111: 3공단영업부 | E111: 최정욱 | F111: 김진남 | G111: JPY | H111: 22800000 | I111: 78.5 | J111: =IF(I111="","",H111/I111) -> 290445.86 | K111: 시설재자금 | L111: 40844 | M111: 41210 | O111: 4 | P111: 김진태 | Q111: 문성완
A112: 연기 | B112: 40837 | D112: 3공단영업부 | E112: 최정욱 | F112: 박윤태 | G112: JPY | H112: 27000000 | I112: 78.5 | J112: =IF(I112="","",H112/I112) -> 343949.04 | K112: 시설재자금 | L112: 40844 | M112: 41210 | O112: 4 | P112: 김진태 | Q112: 문성완
A113: 연기 | B113: 40837 | D113: 3공단영업부 | E113: 최정욱 | F113: 한규상 | G113: JPY | H113: 17600000 | I113: 78.5 | J113: =IF(I113="","",H113/I113) -> 224203.82 | K113: 시설재자금 | L113: 40844 | M113: 41210 | O113: 4 | P113: 김진태 | Q113: 문성완
A114: 신규 | B114: 40840 | D114: 고령지점 | E114: 임병기 | F114: 김석균 | G114: USD | H114: 38880 | I114: 1 | J114: =IF(I114="","",H114/I114) -> 38880 | K114: 운전자금 | L114: 40841 | M114: 41024 | O114: 2.69 | P114: 김진태 | Q114: 문성완
A115: 신규 | B115: 40841 | D115: 3공단영업부 | E115: 최정욱 | F115: 세진금속㈜ | G115: USD | H115: 464000 | I115: 1 | J115: =IF(I115="","",H115/I115) -> 464000 | K115: 운전자금 | L115: 40844 | M115: 41027 | O115: 3.5 | P115: 김진태 | Q115: 문성완
... A238: 연기 | B238: 40996 | D238: 월배영업부 | E238: 마필재 | F238: 김무성 | G238: JPY | H238: 51000000 | I238: 82 | J238: =IF(I238="","",H238/I238) -> 621951.22 | K238: 운전자금 | L238: 40998 | M238: 41363 | O238: 4.15 | P238: 양재율 | Q238: 문성완
A239: 연기 | B239: 40996 | D239: 강남영업부 | E239: 정경준 | F239: 이정숙 | G239: JPY | H239: 45000000 | I239: 82 | J239: =IF(I239="","",H239/I239) -> 548780.49 | K239: 운전자금 | L239: 41003 | M239: 2013-04-04- | O239: 4.5 | P239: 양재율 | Q239: 문성완
A240: 연기 | B240: 40996 | D240: 서울영업부 | E240: 김수현 | F240: 조재호 | G240: JPY | H240: 16000000 | I240: 82 | J240: =IF(I240="","",H240/I240) -> 195121.95 | K240: 운전자금 | L240: 41001 | M240: 41364 | O240: 4.17 | P240: 양재율 | Q240: 문성완
A241: 신규 | B241: 40996 | D241: 노원동지점 | E241: 함장섭 | F241: ㈜화인 | G241: JPY | H241: 81450000 | I241: 82 | J241: =IF(I241="","",H241/I241) -> 993292.68 | K241: 시설재 | L241: 40998 | M241: 41363 | O241: 2.99 | P241: 강현수 | Q241: 권기욱
A242: 연기 | B242: 40997 | D242: 복현지점 | E242: 김기철 | F242: ㈜대동정공 | G242: JPY | H242: 91000000 | I242: 82 | J242: =IF(I242="","",H242/I242) -> 1109756.1 | K242: 시설자금 | L242: 40997 | M242: 40998 | O242: 2.41 | P242: 양재율 | Q242: 문성완
A243: 연기 | B243: 41001 | D243: 반야월지점 | E243: 권영섭 | F243: 정후영 | G243: JPY | H243: 33000000 | I243: 82 | J243: =IF(I243="","",H243/I243) -> 402439.02 | K243: 시설자금 | L243: 41008 | M243: 41371 | O243: 3.77 | P243: 양재율 | Q243: 문성완
A244: 연기 | B244: 41001 | D244: 성서영업부 | E244: 김진해 | F244: ㈜JVM | G244: USD | H244: 3000000 | I244: 1 | J244: =IF(I244="","",H244/I244) -> 3000000 | K244: 운전자금 | L244: 41011 | M244: 41194 | O244: 2.67 | P244: 양재율 | Q244: 문성완
A245: 연기 | B245: 41002 | D245: 반월당지점 | E245: 최정훈 | F245: 천승근 | G245: JPY | H245: 8600000 | I245: 82 | J245: =IF(I245="","",H245/I245) -> 104878.05 | K245: 운전자금 | L245: 41022 | M245: 41387 | O245: 4.5 | P245: 양재율 | Q245: 문성완
A246: 신규 | B246: 41002 | D246: 서울영업부 | E246: 김수현 | F246: 한영주 | G246: JPY | H246: 46100000 | I246: 82 | J246: =IF(I246="","",H246/I246) -> 562195.12 | K246: 운전자금 | L246: 41005 | M246: 41370 | O246: 4.44 | P246: 강현수 | Q246: 권기욱
A247: 신규 | B247: 41002 | D247: 서울영업부 | E247: 김수현 | F247: 한영주 | G247: JPY | H247: 24930000 | I247: 82 | J247: =IF(I247="","",H247/I247) -> 304024.39 | K247: 운전자금 | L247: 41005 | M247: 41385 | O247: 4.05 | P247: 강현수 | Q247: 권기욱
A248: 신규 | B248: 41003 | D248: 복현지점 | E248: 금동삼 | F248: ㈜대동정공 | G248: JPY | H248: 39000000 | I248: 82 | J248: =IF(I248="","",H248/I248) -> 475609.76 | K248: 시설재 | L248: 41004 | M248: 41173 | O248: 2.9 | P248: 강현수 | Q248: 권기욱
A249: 신규 | B249: 41003 | D249: 이현공단지점 | E249: 권용민 | F249: ㈜대성나사산업 | G249: USD | H249: 100000 | I249: 1 | J249: =IF(I249="","",H249/I249) -> 100000 | K249: 운전자금 | L249: 41003 | M249: 41290 | O249: 4.26 | P249: 강현수 | Q249: 권기욱
A250: 연기 | B250: 41005 | D250: 영주지점 | E250: 김대영 | F250: 서인성 | G250: JPY | H250: 350000 | I250: 82 | J250: =IF(I250="","",H250/I250) -> 4268.2927 | K250: 운전자금 | L250: 41013 | M250: 41378 | O250: 4.5 | P250: 양재율 | Q250: 문성완
A251: 신규 | B251: 41005 | D251: 센텀시티지점 | E251: 유창화 | F251: 문점숙 | G251: JPY | H251: 47000000 | I251: 82 | J251: =IF(I251="","",H251/I251) -> 573170.73 | K251: 시설재 | L251: 41012 | M251: 41377 | O251: 3.5 | P251: 강현수 | Q251: 권기욱
... A333: 연기 | B333: 41086 | D333: 경주영업부 | E333: 이성룡 | F333: 고광미 | G333: USD | H333: 480000 | I333: 1 | J333: =IF(I333="","",H333/I333) -> 480000 | K333: 시설재자금 | L333: 41092 | M333: 41457 | O333: 3.4 | P333: 양재율 | Q333: 문성완
A334: 연기 | B334: 41087 | D334: 부산영업부 | E334: 신동준 | F334: ㈜재은씨엔씨 | G334: JPY | H334: 1663900000 | I334: 82 | J334: =IF(I334="","",H334/I334) -> 20291463 | K334: 시설재자금 | L334: 41087 | M334: 41452 | O334: 4.7 | P334: 양재율 | Q334: 문성완 | R334: (주)재은건설로 차주 변경
A335: 연기 | B335: 41087 | D335: 부산영업부 | E335: 신동준 | F335: ㈜재은씨엔씨 | G335: JPY | H335: 328600000 | I335: 82 | J335: =IF(I335="","",H335/I335) -> 4007317.1 | K335: 시설재자금 | L335: 41087 | M335: 41452 | O335: 4.7 | P335: 양재율 | Q335: 문성완 | R335: (주)재은건설로 차주 변경
A336: 연기 | B336: 41087 | D336: 부산영업부 | E336: 신동준 | F336: ㈜재은씨엔씨 | G336: JPY | H336: 61600000 | I336: 82 | J336: =IF(I336="","",H336/I336) -> 751219.51 | K336: 시설재자금 | L336: 41087 | M336: 41452 | O336: 4.7 | P336: 양재율 | Q336: 문성완 | R336: (주)재은건설로 차주 변경
A337: 연기 | B337: 41087 | D337: 월배영업부 | E337: 마필재 | F337: 김오권 | G337: JPY | H337: 60000000 | I337: 82 | J337: =IF(I337="","",H337/I337) -> 731707.32 | K337: 운전자금 | L337: 41089 | M337: 41454 | O337: 3.82 | P337: 양재율 | Q337: 문성완
A338: 신규 | B338: 41093 | D338: 강남영업부 | E338: 박준언 | F338: ㈜티지켐 | G338: USD | H338: 920000 | I338: 1 | J338: =IF(I338="","",H338/I338) -> 920000 | K338: 운전자금 | L338: 41093 | M338: 41458 | O338: 3 | P338: 강현수 | Q338: 권기욱
A339: 연기 | B339: 41094 | D339: 강남영업부 | E339: 정재환 | F339: ㈜유나이티드 오션 | G339: USD | H339: 1500000 | I339: 1 | J339: =IF(I339="","",H339/I339) -> 1500000 | K339: 운전자금 | L339: 41093 | M339: 41277 | O339: 5.5 | P339: 양재율 | Q339: 문성완
A340: 연기 | B340: 41095 | D340: 죽전지점 | E340: 소영섭 | F340: ㈜우성택시 | G340: JPY | H340: 30000000 | I340: 82 | J340: =IF(I340="","",H340/I340) -> 365853.66 | K340: 운전자금 | L340: 41099 | M340: 41100 | O340: 3.7 | P340: 양재율 | Q340: 문성완
A341: 신규 | B341: 41095 | D341: 3공단영업부 | E341: 박성훈 | F341: 세진금속㈜ | G341: USD | H341: 250303 | I341: 1 | J341: =IF(I341="","",H341/I341) -> 250303 | K341: 운전자금 | L341: 41096 | M341: 41280 | O341: 3.5 | P341: 강현수 | Q341: 권기욱
A342: 연기 | B342: 41099 | D342: 부산영업부 | E342: 최정모 | F342: 유두욱 | G342: JPY | H342: 45800000 | I342: 82 | J342: =IF(I342="","",H342/I342) -> 558536.59 | K342: 시설재 | L342: 41100 | M342: 41465 | O342: 4 | P342: 양재율 | Q342: 문성완
A343: 연기 | B343: 41099 | D343: 부산영업부 | E343: 최정모 | F343: 안현둘 | G343: JPY | H343: 46600000 | I343: 82 | J343: =IF(I343="","",H343/I343) -> 568292.68 | K343: 시설재 | L343: 41101 | M343: 41466 | O343: 4 | P343: 양재율 | Q343: 문성완
A344: 연기 | B344: 41099 | D344: 부산영업부 | E344: 최정모 | F344: 조경호 | G344: JPY | H344: 46600000 | I344: 82 | J344: =IF(I344="","",H344/I344) -> 568292.68 | K344: 시설재 | L344: 41104 | M344: 41469 | O344: 4 | P344: 양재율 | Q344: 문성완
A345: 연기 | B345: 41099 | D345: 부산영업부 | E345: 최정모 | F345: 최관석 | G345: JPY | H345: 80500000 | I345: 82 | J345: =IF(I345="","",H345/I345) -> 981707.32 | K345: 시설재 | L345: 41105 | M345: 41470 | O345: 4 | P345: 양재율 | Q345: 문성완
A346: 연기 | B346: 41099 | D346: 부산영업부 | E346: 최정모 | F346: 이상섭 | G346: JPY | H346: 46400000 | I346: 82 | J346: =IF(I346="","",H346/I346) -> 565853.66 | K346: 시설재 | L346: 41108 | M346: 41473 | O346: 4 | P346: 양재율 | Q346: 문성완
A347: 연기 | B347: 41100 | D347: 유통단지영업부 | E347: 손종득 | F347: 박윤희 | G347: USD | H347: 200000 | I347: 1 | J347: =IF(I347="","",H347/I347) -> 200000 | K347: 운전자금 | L347: 41103 | M347: 41167 | O347: 3.26 | P347: 양재율 | Q347: 문성완
A348: 연기 | B348: 41100 | D348: 유통단지영업부 | E348: 손종득 | F348: 박윤희 | G348: USD | H348: 100000 | I348: 1 | J348: =IF(I348="","",H348/I348) -> 100000 | K348: 운전자금 | L348: 41102 | M348: 41167 | O348: 3.26 | P348: 양재율 | Q348: 문성완
... A440: 연기 | B440: 41248 | D440: 서부산지점 | E440: 성구용 | F440: 정정호 | G440: JPY | H440: 77500000 | I440: 82 | J440: =IF(I440="","",H440/I440) -> 945121.95 | K440: 시설재 | L440: 41248 | M440: 41430 | O440: 4.27 | P440: 양재율 | Q440: 문성완
A441: 연기 | B441: 41254 | D441: 월배영업부 | E441: 강평무 | F441: ㈜유성에프티 | G441: JPY | H441: 136500000 | I441: 82 | J441: =IF(I441="","",H441/I441) -> 1664634.1 | K441: 시설재 | L441: 41254 | M441: 42819 | O441: 3.48 | P441: 양재율 | Q441: 문성완 | R441: 만기일 2018년 으로 연장, 2015년 6월부터 3개월마다 11백만엔씩 분할상환예정(이근식차장 6/25일 17시 40분 통화)
A442: 연기 | B442: 41254 | D442: 서부산지점 | E442: 성구용 | F442: ㈜아이온에프앤지 | G442: JPY | H442: 890000000 | I442: 82 | J442: =IF(I442="","",H442/I442) -> 10853659 | K442: 시설재 | L442: 41255 | M442: 41621 | O442: 4.09 | P442: 양재율 | Q442: 문성완
A443: 신규 | B443: 41254 | D443: 부산영업부 | E443: 최정모 | F443: 영산해운㈜ | G443: USD | H443: 1400000 | I443: 82 | J443: =IF(I443="","",H443/I443) -> 17073.171 | K443: 시설재 | L443: 41256 | M443: 41621 | O443: 3.6 | P443: 강현수 | Q443: 권기욱
A444: 신규 | B444: 41254 | D444: 부산영업부 | E444: 최정모 | F444: 영산해운㈜ | G444: USD | H444: 730000 | I444: 82 | J444: =IF(I444="","",H444/I444) -> 8902.439 | K444: 시설재 | L444: 41256 | M444: 42351 | O444: 4.5 | P444: 강현수 | Q444: 권기욱
A445: 연기 | B445: 41257 | D445: 대신동영업부 | E445: 최태곤 | F445: 김양락 | G445: JPY | H445: 160000000 | I445: 82 | J445: =IF(I445="","",H445/I445) -> 1951219.5 | K445: 시설재 | L445: 41260 | M445: 41624 | O445: 3.14 | P445: 양재율 | Q445: 문성완
A446: 연기 | B446: 41257 | D446: 서부산지점 | E446: 성구용 | F446: ㈜에이치에스테크 | G446: JPY | H446: 86700000 | I446: 82 | J446: =IF(I446="","",H446/I446) -> 1057317.1 | K446: 시설재 | L446: 41260 | M446: 41441 | O446: 3.81 | P446: 양재율 | Q446: 문성완
A447: 연기 | B447: 41257 | D447: 서부산지점 | E447: 성구용 | F447: ㈜뉴코텍 | G447: JPY | H447: 87900000 | I447: 82 | J447: =IF(I447="","",H447/I447) -> 1071951.2 | K447: 시설재 | L447: 41260 | M447: 41441 | O447: 3.81 | P447: 양재율 | Q447: 문성완
A448: 연기 | B448: 41257 | D448: 유통단지지점 | E448: 손종득 | F448: 박윤희 | G448: USD | H448: 500000 | I448: 1 | J448: =IF(I448="","",H448/I448) -> 500000 | K448: 운전자금 | L448: 41260 | M448: 41291 | O448: 3.09 | P448: 양재율 | Q448: 문성완
A449: 연기 | B449: 41263 | D449: 효목시장지점 | E449: 최재명 | F449: 윤경규 | G449: JPY | H449: 2500000 | I449: 82 | J449: =IF(I449="","",H449/I449) -> 30487.805 | K449: 운전자금 | L449: 41264 | M449: 41629 | O449: 4.9 | P449: 양재율 | Q449: 문성완
...

Sheet (3)규정
A1: 내규 - 여신/여신관리 - 여신운용지침 - 제6장 여신의종류(기업자금대출) - 제11절 외화대출
A3: 제1관 통 칙
A4: 1. 대출종류
A5: 자금종류에 따라 다음과 같이 분류한다.
A6: 가. 특별외화대출
A7: 한국은행으로부터 외화대출용 특별수탁금을 지원받아 취급하는 대출을 말한다.
A8: 나. 일반외화대출
A9: 당행에서 조달한 외화자금으로 취급하는 대출을 말한다.
A11: 2. 대출대상(2002.8.26 신설)
A12: 가. 기업체 운영에 필요한 운전자금
A13: 나. 기업체 시설투자와 관련한 시설자금
A15: 3. 자금용도 제한(2007.8.10 신설)
... A89: 통화전환수수료는 여신금리적용지침에 의한다
B91: 여신금리적용지침
B92: 제2장 외화대출금리
B93: 1. 금리적용
B95: 외화대출의 금리적용은 다음에 의한다.
B96: 가. 특별외화대출금
B97: (1) 적용이율 : 수탁금리 + 0.75%
B98: (2) 수탁금리는 한국은행 수탁시 적용하는 금리를 말한다.
B99: 나. 일반외화대출금 (2008.3.21 개정)
B100: (1) 적용이율 : 외화시장기준금리 + 가산금리
B101: (가) 외화시장기준금리
B102: 외화시장기준금리는 기간별 LIBOR에 대응하여 결정하고, 당행의 자금사정, 경제여건, 시장의 경쟁력 등을 감안하여 주무부서장이 매일 고시한다.
B103: (나) 가산금리는 원화대출금리지침의 가산금리 및 조정금리 체계를 적용한다.
... B125: (2)징구시기 : 통화전환 약정시에 0.1%를 징구하고 통화전환일에 나머지를 징구한다
A131: 11. 준용규정
A133: 이 절에서 정하지 아니한 사항은 여신관련 규정 및 지침에서 정하는 바에 따른다
A135: 제2관 외화대출 모범규준
A136: 제1목 총 칙
A137: 1. 이 규준은 차주에 대한 위험 고지, 환헤지 안내, 차주의 환리스크 관리능력을 반영한 여신심사 등 외화대출을 취급함에 있어 준수하여야 하는 업무처리절차를 정함으로써 금융소비자의 권익을 보호하고 여심심사체계를 개선함을 목적으로 한다.
A139: 2. 이 규준에서 사용되는 용어의 정의는 다음과 같다.
A140: 가. "외화대출"이란 「외국환거래법」제3조 제1항 제14호의 "거주자"에 대하여 취급하는 「은행업감독업무시행세칙」<별표4-1>'외국환계정 회계처리기준'의 "외화대출금"중 "외화대출","외화표시 원화대출","기타" 및 "외화사모사채"를 포함한다.
A141: 나. "차주"란 외화대출을 제공받거나 외화대출에 대해 보증 또는 담보를 제공함으로써 채무를 부담하는 자로서 금융업을 영위하지 않는 자를 말한다.
A142: 다. "환헤지 상품"이란 「외국환거래규정」제1-2조 제20-2호에서 규정하는 통화를 기초자산으로 하는 파생상품으로서 외화대출의 환리스크를 부분적으로 또는 전부 회피하기 위한 것을 말한다.
A145: 제2목 금융소비자 보호 강화
A146: 1. 차주에게 외화대출 관련 리스크를 사전에 고지하고, 대출실행 이후에도 차주가 관련 리스크를 관리할 수 있도록 다음과 같은 절차를 통해 필요한 정보를 제공하여야 한다.
A147: 가. 대출 실행 이전에 외화대출의 구조 및 리스크를 충분히 설명하고 리스크 요인에 대한 질문 형식의 위험 고지 확인서(별표 1)를 차주의 자필서명을 포함하여 제출받아야 하며, 외화대출의 리스크 요인을 구체적으로 설명한 안내책자(handbook)를 차주에게 교부하여야 한다.
... A174: (3) 종합평점이 60점 미만인 경우 여신거절

Sheet (3)통화전환
A1: 구분 | B1: 신청일 | C1: 지점 | D1: 담당자 | E1: 차주 | F1: 통화 | G1: 금액 | H1: 달러/엔 환율 | I1: 대미환산 | J1: 감면율 | K1: 승인조건 | L1: 심사의견
A2: 통화전환수수료 면제 | B2: 41661 | C2: 서부산지점 | D2: 최진호 | E2: 민미혜 | F2: JPY | G2: 37500000 | H2: 102 | I2: =G2/H2 -> 367647.06 | J2: 1 | K2: 외화대출의 조기상환에 따라 외화조달운용 미스매치 발생하는 점을 감안하여 원화대출 금리 산정시 적절히 반영하시기 바랍니다. | L2: 외화대출금액 37,500,000엔(잔존만기 5개월)의 원화대출로의 통화전환에 따른 수수료(0.25%)를 신청의견을 반영하여 면제함.
A3: 통화전환수수료 면제 | B3: 41767 | C3: 월배영업부 | D3: 양상복 | E3: ㈜남원TEXWELL | F3: JPY | G3: 43830000 | H3: 102 | I3: =G3/H3 -> 429705.88 | J3: 1 | K3: 외화대출의 조기상환에 따라 외화조달운용 미스매치 발생하는 점을 감안하여 원화대출 금리 산정시 적절히 반영하시기 바랍니다. | L3: 외화대출금액43,830,000엔(잔존만기 1개월미만)의 원화대출로의 통화전환에 따른 수수료(0.25%)를 신청의견을 반영하여 면제함.
A4: 통화전환수수료 면제 | B4: 41827 | C4: 센텀시티지점 | D4: 구태훈 | E4: 문점숙 | F4: JPY | G4: 47000000 | H4: 102 | I4: =G4/H4 -> 460784.31 | J4: 1 | K4: 외화대출의 조기상환에 따라 외화조달운용 미스매치 발생하는 점을 감안하여 원화대출 금리 산정시 적절히 반영하시기 바랍니다. | L4: 외화대출금액43,830,000엔(잔존만기 1개월미만)의 원화대출로의 통화전환에 따른 수수료(0.25%)를 신청의견을 반영하여 면제함. (2014.07.10 예정) | N4: 일부 상환 및 일부전환
A5: 통화전환수수료 면제 | B5: 41855 | C5: 반야월지점 | D5: 양성욱 | E5: 김진도 | F5: JPY | G5: 75700000 | H5: 102 | I5: =G5/H5 -> 742156.86 | J5: 1 | K5: 외화대출의 조기상환에 따라 외화조달운용 미스매치 발생하는 점을 감안하여 원화대출 금리 산정시 적절히 반영하시기 바랍니다. | L5: 외화대출 75,700,000엔의 원화대출로의 통화전환에 따른 미징구수수료(0.15%,잔존만기 1년미만)를 신청의견 반영하여 면제함.
A6: 통화전환수수료 면제 | B6: 42131 | C6: 부산영업부 | D6: 최정모 | E6: 영산해운㈜ | F6: JPY | G6: 239400000 | H6: 119 | I6: 2011764.7 | J6: 1 | K6: 외화대출의 조기상환에 따라 외화조달운용 미스매치 발생하는 점을 감안하여 원화대출 금리 산정시 적절히 반영하시기 바랍니다. | L6: 외화대출 239,400,000엔의 원화대출로의 통화전환에 따른 미징구수수료(0.15%,잔존만기 1년미만)를 신청의견 반영하여 면제함.
A7: 통화전환수수료 면제 | B7: 42131 | C7: 부산영업부 | D7: 최정모 | E7: 영산해운㈜ | F7: JPY | G7: 239400000 | H7: 119 | I7: 2011764.7 | J7: 1 | K7: 외화대출의 조기상환에 따라 외화조달운용 미스매치 발생하는 점을 감안하여 원화대출 금리 산정시 적절히 반영하시기 바랍니다. | L7: 외화대출 239,400,000엔의 원화대출로의 통화전환에 따른 미징구수수료(0.15%,잔존만기 1년미만)를 신청의견 반영하여 면제함.
A8: 통화전환수수료 면제 | B8: 42131 | C8: 부산영업부 | D8: 최정모 | E8: 영산해운㈜ | F8: JPY | G8: 239400000 | H8: 119 | I8: 2011764.7 | J8: 1 | K8: 외화대출의 조기상환에 따라 외화조달운용 미스매치 발생하는 점을 감안하여 원화대출 금리 산정시 적절히 반영하시기 바랍니다. | L8: 외화대출 239,400,000엔의 원화대출로의 통화전환에 따른 미징구수수료(0.15%,잔존만기 1년미만)를 신청의견 반영하여 면제함.
A9: 통화전환수수료 면제 | B9: 42131 | C9: 부산영업부 | D9: 최정모 | E9: 영산해운㈜ | F9: JPY | G9: 239400000 | H9: 119 | I9: 2011764.7 | J9: 1 | K9: 외화대출의 조기상환에 따라 외화조달운용 미스매치 발생하는 점을 감안하여 원화대출 금리 산정시 적절히 반영하시기 바랍니다. | L9: 외화대출 239,400,000엔의 원화대출로의 통화전환에 따른 미징구수수료(0.15%,잔존만기 1년미만)를 신청의견 반영하여 면제함.
A10: 통화전환수수료 면제 | B10: 42152 | C10: 경산영업부 | D10: 이상한 | E10: 강창규 | F10: JPY | G10: 20000000 | H10: 124 | I10: 161290.32 | J10: 1 | K10: 외화대출의 조기상환에 따라 외화조달운용 미스매치 발생하는 점을 감안하여 원화대출 금리 산정시 적절히 반영하시기 바랍니다. | L10: 외화대출 20,000,000엔의 원화대출로의 통화전환에 따른 미징구수수료(0.15%,잔존만기 1년미만)를 신청의견 반영하여 면제함.
A11: 통화전환수수료 면제 | B11: 42312 | C11: 동성로지점 | D11: 배병기 | E11: 강부덕 | F11: JPY | G11: 66000000 | H11: 121 | I11: 545454.55 | J11: 1 | K11: 외화대출의 조기상환에 따라 외화조달운용 미스매치 발생하는 점을 감안하여 원화대출 금리 산정시 적절히 반영하시기 바랍니다. | L11: 외화대출 66,000,000엔의 원화대출로의 통화전환에 따른 미징구수수료(0.15%,잔존만기 1년미만)를 신청의견 반영하여 면제함.
A12: 통화전환수수료 면제 | B12: 42340 | C12: 북성로지점 | D12: 김종석 | E12: 이상제 | F12: JPY | G12: 66000000 | H12: 121 | I12: 545454.55 | J12: 1 | K12: 외화대출의 조기상환에 따라 외화조달운용 미스매치 발생하는 점을 감안하여 원화대출 금리 산정시 적절히 반영하시기 바랍니다. | L12: 외화대출 66,000,000엔의 원화대출로의 통화전환에 따른 미징구수수료(0.15%,잔존만기 1년미만)를 신청의견 반영하여 면제함.
A13: 통화전환수수료 면제 | B13: 42353 | C13: 고령지점 | D13: 장훈 | E13: 까나베나㈜ | F13: JPY | G13: 36000000 | H13: 121.91 | I13: 295299.81 | J13: 1 | K13: 외화대출의 조기상환에 따라 외화조달운용 미스매치 발생하는 점을 감안하여 원화대출 금리 산정시 적절히 반영하시기 바랍니다. | L13: 외화대출 36,000,000엔의 원화대출로의 통화전환에 따른 미징구수수료(0.15%,잔존만기 1년미만)를 신청의견 반영하여 면제함.
A14: 통화전환수수료 면제 | B14: 42369 | C14: 성서공단영업부 | D14: 김숙희 | E14: ㈜에이스유리철강 | F14: JPY | G14: 54000000 | H14: 121.91 | I14: 442949.72 | J14: 1 | K14: 외화대출의 조기상환에 따라 외화조달운용 미스매치 발생하는 점을 감안하여 원화대출 금리 산정시 적절히 반영하시기 바랍니다. | L14: 외화대출 54,000,000엔의 원화대출로의 통화전환에 따른 미징구수수료(0.15%,잔존만기 1년미만)를 신청의견 반영하여 면제함.
A17: 통화전환수수료 면제 | B17: 45181 | C17: 서부산지점 | D17: 최진호 | E17: ㈜용진스테코 | F17: JPY | G17: 300000000 | H17: 146 | I17: =G17/H17 -> 2054794.5 | J17: 1 | K17: 본건 기운용중인 일본엔화 외화대출 통화전환 수수료 면제 신청건으로 우수고객 거래기여도 우수하며 통화전환에 따른 유동성관리에 큰 문제가 없어 승인코자 함. | L17: 본건 기운용중인 일본엔화 외화대출 통화전환 수수료 면제 신청건으로 우수고객 거래기여도 우수하며 통화전환에 따른 유동성관리에 큰 문제가 없어 승인코자 함.

Sheet 외화예금승인현황(2015년이전)
A1: 신규 외화대출한도 신규 관리대장(넥스피아 이후 2102 - 1003) | H1: 외화정기예금 대림산업(주) USD 20,000,000 기본금리(0.3161)에 가산금리(0.1339)를 추가하여 최종적용금리(0.45)로 승인함. | J1: 920정하고
A2: 신규/연장 | B2: 신청일 | C2: 지점 | D2: 담당자 | E2: 업체명 | F2: 통화 | G2: 금액 | H2: 상품 | I2: 기본금리 | J2: 가산금리 | K2: 적용금리 | L2: 취급일 | M2: 만기 | N2: 신청번호
A3: 신규 | B3: 40821 | C3: 성서영업부 | D3: 성명희 | E3: 유브이피에이치아이 | F3: USD | G3: 8238198.5 | H3: 외화정기예금 | I3: 0.1117 | J3: 0.3883 | K3: 0.5 | L3: 40821 | M3: 40836
A4: 신규 | B4: 40841 | C4: 강남영업부 | D4: 전혜연 | E4: 동원산업㈜ | F4: USD | G4: 5000000 | H4: 외화보통예금MMDA | I4: 0.0521 | J4: 0.1479 | K4: 0.2 | L4: 40841 | M4: MMDA
A5: 신규 | B5: 40850 | C5: 성서영업부 | D5: 성명희 | E5: 유브이피에이치아이 | F5: USD | G5: 10309833 | H5: 외화정기예금 | I5: 0.11 | J5: 0.29 | K5: 0.4 | L5: 40850 | M5: 40865
A6: 신규 | B6: 40886 | C6: 성서영업부 | D6: 성명희 | E6: 유브이피에이치아이 | F6: USD | G6: 9929942.2 | H6: 외화정기예금 | I6: 0.1198 | J6: 0.2802 | K6: 0.4 | L6: 40886 | M6: 40897
A7: 신규 | B7: 40913 | C7: 성서영업부 | D7: 성명희 | E7: 유브이피에이치아이 | F7: USD | G7: 8788392.5 | H7: 외화정기예금 | I7: 0.1264 | J7: 0.2736 | K7: 0.4 | L7: 40913 | M7: 40928
A8: 신규 | B8: 40926 | C8: 달성공단영업부 | D8: 조창호 | E8: 이관수 | F8: USD | G8: 1000000 | H8: 외화정기예금 | I8: 1.2643 | J8: 0.0357 | K8: 1.3 | L8: 40926 | M8: 41108
A9: 신규 | B9: 40980 | C9: 경산공단영업부 | D9: 이상근 | E9: 에스엘㈜ | F9: USD | G9: 5000000 | H9: 외화정기예금 | I9: 0.7215 | J9: 0.4785 | K9: 1.2 | L9: 40980 | M9: 41072
A10: 신규 | B10: 41016 | C10: 내당동지점 | D10: 박미정 | E10: 이재형 | F10: USD | G10: 1805178.3 | H10: 외화정기예금 | I10: 1.358 | J10: 0.2 | K10: 1.558 | L10: 41016 | M10: 41380
A11: 신규 | B11: 41072 | C11: 강남영업부 | D11: 문명숙 | E11: ㈜팬택 | F11: USD | G11: 5000000 | H11: 외화정기예금 | I11: 0.1128 | J11: 0.1 | K11: 0.2128 | L11: 41072 | M11: 41082
A12: 신규 | B12: 41072 | C12: 경산공단영업부 | D12: 신제열 | E12: 에스엘㈜ | F12: USD | G12: 5000000 | H12: 외화정기예금 | I12: 0.7 | J12: 0.2 | K12: 0.9 | L12: 41072 | M12: 41164
A13: 신규 | B13: 41088 | C13: 강남영업부 | D13: 문명숙 | E13: ㈜팬택 | F13: USD | G13: 3000000 | H13: 외화정기예금 | I13: 0.1151 | J13: 0.1 | K13: 0.2151 | L13: 41088 | M13: 41095
A14: 신규 | B14: 41095 | C14: 강남영업부 | D14: 문명숙 | E14: ㈜팬택 | F14: USD | G14: 3000000 | H14: 외화정기예금 | I14: 0.1193 | J14: 0.1 | K14: 0.2193 | L14: 41095 | M14: 41102
A15: 신규 | B15: 40926 | C15: 달성공단영업부 | D15: 조창호 | E15: 이관수 | F15: USD | G15: 1000000 | H15: 외화정기예금 | I15: 1.2013 | J15: =K15-I15 -> 0.0387 | K15: 1.24 | L15: 41108 | M15: 41292
